Workbook

Sheet Biodata
A2: Citi-Nati Supermarket
A4: Employee List
A6: Pay Incremental Factor (based on Unitterupted Service
A7: 1 to 6 months in service | C7: 0
A8: 6 months to 1 year in service | C8: 0
A9: 1 year to 5 years in service | C9: 0
A10: 5 years and above in service | C10: 0
A12: Management Team
A14: Emp No. | B14: First Name | C14: Surname | D14: Agreed Salary per Month | E14: Annual Increment | F14: Salary after Increment | G14: Date of Birth | H14: District of Origin | I14: Village | J14: Traditional Authority | K14: National Identification Card | L14: Expiry Date | M14: Date of Employment | N14: Contact Number | P14: 1 | Q14: Daniel Mponda | S14: 60000
A15: CITI01 | B15: Sapulene | C15: Mkulichi | D15: 0 | E15: =IF(Wages!R162="vacant",0,IF(Wages!R162/30<6,0,IF(Wages!R162/30<12,D15*$C$8/100,IF(Wages!R162/30<60,D15*$C$9/100,IF(Wages!R162/30>59,D15*$C$10/100,""))))) -> 0 | F15: =IF(B15="vacant",0,D15+E15) -> 0 | G15: 24438 | H15: Zomba | I15: Chikwekwe | J15: Mulumbe | K15: K7Q3TYCY | L15: 44892 | M15: 35799 | N15: 0999953442 | P15: =+P14+1 -> 2 | Q15: Martin Kandalama | S15: 70000
A16: CITI02 | B16: George | C16: Matemba | D16: 120000 | E16: =IF(Wages!R163="vacant",0,IF(Wages!R163/30<6,0,IF(Wages!R163/30<12,D16*$C$8/100,IF(Wages!R163/30<60,D16*$C$9/100,IF(Wages!R163/30>59,D16*$C$10/100,""))))) -> 0 | F16: =IF(B16="vacant",0,D16+E16) -> 120000 | G16: 32946 | H16: Zomba | I16: Chikwekwe | J16: Mulumbe | K16: SX5E2R90 | L16: 45730 | M16: 41630 | N16: 0888109501 | P16: =+P15+1 -> 3 | Q16: Elizabeth Kabudula | S16: 30000
A17: CITI03 | B17: vacant | D17: 100000 | E17: =IF(Wages!R164="vacant",0,IF(Wages!R164/30<6,0,IF(Wages!R164/30<12,D17*$C$8/100,IF(Wages!R164/30<60,D17*$C$9/100,IF(Wages!R164/30>59,D17*$C$10/100,""))))) -> 0 | F17: =IF(B17="vacant",0,D17+E17) -> 0 | G17: 27/06/2000 | H17: Blantyre | I17: Kunjawa | J17: Kapeni | K17: 00JPEBYO | L17: 27/06/2026 | M17: 45386 | N17: 0995261886 | P17: =+P16+1 -> 4 | Q17: Henry Saona | S17: 150000
P18: =+P17+1 -> 5 | Q18: James Bongwe | S18: 100000
A19: Domasi Supermarket Employees | P19: =+P18+1 -> 6 | Q19: Yankho Gulani | S19: 100000
Q20: Sub-Total | S20: =SUM(S14:S19) -> 510000
A21: Emp No. | B21: First Name | C21: Surname | D21: Agreed Salary per Month | E21: Annual Increment | F21: Salary after Increment | G21: Date of Birth | H21: District of Origin | I21: Village | J21: Traditional Authority | K21: National Identification Card | L21: Expiry Date | M21: Date of Employment | N21: =N14 -> Contact Number
A22: CITI04 | B22: Alinafe | C22: James | D22: 80000 | E22: =IF(Wages!R165="vacant",0,IF(Wages!R165/30<6,0,IF(Wages!R165/30<12,D22*$C$8/100,IF(Wages!R165/30<60,D22*$C$9/100,IF(Wages!R165/30>59,D22*$C$10/100,""))))) -> 0 | F22: =IF(B22="vacant",0,D22+E22) -> 80000 | G22: 44139 | H22: Zomba | I22: Malonje | J22: Malemia | K22: TS62TH8A | L22: 20/10/2032 | M22: 44854 | N22: 0888529172/0995826404 | Q22: Citi-Nati Supermarkets, Resturant and Stop Over
A23: CITI05 | B23: Chimwemwe | C23: Banda | D23: 80000 | E23: =IF(Wages!R166="vacant",0,IF(Wages!R166/30<6,0,IF(Wages!R166/30<12,D23*$C$8/100,IF(Wages!R166/30<60,D23*$C$9/100,IF(Wages!R166/30>59,D23*$C$10/100,""))))) -> 0 | F23: =IF(B23="vacant",0,D23+E23) -> 80000 | G23: 22/04/1998 | H23: Blantyre | I23: Puna | J23: Machinjiri | M23: 45204 | P23: 1 | Q23: George Matemba | S23: 140000
A24: CITI06 | B24: vacant | D24: 0 | E24: =IF(Wages!R167="vacant",0,IF(Wages!R167/30<6,0,IF(Wages!R167/30<12,D24*$C$8/100,IF(Wages!R167/30<60,D24*$C$9/100,IF(Wages!R167/30>59,D24*$C$10/100,""))))) -> 0 | F24: =IF(B24="vacant",0,D24+E24) -> 0 | G24: 31/07/2000 | H24: Ntcheu | I24: Jenya | J24: Mphambala | K24: OONSKXV4 | L24: 31/07/2026 | M24: 45488 | N24: 0991231359 | P24: =P23+1 -> 2 | Q24: Alinafe James | S24: 0
A25: CITI07 | B25: Maureen | C25: Ulaya | D25: =+S38 -> 80000 | E25: =IF(Wages!R159="vacant",0,IF(Wages!R159/30<6,0,IF(Wages!R159/30<12,D25*$C$8/100,IF(Wages!R159/30<60,D25*$C$9/100,IF(Wages!R159/30>59,D25*$C$10/100,""))))) -> 0 | F25: =IF(B25="vacant",0,D25+E25) -> 80000 | M25: 45809 | N25: 0995337862 | P25: =P24+1 -> 3 | Q25: Francis Nebert | S25: 0
A26: CITI08 | B26: Francis | C26: Chatsweka | D26: 70000 | E26: =IF(Wages!R169="vacant",0,IF(Wages!R169/30<6,0,IF(Wages!R169/30<12,D26*$C$8/100,IF(Wages!R169/30<60,D26*$C$9/100,IF(Wages!R169/30>59,D26*$C$10/100,""))))) -> 0 | F26: =IF(B26="vacant",0,D26+E26) -> 70000 | G26: 32972 | H26: Zomba | I26: Yoyola | J26: Malemia | K26: T711G2DS | L26: 46121 | M26: 45241 | P26: =P25+1 -> 4 | Q26: Chimwemwe Banda | S26: 70000
A27: CITI09 | B27: Stenala | C27: Mponda | D27: 70000 | E27: =IF(Wages!R170="vacant",0,IF(Wages!R170/30<6,0,IF(Wages!R170/30<12,D27*$C$8/100,IF(Wages!R170/30<60,D27*$C$9/100,IF(Wages!R170/30>59,D27*$C$10/100,""))))) -> 0 | F27: =IF(B27="vacant",0,D27+E27) -> 70000 | G27: 26/04/1980 | H27: Machinga | I27: Mkwanda | J27: Ngokwe | K27: Q9EJ6EJD | L27: 26/04/2026 | M27: 45533 | N27: 0997793088 | P27: =P26+1 -> 5 | Q27: Francis Chatsweka | S27: 60000
A28: CITI10 | B28: Simikizani | C28: Siki | D28: 70000 | E28: =IF(Wages!R171="vacant",0,IF(Wages!R171/30<6,0,IF(Wages!R171/30<12,D28*$C$8/100,IF(Wages!R171/30<60,D28*$C$9/100,IF(Wages!R171/30>59,D28*$C$10/100,""))))) -> 0 | F28: =IF(B28="vacant",0,D28+E28) -> 70000 | M28: 45163 | P28: =P27+1 -> 6 | Q28: Stenala Mponda | S28: 60000
A29: CITI11 | B29: Amini | C29: Wecha | D29: 70000 | E29: =IF(Wages!R172="vacant",0,IF(Wages!R172/30<6,0,IF(Wages!R172/30<12,D29*$C$8/100,IF(Wages!R172/30<60,D29*$C$9/100,IF(Wages!R172/30>59,D29*$C$10/100,""))))) -> 0 | F29: =IF(B29="vacant",0,D29+E29) -> 70000 | M29: 45838 | P29: =P28+1 -> 7 | Q29: Simikizani Siki | S29: 60000
P30: =P29+1 -> 8 | Q30: Tayifolo Mandowa | S30: 120000
P31: =P30+1 -> 9 | Q31: Monica George | S31: 80000
A32: Stop Over Employees | P32: =P31+1 -> 10 | Q32: Madalitso Baluti | S32: 90000
P33: =P32+1 -> 11 | Q33: Peter James | S33: 60000
A34: Emp No. | B34: First Name | C34: Surname | D34: Agreed Salary per Month | E34: Annual Increment | F34: Salary after Increment | G34: Date of Birth | H34: District of Origin | I34: Village | J34: Traditional Authority | K34: National Identification Card | L34: Expiry Date | M34: Date of Employment | N34: =N21 -> Contact Number | P34: =P33+1 -> 12 | Q34: Maggie Billy | S34: 60000
A35: CITI12 | B35: Tayifolo | C35: Mandowa | D35: =+S30 -> 120000 | E35: =IF(Wages!R173="vacant",0,IF(Wages!R173/30<6,0,IF(Wages!R173/30<12,D35*$C$8/100,IF(Wages!R173/30<60,D35*$C$9/100,IF(Wages!R173/30>59,D35*$C$10/100,""))))) -> 0 | F35: =IF(B35="vacant",0,D35+E35) -> 120000 | G35: 26/04/1980 | H35: Machinga | I35: Mkwanda | J35: Ngokwe | K35: Q9EJ6EJD | L35: 26/04/2026 | M35: 45533 | N35: 0997793088 | P35: =P34+1 -> 13 | Q35: Amini Wecha | S35: 60000
A36: CITI13 | B36: Monica | C36: George | D36: =+S31 -> 80000 | E36: =IF(Wages!R174="vacant",0,IF(Wages!R174/30<6,0,IF(Wages!R174/30<12,D36*$C$8/100,IF(Wages!R174/30<60,D36*$C$9/100,IF(Wages!R174/30>59,D36*$C$10/100,""))))) -> 0 | F36: =IF(B36="vacant",0,D36+E36) -> 80000 | G36: 16/04/1997 | H36: Machinga | I36: Kagwa | J36: Liwonde | M36: 45385 | N36: 0882689123 | P36: =P35+1 -> 14 | Q36: Agness Mponda | S36: =Biodata!S70 -> 0
A37: CITI14 | B37: Madalitso | C37: Baluti | D37: =+S32 -> 90000 | E37: =IF(Wages!R175="vacant",0,IF(Wages!R175/30<6,0,IF(Wages!R175/30<12,D37*$C$8/100,IF(Wages!R175/30<60,D37*$C$9/100,IF(Wages!R175/30>59,D37*$C$10/100,""))))) -> 0 | F37: =IF(B37="vacant",0,D37+E37) -> 90000 | G37: 16/03/1998 | H37: Zomba | I37: Makuwira | J37: Makuwira | M37: 45663 | P37: =P36+1 -> 15 | Q37: Elizabeth Chinkono | S37: 100000
P38: =P37+1 -> 16 | Q38: Maureen Ulaya | S38: 80000
P39: =P38+1 -> 17 | Q39: Leonard Stephano | S39: =Biodata!S72 -> 0
A40: Restaurant Employees | P40: =P39+1 -> 18 | Q40: Ibrahim Amadu | S40: 80000
A42: Emp No. | B42: First Name | C42: Surname | D42: Agreed Salary per Month | E42: Annual Increment | F42: Salary after Increment | G42: Date of Birth | H42: District of Origin | I42: Village | J42: Traditional Authority | K42: National Identification Card | L42: Expiry Date | M42: Date of Employment | N42: =N34 -> Contact Number
A43: CITI15 | B43: Peter | C43: James | D43: =+S33 -> 60000 | E43: =IF(Wages!R176="vacant",0,IF(Wages!R176/30<6,0,IF(Wages!R176/30<12,D43*$C$8/100,IF(Wages!R176/30<60,D43*$C$9/100,IF(Wages!R176/30>59,D43*$C$10/100,""))))) -> 0 | F43: =IF(B43="vacant",0,D43+E43) -> 60000 | G43: 16/03/2000 | H43: Zomba | I43: Saidi | J43: Mwambo | M43: 45558
A44: CITI16 | B44: Maggie | C44: Billy | D44: 80000 | E44: =IF(Wages!R177="vacant",0,IF(Wages!R177/30<6,0,IF(Wages!R177/30<12,D44*$C$8/100,IF(Wages!R177/30<60,D44*$C$9/100,IF(Wages!R177/30>59,D44*$C$10/100,""))))) -> 0 | F44: =IF(B44="vacant",0,D44+E44) -> 80000 | G44: 17/06/2000 | H44: Zomba | I44: Sani | J44: Chikowi | M44: 45421
A45: CITI17 | B45: vacant | E45: =IF(Wages!R178="vacant",0,IF(Wages!R178/30<6,0,IF(Wages!R178/30<12,D45*$C$8/100,IF(Wages!R178/30<60,D45*$C$9/100,IF(Wages!R178/30>59,D45*$C$10/100,""))))) -> 0 | F45: =IF(B45="vacant",0,D45+E45) -> 0 | M45: 43665
A46: CITI18 | B46: Esnat | C46: Adam | D46: 80000 | E46: =IF(Wages!R179="vacant",0,IF(Wages!R179/30<6,0,IF(Wages!R179/30<12,D46*$C$8/100,IF(Wages!R179/30<60,D46*$C$9/100,IF(Wages!R179/30>59,D46*$C$10/100,""))))) -> 0 | F46: =IF(B46="vacant",0,D46+E46) -> 80000 | G46: 36157 | H46: Zomba | I46: Potani | J46: Mlumbe | K46: WHTVMCR | L46: 12781 | M46: 45901 | N46: 09
A50: Domasi Residence
A52: Emp No. | B52: First Name | C52: Surname | D52: Agreed Salary per Month | E52: Annual Increment | F52: Salary after Increment | G52: Date of Birth | H52: District of Origin | I52: Village | J52: Traditional Authority | K52: National Identification Card | L52: Expiry Date | M52: Date of Employment | N52: =N42 -> Contact Number
A53: CITI19 | B53: Martin | C53: Kandalama | D53: =+S15 -> 70000 | E53: =IF(Wages!R180="vacant",0,IF(Wages!R180/30<6,0,IF(Wages!R180/30<12,D53*$C$8/100,IF(Wages!R180/30<60,D53*$C$9/100,IF(Wages!R180/30>59,D53*$C$10/100,""))))) -> 0 | F53: =IF(B53="vacant",0,D53+E53) -> 70000 | G53: 26/09/1987 | H53: Zomba | I53: Nambwari | J53: Mwambo | K53: SB3M7TDV | L53: 45195 | M53: 45870
A54: CITI20 | B54: Daniel | C54: Mponda | D54: 70000 | E54: =IF(Wages!R181="vacant",0,IF(Wages!R181/30<6,0,IF(Wages!R181/30<12,D54*$C$8/100,IF(Wages!R181/30<60,D54*$C$9/100,IF(Wages!R181/30>59,D54*$C$10/100,""))))) -> 0 | F54: =IF(B54="vacant",0,D54+E54) -> 70000 | G54: 15/08/1975 | H54: Zomba | I54: Chimbalanga | J54: Chikowi | K54: NV81FF18 | L54: 15/08/2026 | M54: 45658
A55: CITI21 | B55: Elizabeth | C55: Kabudula | D55: 20000 | E55: =IF(Wages!R182="vacant",0,IF(Wages!R182/30<6,0,IF(Wages!R182/30<12,D55*$C$8/100,IF(Wages!R182/30<60,D55*$C$9/100,IF(Wages!R182/30>59,D55*$C$10/100,""))))) -> 0 | F55: =IF(B55="vacant",0,D55+E55) -> 20000 | M55: 45870
A56: CITI22 | B56: vacant | D56: 0 | E56: =IF(Wages!R183="vacant",0,IF(Wages!R183/30<6,0,IF(Wages!R183/30<12,D56*$C$8/100,IF(Wages!R183/30<60,D56*$C$9/100,IF(Wages!R183/30>59,D56*$C$10/100,""))))) -> 0 | F56: =IF(B56="vacant",0,D56+E56) -> 0
A59: Nyambadwe Residence
A61: Emp No. | B61: First Name | C61: Surname | D61: Agreed Salary per Month | E61: Annual Increment | F61: Salary after Increment | G61: Date of Birth | H61: District of Origin | I61: Village | J61: Traditional Authority | K61: National Identification Card | L61: Expiry Date | M61: Date of Employment | N61: =N52 -> Contact Number
A62: CITI23 | B62: William | C62: Mahinya | D62: 150000 | E62: =IF(Wages!R184="vacant",0,IF(Wages!R184/30<6,0,IF(Wages!R184/30<12,D62*$C$8/100,IF(Wages!R184/30<60,D62*$C$9/100,IF(Wages!R184/30>59,D62*$C$10/100,""))))) -> 0 | F62: =IF(B62="vacant",0,D62+E62) -> 150000 | H62: Balaka | I62: Mitochi | J62: Nsamala | M62: 45962 | N62: 0886690519/0992121795 | O62: 987138556 | P62: for sister 0883457788/0991213410/0894554196 | T62: uncle 0884147135
A63: CITI24 | B63: vacant | D63: 0 | E63: =IF(Wages!R185="vacant",0,IF(Wages!R185/30<6,0,IF(Wages!R185/30<12,D63*$C$8/100,IF(Wages!R185/30<60,D63*$C$9/100,IF(Wages!R185/30>59,D63*$C$10/100,""))))) -> 0 | F63: =IF(B63="vacant",0,D63+E63) -> 0 | G63: 36949 | H63: Thyolo | I63: Kachingwe | J63: Nanseta | M63: 45715 | N63: 0886851058/0985279327
A64: CITI25 | D64: 0 | E64: =IF(Wages!R186="vacant",0,IF(Wages!R186/30<6,0,IF(Wages!R186/30<12,D64*$C$8/100,IF(Wages!R186/30<60,D64*$C$9/100,IF(Wages!R186/30>59,D64*$C$10/100,""))))) -> 0 | F64: =IF(B64="vacant",0,D64+E64) -> 0 | H64: Blantyre | I64: Kunjawa | J64: Kapeni | K64: WT6WTBTA | M64: 45386 | N64: 0884821149
A65: CITI26 | B65: vacant | D65: 0 | E65: =IF(Wages!R187="vacant",0,IF(Wages!R187/30<6,0,IF(Wages!R187/30<12,D65*$C$8/100,IF(Wages!R187/30<60,D65*$C$9/100,IF(Wages!R187/30>59,D65*$C$10/100,""))))) -> 0 | F65: =IF(B65="vacant",0,D65+E65) -> 0 | G65: 31711 | H65: Thyolo | I65: Sumbuleta | J65: Mchiramwera | K65: S1WHXEW6 | L65: 44859 | M65: 45694 | N65: 0982802591
A66: CITI27 | B66: Yankho | C66: Gulani | D66: 120000 | E66: =IF(Wages!R200="vacant",0,IF(Wages!R200/30<6,0,IF(Wages!R200/30<12,D66*$C$8/100,IF(Wages!R200/30<60,D66*$C$9/100,IF(Wages!R200/30>59,D66*$C$10/100,""))))) -> 0 | F66: =IF(B66="vacant",0,D66+E66) -> 120000 | G66: 1993 | H66: Thyolo | I66: Chafa | J66: Changata | M66: 45481 | N66: 0984448357
A70: Chinyonga Supermarket Employees
A72: Emp No. | B72: First Name | C72: Surname | D72: Agreed Salary per Month | E72: Annual Increment | F72: Salary after Increment | G72: Date of Birth | H72: District of Origin | I72: Village | J72: Traditional Authority | K72: National Identification Card | L72: Expiry Date | M72: Date of Employment | N72: Contact Number
A73: CITI28 | B73: Agness | C73: Mponda | D73: 80000 | E73: =IF(Wages!R207="vacant",0,IF(Wages!R207/30<6,0,IF(Wages!R207/30<12,D73*$C$8/100,IF(Wages!R207/30<60,D73*$C$9/100,IF(Wages!R207/30>59,D73*$C$10/100,""))))) -> 0 | F73: =IF(B73="vacant",0,D73+E73) -> 80000 | G73: 37475 | H73: Thyolo | K73: OKC34FAB | L73: 46972 | M73: 45853 | N73: 0990943701
A74: CITI29 | B74: Elizabeth | C74: Chinkono | D74: 100000 | E74: =IF(Wages!R208="vacant",0,IF(Wages!R208/30<6,0,IF(Wages!R208/30<12,D74*$C$8/100,IF(Wages!R208/30<60,D74*$C$9/100,IF(Wages!R208/30>59,D74*$C$10/100,""))))) -> 0 | F74: =IF(B74="vacant",0,D74+E74) -> 100000 | M74: 45890 | N74: 0995337862
A75: CITI30 | B75: vacant | E75: =IF(Wages!R209="vacant",0,IF(Wages!R209/30<6,0,IF(Wages!R209/30<12,D75*$C$8/100,IF(Wages!R209/30<60,D75*$C$9/100,IF(Wages!R209/30>59,D75*$C$10/100,""))))) -> 0 | F75: =IF(B75="vacant",0,D75+E75) -> 0
A76: CITI30 | B76: Dancan | C76: Botha | D76: 94000 | E76: =IF(Wages!R210="vacant",0,IF(Wages!R210/30<6,0,IF(Wages!R210/30<12,D76*$C$8/100,IF(Wages!R210/30<60,D76*$C$9/100,IF(Wages!R210/30>59,D76*$C$10/100,""))))) -> 0 | F76: =IF(B76="vacant",0,D76+E76) -> 94000 | G76: 26063 | K76: 0W88M5HT | L76: 47391 | M76: 45901 | N76: 0899779017
A77: CITI31 | B77: Ibrahim | C77: Amadu | D77: 80000 | E77: =IF(Wages!R211="vacant",0,IF(Wages!R211/30<6,0,IF(Wages!R211/30<12,D77*$C$8/100,IF(Wages!R211/30<60,D77*$C$9/100,IF(Wages!R211/30>59,D77*$C$10/100,""))))) -> 0 | F77: =IF(B77="vacant",0,D77+E77) -> 80000 | G77: 29809 | K77: QK423SPE | L77: 46610 | M77: 45839 | N77: 0982802591

Sheet Pay Sheet
A1: Citi-Nati Supermarket
B2: Enter Month to Pay Here--------------> | C2: 1
B3: Enter Position in Month to pay Here | C3: 1 | D3: (Enter 1 for mid, 2 for full month)
A5: Wages for Residences, Supermarket, Stop-Over and Restaurant
B7: ='Combined Pay'!B6 -> Month for Payment of Wages: | C7: ='Combined Pay'!C6 -> Mid | D7: ='Combined Pay'!D6 -> January 2026
A9: Total Wages Due | D9: =D21+D48 -> 967000
A11: Count | B11: Nyambadwe and Domasi Residence
A12: ='Combined Pay'!A13 -> 1 | B12: ='Combined Pay'!B13 -> Martin Kandalama | D12: ='Combined Pay'!D13 -> 35000
A13: =SUM(A12+1) -> 2 | B13: ='Combined Pay'!B14 -> Daniel Mponda | D13: ='Combined Pay'!D14 -> 35000
A14: =SUM(A13+1) -> 3 | B14: ='Combined Pay'!B15 -> Elizabeth Kabudula | D14: ='Combined Pay'!D15 -> 10000
A15: =A14+1 -> 4 | B15: ='Combined Pay'!B16 -> vacant | D15: ='Combined Pay'!D16 -> 0
A16: =A15+1 -> 5 | B16: ='Combined Pay'!B17 -> William Mahinya | D16: ='Combined Pay'!D17 -> 75000
A17: =A16+1 -> 6 | B17: ='Combined Pay'!B18 -> vacant | D17: ='Combined Pay'!D18 -> 0
A18: =A17+1 -> 7 | B18: ='Combined Pay'!B19 | D18: ='Combined Pay'!D19 -> 0
A19: =A18+1 -> 8 | B19: ='Combined Pay'!B20 -> vacant | D19: ='Combined Pay'!D20 -> 0
A20: =A19+1 -> 9 | B20: ='Combined Pay'!B21 -> Yankho Gulani | D20: ='Combined Pay'!D21 -> 60000
B21: ='Combined Pay'!B22 -> Sub-Total | D21: =SUM(D12:D20) -> 215000
A23: Count | B23: ='Combined Pay'!B24 -> Citi-Nati Supermarkets, Resturant and Stop Over
A24: 1 | B24: ='Combined Pay'!B25 -> Sapulene Mkulichi | D24: ='Combined Pay'!D25 -> 0
A25: =SUM(A24+1) -> 2 | B25: ='Combined Pay'!B26 -> George Matemba | D25: ='Combined Pay'!D26 -> 60000
A26: =SUM(A25+1) -> 3 | B26: ='Combined Pay'!B27 -> vacant | D26: ='Combined Pay'!D27 -> 0
A27: =SUM(A26+1) -> 4 | B27: ='Combined Pay'!B28 -> Alinafe James | D27: ='Combined Pay'!D28 -> 40000
A28: =SUM(A27+1) -> 5 | B28: ='Combined Pay'!B29 -> Chimwemwe Banda | D28: ='Combined Pay'!D29 -> 40000
A29: =SUM(A28+1) -> 6 | B29: ='Combined Pay'!B30 -> vacant | D29: ='Combined Pay'!D30 -> 0
A30: =SUM(A29+1) -> 7 | B30: ='Combined Pay'!B31 -> Maureen Ulaya | D30: ='Combined Pay'!D31 -> 40000
A31: =SUM(A30+1) -> 8 | B31: ='Combined Pay'!B32 -> Francis Chatsweka | D31: ='Combined Pay'!D32 -> 35000
A32: =SUM(A31+1) -> 9 | B32: ='Combined Pay'!B33 -> Stenala Mponda | D32: ='Combined Pay'!D33 -> 35000
A33: =SUM(A32+1) -> 10 | B33: ='Combined Pay'!B34 -> Simikizani Siki | D33: ='Combined Pay'!D34 -> 35000
A34: =SUM(A33+1) -> 11 | B34: ='Combined Pay'!B35 -> Amini Wecha | D34: ='Combined Pay'!D35 -> 35000
A35: =SUM(A34+1) -> 12 | B35: ='Combined Pay'!B36 -> Tayifolo Mandowa | D35: ='Combined Pay'!D36 -> 60000
A36: =SUM(A35+1) -> 13 | B36: ='Combined Pay'!B37 -> Monica George | D36: ='Combined Pay'!D37 -> 40000
... A46: =SUM(A45+1) -> 23 | B46: ='Combined Pay'!B47 -> Ibrahim Amadu | D46: ='Combined Pay'!D47 -> 40000
B48: ='Combined Pay'!B49 -> Sub-Total | D48: =SUM(D24:D46) -> 752000
D50: Amounts Due
B51: Management Employees | D51: =Wages!R257 -> 120000
B52: Domasi Supermarket Employees | D52: =Wages!R258 -> 520000
B53: Stop-Over Employees | D53: =Wages!R259 -> 290000
B54: Restuarant Employees | D54: =Wages!R260 -> 220000
B55: Domasi Residence Employees | D55: =Wages!R261 -> 160000
B56: Nyambadwe Residence Employees | D56: =Wages!R262 -> 270000
B57: Chinyonga Supermarket Employees | D57: =Wages!R263 -> 354000
B58: Total Wages to Pay Entire Month | D58: =SUM(D51:D57) -> 1934000

Sheet Final
A1: Citi-Nati Supermarket
A3: Wages for Residences, Supermarket, Stop-Over and Restaurant
B5: ='Combined Pay'!B6 -> Month for Payment of Wages: | C5: ='Combined Pay'!C6 -> Mid | D5: ='Combined Pay'!D6 -> January 2026
A7: Total Wages Due | D7: =D15+D36 -> 967000
A9: Count | B9: Nyambadwe and Domasi Residence
A10: 1 | B10: ='Pay Sheet'!B12 -> Martin Kandalama | D10: =+'Pay Sheet'!D12 -> 35000
A11: =SUM(A10+1) -> 2 | B11: ='Pay Sheet'!B13 -> Daniel Mponda | D11: =+'Pay Sheet'!D13 -> 35000
A12: =SUM(A11+1) -> 3 | B12: ='Pay Sheet'!B14 -> Elizabeth Kabudula | D12: =+'Pay Sheet'!D14 -> 10000
A13: =SUM(A12+1) -> 4 | B13: ='Pay Sheet'!B20 -> Yankho Gulani | D13: =+'Pay Sheet'!D20 -> 60000
A14: =SUM(A13+1) -> 5 | B14: ='Pay Sheet'!B16 -> William Mahinya | D14: ='Pay Sheet'!D16 -> 75000
B15: ='Pay Sheet'!B21 -> Sub-Total | D15: =SUM(D10:D14) -> 215000
B17: ='Pay Sheet'!B23 -> Citi-Nati Supermarkets, Resturant and Stop Over
A18: 1 | B18: ='Pay Sheet'!B25 -> George Matemba | D18: =+'Pay Sheet'!D25 -> 60000
A19: =+A18+1 -> 2 | B19: ='Pay Sheet'!B27 -> Alinafe James | D19: =+'Pay Sheet'!D27 -> 40000
A20: =+A19+1 -> 3 | B20: ='Pay Sheet'!B28 -> Chimwemwe Banda | D20: =+'Pay Sheet'!D28 -> 40000
A21: =+A20+1 -> 4 | B21: ='Pay Sheet'!B30 -> Maureen Ulaya | D21: =+'Pay Sheet'!D30 -> 40000
A22: =+A21+1 -> 5 | B22: ='Pay Sheet'!B31 -> Francis Chatsweka | D22: =+'Pay Sheet'!D31 -> 35000 | F22: =+'Pay Sheet'!D9-Final!D7 -> 0
A23: =+A22+1 -> 6 | B23: ='Pay Sheet'!B32 -> Stenala Mponda | D23: =+'Pay Sheet'!D32 -> 35000
A24: =+A23+1 -> 7 | B24: ='Pay Sheet'!B33 -> Simikizani Siki | D24: =+'Pay Sheet'!D33 -> 35000
A25: =+A24+1 -> 8 | B25: ='Pay Sheet'!B34 -> Amini Wecha | D25: =+'Pay Sheet'!D34 -> 35000
A26: =+A25+1 -> 9 | B26: ='Pay Sheet'!B35 -> Tayifolo Mandowa | D26: =+'Pay Sheet'!D35 -> 60000
A27: =+A26+1 -> 10 | B27: ='Pay Sheet'!B36 -> Monica George | D27: =+'Pay Sheet'!D36 -> 40000
A28: =+A27+1 -> 11 | B28: ='Pay Sheet'!B37 -> Madalitso Baluti | D28: =+'Pay Sheet'!D37 -> 45000
A29: =+A28+1 -> 12 | B29: ='Pay Sheet'!B38 -> Peter James | D29: =+'Pay Sheet'!D38 -> 30000
A30: =+A29+1 -> 13 | B30: ='Pay Sheet'!B39 -> Maggie Billy | D30: =+'Pay Sheet'!D39 -> 40000
A31: =+A30+1 -> 14 | B31: ='Pay Sheet'!B41 -> Esnat Adam | D31: =+'Pay Sheet'!D41 -> 40000
A32: =+A31+1 -> 15 | B32: ='Pay Sheet'!B42 -> Agness Mponda | D32: =+'Pay Sheet'!D42 -> 40000
A33: =+A32+1 -> 16 | B33: ='Pay Sheet'!B43 -> Elizabeth Chinkono | D33: =+'Pay Sheet'!D43 -> 50000
A34: =+A33+1 -> 17 | B34: ='Pay Sheet'!B45 -> Dancan Botha | D34: =+'Pay Sheet'!D45 -> 47000
A35: =+A34+1 -> 18 | B35: ='Pay Sheet'!B46 -> Ibrahim Amadu | D35: =+'Pay Sheet'!D46 -> 40000
B36: ='Pay Sheet'!B48 -> Sub-Total | D36: =SUM(D18:D35) -> 752000
D39: =+'Pay Sheet'!D50 -> Amounts Due
B40: =+'Pay Sheet'!B51 -> Management Employees | D40: =+'Pay Sheet'!D51 -> 120000
B41: =+'Pay Sheet'!B52 -> Domasi Supermarket Employees | D41: =+'Pay Sheet'!D52 -> 520000
B42: =+'Pay Sheet'!B53 -> Stop-Over Employees | D42: =+'Pay Sheet'!D53 -> 290000
B43: =+'Pay Sheet'!B54 -> Restuarant Employees | D43: =+'Pay Sheet'!D54 -> 220000
B44: =+'Pay Sheet'!B55 -> Domasi Residence Employees | D44: =+'Pay Sheet'!D55 -> 160000
B45: =+'Pay Sheet'!B56 -> Nyambadwe Residence Employees | D45: =+'Pay Sheet'!D56 -> 270000
B46: =+'Pay Sheet'!B57 -> Chinyonga Supermarket Employees | D46: =+'Pay Sheet'!D57 -> 354000
B47: =+'Pay Sheet'!B58 -> Total Wages to Pay Entire Month | D47: =+'Pay Sheet'!D58 -> 1934000

Sheet Terminations
A1: Citi-Nati Supermarket
A5: =Wages!K216 -> Termination of Contract Calculations
A6: Enter Employee to Terminate Contract | B6: james
A7: Enter Date of Termination | B7: 45626
A8: Enter Reason to Terminate Contract | B8: 2 | C8: (Enter 1 for termination or 2 for resignation)
A9: Enter Days Worked During the Month of Termination | B9: 0
A10: Did Employee Received Half Pay Wage? | B10: 0 | C10: (enter 1 if yes or 0 if no)
A11: Total amount due after Termination | B11: =Wages!G241 -> Not applicable
A12: Total Amount due after Resignation/Dismissal | B12: =Wages!G277 -> Nil
A14: =Wages!A216 -> Employer Induced Termination
A15: =Wages!A219 -> Name of Employee: | B15: =Wages!F219 -> Not Applicable
A17: =Wages!A221 -> Date Contract Terminated | B17: =Wages!G221 -> Not applicable
A18: =Wages!A223 -> Payslip for end of Contract | B18: =Wages!G223 -> Not applicable
A19: =Wages!A225 -> Number of Months Worked Continously | B19: =Wages!G225 -> Not applicable
A20: =Wages!A227 -> Gratuity at 5% of the last salary mutiplied by Number of Months of Uninterrupted Employment | B20: =Wages!G227 -> Not applicable
A21: =Wages!A229 -> Accrued Leave Days in Number of Months Worked Continuously | B21: =Wages!G229 -> Not applicable
A22: =Wages!A231 -> Leave Pay on Accrued Leave Days | B22: =Wages!G231 -> Not applicable
A23: =Wages!A233 -> One Month Pay In Lieu of Notice | B23: =Wages!G233 -> Not applicable
A24: =Wages!A235 -> Total Gross Amount Due at End of Contract | B24: =Wages!G235 -> Not applicable
A25: =Wages!A237 -> Less Outstanding Loan Obligations | B25: =Wages!G237 -> Not applicable
A26: =Wages!A239 -> Less part-payment of Salary made during mid month of | B26: =IF(B10=1,Wages!G239,"Not applicable") -> Not applicable
A27: =Wages!A241 -> Total Net Amount Due at End of Contract | B27: =Wages!G241 -> Not applicable
A28: =Wages!A243 -> Employer's Signature Confirming Payment of the Net Amount Due Following End of Contract | B28: ------------------------------------------
A29: =Wages!A245 -> Employee's Signature agreeing to the amount due following end of Contract | B29: ------------------------------------------
A30: =Wages!A247 -> Date signed | B30: ------------------------------------------
A33: =Wages!A252 -> Employee Resignation/Dismissal
A34: =Wages!A255 -> Name of Employee: | B34: =Wages!F255 -> Employee does not exist
A36: =Wages!A257 -> Date Contract Terminated | B36: =Wages!G257 -> None
A37: =Wages!A259 -> Payslip for end of Contract | B37: =Wages!G259 -> None
A38: =Wages!A261 -> Number of Months Worked Continously | B38: =Wages!G261 -> Nil
A39: =Wages!A263 -> Number of days worked during month of resignation/dismissal | B39: =Wages!G263 -> Nil
A40: =Wages!A265 -> Salary for days worked during month of resignation/dismissal | B40: =Wages!G265 -> Nil
A41: =Wages!A267 -> One Month Pay In Lieu of Notice | B41: =Wages!G267 -> Nil
A42: =Wages!A269 -> Gratuity at 5% of the last salary mutiplied by Number of Months of Uninterrupted Employment | B42: =Wages!G269 -> Nil
A43: =Wages!A271 -> Total Gross Amount Due at End of Contract | B43: =Wages!G271 -> Nil
A44: =Wages!A273 -> Less Outstanding Loan Obligations | B44: =Wages!G273 -> Nil
A45: =Wages!A275 -> Less part-payment of Salary made during mid month of | B45: =IF(B10=1,Wages!G275,"Not applicable") -> Not applicable
A46: =Wages!A277 -> Total Net Amount Due at End of Contract | B46: =Wages!G277 -> Nil
A47: =Wages!A279 -> Employer's Signature Confirming Payment of the Net Amount Due Following End of Contract | B47: ------------------------------------------
A48: =Wages!A281 -> Employee's Signature agreeing to the amount due following end of Contract | B48: ------------------------------------------
A49: =Wages!A283 -> Date signed | B49: ------------------------------------------

Sheet Wages
A2: Citi-Nati Supermarket | H2: Tax Rates WEF 1st April, 24
H3: 150000 | I3: 150001 | J3: 0 | K3: First
A4: Month to pay | C4: ='Pay Sheet'!C2 -> 1 | E4: Month Wages to Pay: | F4: =B$8 -> Mid | G4: =E18 -> January 2026 | H4: 350000 | I4: 350001 | J4: 0.25 | K4: Next | L4: =H4*J4 -> 87500
H5: 2050000 | I5: 2050001 | J5: 0.3 | K5: Next | L5: =H5*J5 -> 615000
A6: Position in month | C6: ='Pay Sheet'!C3 -> 1 | D6: 1 for mid, 2 for full month | H6: 2550000 | I6: 0 | J6: 0.35 | K6: Next
B8: =IF(C6=1,"Mid",IF(C6=2,"End","wrong entry")) -> Mid
B9: =IF(C4<9,E18,IF(C4=9,LoanSchedule!D67,IF(C4=10,LoanSchedule!D68,IF(C4=11,LoanSchedule!D69,IF(C4=12,LoanSchedule!D70,"wrong month"))))) -> January 2026 | C9: NB: for loans, overtime, days absent or termination of contracts, go to cells L141, C141 or K184 after the payslips
A11: 1 | B11: <---- position in month | G11: Half Pay | I11: Full Pay
E12: Total P.A.Y.E | G12: =I12/2 -> 0 | I12: =E203 -> 0
D13: Total wages to pay net of P.A.Y.E: | G13: =I13/2 -> 967000 | I13: =E207 -> 1934000
C15: Citi-Nati Shopping Centre | G15: Citi-Nati Shopping Centre | K15: Citi-Nati Shopping Centre | O15: Citi-Nati Shopping Centre
C16: Name of Employee: | D16: =CONCATENATE(+Biodata!B15,+" ",+Biodata!C15) -> Sapulene Mkulichi | G16: =C16 -> Name of Employee: | H16: =CONCATENATE(+Biodata!B16, +" ",+Biodata!C16) -> George Matemba | K16: Name of Employee: | L16: =CONCATENATE(+Biodata!B22,+" ",+Biodata!C22) -> Alinafe James | O16: Name of Employee: | P16: =CONCATENATE(+Biodata!B23,+" ",+Biodata!C23) -> Chimwemwe Banda
C17: Employee Number: | E17: =Biodata!A15 -> CITI01 | G17: Employee Number: | I17: =Biodata!A16 -> CITI02 | K17: Employee Number: | M17: =Biodata!A22 -> CITI04 | O17: Employee Number: | Q17: =Biodata!A23 -> CITI05
B18: =E18 -> January 2026 | C18: Payslip for the Month: | E18: =+IF(C4=1,LoanSchedule!D59,IF(C4=2,LoanSchedule!D60,IF(C4=3,LoanSchedule!D61,IF(C4=4,LoanSchedule!D62,IF(C4=5,LoanSchedule!D63,IF(C4=6,LoanSchedule!D64,IF(C4=7,LoanSchedule!D65,IF(C4=8,LoanSchedule!D66,B9)))))))) -> January 2026 | G18: Payslip for the Month: | I18: =$B$18 -> January 2026 | K18: Payslip for the Month: | M18: =$B$18 -> January 2026 | O18: Payslip for the Month: | Q18: =$B$18 -> January 2026
C19: Gross Salary | E19: =LoanSchedule!C14 -> 0 | G19: Gross Salary | I19: =LoanSchedule!D14 -> 120000 | K19: Gross Salary | M19: =LoanSchedule!F14 -> 80000 | O19: Gross Salary | Q19: =LoanSchedule!G14 -> 80000
C20: Overtime Claim | E20: =LoanSchedule!C20 -> 0 | G20: Overtime Claim | I20: =LoanSchedule!D20 -> 0 | K20: Overtime Claim | M20: =LoanSchedule!F20 -> 0 | O20: Overtime Claim | Q20: =LoanSchedule!G20 -> 0
C21: P.A.Y.E | D21: =IF(AND(SUM(E19-$H$3)<$I$3,E19<$I$3),0,IF(AND(SUM(E19-$H$3)<$I$4,E19>$I$3),SUM((E19-$H$3)*$J$4),IF(AND(SUM(E19-$H$3)<$I$5,E19>$I$4),SUM($L$4+(E19-$H$3-$H$4)*$J$5),SUM($L$4+$L$5+(E19-$H$3-$H$4-$H$5)*$J$6)))) -> 0 | G21: =C21 -> P.A.Y.E | H21: =IF(AND(SUM(I19-$H$3)<$I$3,I19<$I$3),0,IF(AND(SUM(I19-$H$3)<$I$4,I19>$I$3),SUM((I19-$H$3)*$J$4),IF(AND(SUM(I19-$H$3)<$I$5,I19>$I$4),SUM($L$4+(I19-$H$3-$H$4)*$J$5),SUM($L$4+$L$5+(I19-$H$3-$H$4-$H$5)*$J$6)))) -> 0 | K21: =C93 -> P.A.Y.E | L21: =IF(AND(SUM(M19-$H$3)<$I$3,M19<$I$3),0,IF(AND(SUM(M19-$H$3)<$I$4,M19>$I$3),SUM((M19-$H$3)*$J$4),IF(AND(SUM(M19-$H$3)<$I$5,M19>$I$4),SUM($L$4+(M19-$H$3-$H$4)*$J$5),SUM($L$4+$L$5+(M19-$H$3-$H$4-$H$5)*$J$6)))) -> 0 | O21: =K21 -> P.A.Y.E | P21: =IF(AND(SUM(Q19-$H$3)<$I$3,Q19<$I$3),0,IF(AND(SUM(Q19-$H$3)<$I$4,Q19>$I$3),SUM((Q19-$H$3)*$J$4),IF(AND(SUM(Q19-$H$3)<$I$5,Q19>$I$4),SUM($L$4+(Q19-$H$3-$H$4)*$J$5),SUM($L$4+$L$5+(Q19-$H$3-$H$4-$H$5)*$J$6)))) -> 0
C22: Xmas Gift/Leave Pay | E22: =LoanSchedule!C27 -> 0 | G22: =C22 -> Xmas Gift/Leave Pay | I22: =LoanSchedule!D27 -> 0 | K22: =C94 -> Xmas Gift/Leave Pay | L22: 0 | M22: =LoanSchedule!F27 -> 0 | O22: =K22 -> Xmas Gift/Leave Pay | Q22: =LoanSchedule!G27 -> 0
C23: Medical Aid Scheme | G23: Medical Aid Scheme | K23: Medical Aid Scheme | O23: Medical Aid Scheme
C24: Loan Instalment | D24: =LoanSchedule!C55 -> 0 | G24: =C24 -> Loan Instalment | H24: =+LoanSchedule!D55 -> 0 | K24: =C96 -> Loan Instalment | L24: =LoanSchedule!F55 -> 0 | O24: =K24 -> Loan Instalment | P24: =LoanSchedule!G55 -> 0
C25: Absence Deduction | D25: =ROUNDDOWN(LoanSchedule!C23,1) -> 0 | G25: =C25 -> Absence Deduction | H25: =ROUNDDOWN(LoanSchedule!D23,1) -> 0 | K25: =C97 -> Absence Deduction | L25: =ROUNDDOWN(LoanSchedule!F23,1) -> 0 | O25: =K25 -> Absence Deduction | P25: =ROUNDDOWN(LoanSchedule!G23,1) -> 0
C26: Total Deductions | D26: =SUM(D21:D25) -> 0 | G26: =C26 -> Total Deductions | H26: =SUM(H21:H25) -> 0 | K26: =C26 -> Total Deductions | L26: =SUM(L21:L25) -> 0 | O26: =K26 -> Total Deductions | P26: =+P24+P25 -> 0
C27: Loan Balance | D27: =LoanSchedule!C54 -> 0 | G27: =C27 -> Loan Balance | H27: =LoanSchedule!D54 -> 0 | K27: =C99 -> Loan Balance | L27: =LoanSchedule!F54 -> 0 | O27: =K27 -> Loan Balance | P27: =LoanSchedule!G54 -> 0
C29: Net Pay for the Month | E29: =SUM(E19+E20+E22-D26) -> 0 | G29: Net Pay for the Month | I29: =SUM(I19+I20+I22-H26) -> 120000 | K29: Net Pay for the Month | M29: =SUM(M19+M20+M22-L26) -> 80000 | O29: Net Pay for the Month | Q29: =SUM(Q19+Q20+Q22-P26) -> 80000
C30: Net Pay mid and end of Month | E30: =E29/2 -> 0 | G30: =C30 -> Net Pay mid and end of Month | I30: =I29/2 -> 60000 | K30: =C30 -> Net Pay mid and end of Month | M30: =M29/2 -> 40000 | O30: =C30 -> Net Pay mid and end of Month | Q30: =Q29/2 -> 40000
C33: Citi-Nati Shopping Centre | G33: Citi-Nati Shopping Centre | K33: Citi-Nati Shopping Centre | O33: Citi-Nati Shopping Centre
C34: Name of Employee: | D34: =CONCATENATE(+Biodata!B24,+" ",+Biodata!C24) -> vacant | G34: =C34 -> Name of Employee: | H34: =CONCATENATE(+Biodata!B25,+" ",+Biodata!C25) -> Maureen Ulaya | K34: Name of Employee: | L34: =CONCATENATE(+Biodata!B26,+" ",+Biodata!C26) -> Francis Chatsweka | O34: Name of Employee: | P34: =CONCATENATE(+Biodata!B27,+" ",+Biodata!C27) -> Stenala Mponda
C35: Employee Number: | E35: =Biodata!A24 -> CITI06 | G35: Employee Number: | I35: =Biodata!A25 -> CITI07 | K35: Employee Number: | M35: =Biodata!A26 -> CITI08 | O35: Employee Number: | Q35: =Biodata!A27 -> CITI09
C36: Payslip for the Month: | E36: =$B$18 -> January 2026 | G36: Payslip for the Month: | I36: =$B$18 -> January 2026 | K36: Payslip for the Month: | M36: =$B$18 -> January 2026 | O36: Payslip for the Month: | Q36: =$B$18 -> January 2026
C37: Gross Salary | E37: =LoanSchedule!H14 -> 0 | G37: Gross Salary | I37: =LoanSchedule!I14 -> 80000 | K37: Gross Salary | M37: =LoanSchedule!J14 -> 70000 | O37: Gross Salary | Q37: =LoanSchedule!K14 -> 70000
C38: Overtime Claim | D38: 0 | E38: =LoanSchedule!H20 -> 0 | G38: Overtime Claim | I38: =LoanSchedule!I20 -> 0 | K38: Overtime Claim | M38: =LoanSchedule!J20 -> 0 | O38: Overtime Claim | Q38: =LoanSchedule!K20 -> 0
C39: P.A.Y.E | D39: =IF(AND(SUM(E37-$H$3)<$I$3,E37<$I$3),0,IF(AND(SUM(E37-$H$3)<$I$4,E37>$I$3),SUM((E37-$H$3)*$J$4),IF(AND(SUM(E37-$H$3)<$I$5,E37>$I$4),SUM($L$4+(E37-$H$3-$H$4)*$J$5),SUM($L$4+$L$5+(E37-$H$3-$H$4-$H$5)*$J$6)))) -> 0 | G39: =C39 -> P.A.Y.E | H39: =IF(AND(SUM(I37-$H$3)<$I$3,I37<$I$3),0,IF(AND(SUM(I37-$H$3)<$I$4,I37>$I$3),SUM((I37-$H$3)*$J$4),IF(AND(SUM(I37-$H$3)<$I$5,I37>$I$4),SUM($L$4+(I37-$H$3-$H$4)*$J$5),SUM($L$4+$L$5+(I37-$H$3-$H$4-$H$5)*$J$6)))) -> 0 | K39: =K21 -> P.A.Y.E | L39: =IF(AND(SUM(M37-$H$3)<$I$3,M37<$I$3),0,IF(AND(SUM(M37-$H$3)<$I$4,M37>$I$3),SUM((M37-$H$3)*$J$4),IF(AND(SUM(M37-$H$3)<$I$5,M37>$I$4),SUM($L$4+(M37-$H$3-$H$4)*$J$5),SUM($L$4+$L$5+(M37-$H$3-$H$4-$H$5)*$J$6)))) -> 0 | O39: =O21 -> P.A.Y.E | P39: =IF(AND(SUM(Q37-$H$3)<$I$3,Q37<$I$3),0,IF(AND(SUM(Q37-$H$3)<$I$4,Q37>$I$3),SUM((Q37-$H$3)*$J$4),IF(AND(SUM(Q37-$H$3)<$I$5,Q37>$I$4),SUM($L$4+(Q37-$H$3-$H$4)*$J$5),SUM($L$4+$L$5+(Q37-$H$3-$H$4-$H$5)*$J$6)))) -> 0
C40: Xmas Gift/Leave Pay | E40: =LoanSchedule!H27 -> 0 | G40: =C40 -> Xmas Gift/Leave Pay | I40: =LoanSchedule!I27 -> 0 | K40: =K22 -> Xmas Gift/Leave Pay | M40: =LoanSchedule!J27 -> 0 | O40: =K40 -> Xmas Gift/Leave Pay | Q40: =LoanSchedule!K27 -> 0
C41: Medical Aid Scheme | G41: Medical Aid Scheme | K41: Medical Aid Scheme | O41: Medical Aid Scheme
C42: Loan Instalment | D42: =LoanSchedule!H55 -> 0 | G42: =C42 -> Loan Instalment | H42: =LoanSchedule!I55 -> 0 | K42: =K24 -> Loan Instalment | L42: =LoanSchedule!J55 -> 0 | O42: =K42 -> Loan Instalment | P42: =LoanSchedule!K55 -> 0
C43: Absence Deduction | D43: =ROUNDDOWN(LoanSchedule!H23,1) -> 0 | G43: =C43 -> Absence Deduction | H43: =ROUNDDOWN(LoanSchedule!I23,1) -> 0 | K43: =K25 -> Absence Deduction | L43: =ROUNDDOWN(LoanSchedule!J23,1) -> 0 | O43: =K43 -> Absence Deduction | P43: =ROUNDDOWN(LoanSchedule!K23,1) -> 0
C44: Total Deductions | D44: =SUM(D39:D43) -> 0 | G44: =G26 -> Total Deductions | H44: =SUM(H39:H43) -> 0 | K44: =K26 -> Total Deductions | L44: =SUM(L39:L43) -> 0 | O44: =K44 -> Total Deductions | P44: =+P42+P43 -> 0
C45: Loan Balance | D45: =LoanSchedule!H54 -> 0 | G45: =C45 -> Loan Balance | H45: =LoanSchedule!I54 -> 0 | K45: =K27 -> Loan Balance | L45: =LoanSchedule!J54 -> 0 | O45: =K45 -> Loan Balance | P45: =LoanSchedule!K54 -> 0
C47: Net Pay for the Month | E47: =SUM(E37+E38+E40-D44) -> 0 | G47: Net Pay for the Month | I47: =SUM(I37+I38+I40-H44) -> 80000 | K47: Net Pay for the Month | M47: =SUM(M37+M38+M40-L44) -> 70000 | O47: Net Pay for the Month | Q47: =SUM(Q37+Q38+Q40-P44) -> 70000
C48: Net Pay mid and end of Month | E48: =E47/2 -> 0 | G48: =C48 -> Net Pay mid and end of Month | I48: =I47/2 -> 40000 | K48: =C48 -> Net Pay mid and end of Month | M48: =M47/2 -> 35000 | O48: =C48 -> Net Pay mid and end of Month | Q48: =Q47/2 -> 35000
C51: Citi-Nati Shopping Centre | G51: Citi-Nati Shopping Centre | K51: Citi-Nati Shopping Centre | O51: Citi-Nati Shopping Centre
C52: Name of Employee: | D52: =CONCATENATE(+Biodata!B28,+" ",+Biodata!C28) -> Simikizani Siki | G52: Name of Employee: | H52: =CONCATENATE(+Biodata!B29,+" ",+Biodata!C29) -> Amini Wecha | K52: Name of Employee: | L52: =CONCATENATE(+Biodata!B35,+" ",+Biodata!C35) -> Tayifolo Mandowa | O52: Name of Employee: | P52: =CONCATENATE(+Biodata!B36,+" ",+Biodata!C36) -> Monica George
C53: Employee Number: | E53: =Biodata!A28 -> CITI10 | G53: Employee Number: | I53: =Biodata!A29 -> CITI11 | K53: Employee Number: | M53: =Biodata!A35 -> CITI12 | O53: Employee Number: | Q53: =Biodata!A36 -> CITI13
C54: Payslip for the Month: | E54: =$B$18 -> January 2026 | G54: Payslip for the Month: | I54: =$B$18 -> January 2026 | K54: Payslip for the Month: | M54: =$B$18 -> January 2026 | O54: Payslip for the Month: | Q54: =$B$18 -> January 2026
C55: Gross Salary | E55: =LoanSchedule!L14 -> 70000 | G55: Gross Salary | I55: =LoanSchedule!M14 -> 70000 | K55: Gross Salary | M55: =LoanSchedule!N14 -> 120000 | O55: Gross Salary | Q55: =LoanSchedule!O14 -> 80000
C56: Overtime Claim | E56: =LoanSchedule!L20 -> 0 | G56: Overtime Claim | I56: =LoanSchedule!M20 -> 0 | K56: Overtime Claim | M56: =LoanSchedule!N20 -> 0 | O56: Overtime Claim | Q56: =LoanSchedule!O20 -> 0
C57: P.A.Y.E | D57: =IF(AND(SUM(E55-$H$3)<$I$3,E55<$I$3),0,IF(AND(SUM(E55-$H$3)<$I$4,E55>$I$3),SUM((E55-$H$3)*$J$4),IF(AND(SUM(E55-$H$3)<$I$5,E55>$I$4),SUM($L$4+(E55-$H$3-$H$4)*$J$5),SUM($L$4+$L$5+(E55-$H$3-$H$4-$H$5)*$J$6)))) -> 0 | G57: =C57 -> P.A.Y.E | H57: =IF(AND(SUM(I55-$H$3)<$I$3,I55<$I$3),0,IF(AND(SUM(I55-$H$3)<$I$4,I55>$I$3),SUM((I55-$H$3)*$J$4),IF(AND(SUM(I55-$H$3)<$I$5,I55>$I$4),SUM($L$4+(I55-$H$3-$H$4)*$J$5),SUM($L$4+$L$5+(I55-$H$3-$H$4-$H$5)*$J$6)))) -> 0 | K57: =K39 -> P.A.Y.E | L57: =IF(AND(SUM(M55-$H$3)<$I$3,M55<$I$3),0,IF(AND(SUM(M55-$H$3)<$I$4,M55>$I$3),SUM((M55-$H$3)*$J$4),IF(AND(SUM(M55-$H$3)<$I$5,M55>$I$4),SUM($L$4+(M55-$H$3-$H$4)*$J$5),SUM($L$4+$L$5+(M55-$H$3-$H$4-$H$5)*$J$6)))) -> 0 | O57: =K57 -> P.A.Y.E | P57: =IF(AND(SUM(Q55-$H$3)<$I$3,Q55<$I$3),0,IF(AND(SUM(Q55-$H$3)<$I$4,Q55>$I$3),SUM((Q55-$H$3)*$J$4),IF(AND(SUM(Q55-$H$3)<$I$5,Q55>$I$4),SUM($L$4+(Q55-$H$3-$H$4)*$J$5),SUM($L$4+$L$5+(Q55-$H$3-$H$4-$H$5)*$J$6)))) -> 0
C58: =C40 -> Xmas Gift/Leave Pay | E58: =+LoanSchedule!L27 -> 0 | G58: =C58 -> Xmas Gift/Leave Pay | I58: =LoanSchedule!M27 -> 0 | K58: =K40 -> Xmas Gift/Leave Pay | M58: =+LoanSchedule!N27 -> 0 | O58: =K58 -> Xmas Gift/Leave Pay | Q58: =LoanSchedule!O27 -> 0
C59: Medical Aid Scheme | G59: Medical Aid Scheme | K59: Medical Aid Scheme | O59: Medical Aid Scheme
C60: =C42 -> Loan Instalment | D60: =LoanSchedule!L55 -> 0 | G60: =C60 -> Loan Instalment | H60: =LoanSchedule!M55 -> 0 | K60: =K42 -> Loan Instalment | L60: =LoanSchedule!N55 -> 0 | O60: =K60 -> Loan Instalment | P60: =LoanSchedule!O55 -> 0
C61: =C43 -> Absence Deduction | D61: =ROUNDDOWN(LoanSchedule!L23,1) -> 0 | G61: =C61 -> Absence Deduction | H61: =ROUNDDOWN(LoanSchedule!M23,1) -> 0 | K61: =K43 -> Absence Deduction | L61: =ROUNDDOWN(LoanSchedule!N23,1) -> 0 | O61: =K61 -> Absence Deduction | P61: =ROUNDDOWN(LoanSchedule!O23,1) -> 0
C62: =C44 -> Total Deductions | D62: =SUM(D57:D61) -> 0 | G62: =G44 -> Total Deductions | H62: =SUM(H57:H61) -> 0 | K62: =K44 -> Total Deductions | L62: =SUM(L57:L61) -> 0 | O62: =K62 -> Total Deductions | P62: =+P60+P61 -> 0
C63: =C45 -> Loan Balance | D63: =LoanSchedule!L54 -> 0 | G63: =C63 -> Loan Balance | H63: =LoanSchedule!M54 -> 0 | K63: =K45 -> Loan Balance | L63: =LoanSchedule!N54 -> 0 | O63: =K63 -> Loan Balance | P63: =LoanSchedule!O54 -> 0
C65: Net Pay for the Month | E65: =SUM(E55+E56+E58-D62) -> 70000 | G65: Net Pay for the Month | I65: =SUM(I55+I56+I58-H62) -> 70000 | K65: Net Pay for the Month | M65: =SUM(M55+M56+M58-L62) -> 120000 | O65: Net Pay for the Month | Q65: =SUM(Q55+Q56+Q58-P62) -> 80000
C66: =C48 -> Net Pay mid and end of Month | E66: =E65/2 -> 35000 | G66: =G48 -> Net Pay mid and end of Month | I66: =I65/2 -> 35000 | K66: =C66 -> Net Pay mid and end of Month | M66: =M65/2 -> 60000 | O66: =G66 -> Net Pay mid and end of Month | Q66: =Q65/2 -> 40000
C69: Citi-Nati Shopping Centre | G69: Citi-Nati Shopping Centre | K69: Citi-Nati Shopping Centre | O69: Citi-Nati Shopping Centre
C70: Name of Employee: | D70: =CONCATENATE(+Biodata!B37,+" ",+Biodata!C37) -> Madalitso Baluti | G70: Name of Employee: | H70: =CONCATENATE(+Biodata!B43,+" ",+Biodata!C43) -> Peter James | K70: Name of Employee: | L70: =CONCATENATE(+Biodata!B44,+" ",+Biodata!C44) -> Maggie Billy | O70: Name of Employee: | P70: =CONCATENATE(+Biodata!B45,+" ",+Biodata!C45) -> vacant
C71: Employee Number: | E71: =Biodata!A37 -> CITI14 | G71: Employee Number: | I71: =Biodata!A43 -> CITI15 | K71: Employee Number: | M71: =Biodata!A44 -> CITI16 | O71: Employee Number: | Q71: =Biodata!A45 -> CITI17
C72: Payslip for the Month: | E72: =$B$18 -> January 2026 | G72: Payslip for the Month: | I72: =$B$18 -> January 2026 | K72: Payslip for the Month: | M72: =$B$18 -> January 2026 | O72: Payslip for the Month: | Q72: =$B$18 -> January 2026
C73: Gross Salary | E73: =LoanSchedule!P14 -> 90000 | G73: Gross Salary | I73: =LoanSchedule!Q14 -> 60000 | K73: Gross Salary | M73: =LoanSchedule!R14 -> 80000 | O73: Gross Salary | Q73: =LoanSchedule!S14 -> 0
C74: Overtime Claim | E74: =LoanSchedule!P20 -> 0 | G74: Overtime Claim | I74: =LoanSchedule!Q20 -> 0 | K74: Overtime Claim | M74: =LoanSchedule!R20 -> 0 | O74: Overtime Claim | Q74: =LoanSchedule!S20 -> 0
C75: P.A.Y.E | D75: =IF(AND(SUM(E73-$H$3)<$I$3,E73<$I$3),0,IF(AND(SUM(E73-$H$3)<$I$4,E73>$I$3),SUM((E73-$H$3)*$J$4),IF(AND(SUM(E73-$H$3)<$I$5,E73>$I$4),SUM($L$4+(E73-$H$3-$H$4)*$J$5),SUM($L$4+$L$5+(E73-$H$3-$H$4-$H$5)*$J$6)))) -> 0 | G75: =C75 -> P.A.Y.E | H75: =IF(AND(SUM(I73-$H$3)<$I$3,I73<$I$3),0,IF(AND(SUM(I73-$H$3)<$I$4,I73>$I$3),SUM((I73-$H$3)*$J$4),IF(AND(SUM(I73-$H$3)<$I$5,I73>$I$4),SUM($L$4+(I73-$H$3-$H$4)*$J$5),SUM($L$4+$L$5+(I73-$H$3-$H$4-$H$5)*$J$6)))) -> 0 | K75: =K57 -> P.A.Y.E | L75: =IF(AND(SUM(M73-$H$3)<$I$3,M73<$I$3),0,IF(AND(SUM(M73-$H$3)<$I$4,M73>$I$3),SUM((M73-$H$3)*$J$4),IF(AND(SUM(M73-$H$3)<$I$5,M73>$I$4),SUM($L$4+(M73-$H$3-$H$4)*$J$5),SUM($L$4+$L$5+(M73-$H$3-$H$4-$H$5)*$J$6)))) -> 0 | O75: =K75 -> P.A.Y.E | P75: =IF(AND(SUM(Q73-$H$3)<$I$3,Q73<$I$3),0,IF(AND(SUM(Q73-$H$3)<$I$4,Q73>$I$3),SUM((Q73-$H$3)*$J$4),IF(AND(SUM(Q73-$H$3)<$I$5,Q73>$I$4),SUM($L$4+(Q73-$H$3-$H$4)*$J$5),SUM($L$4+$L$5+(Q73-$H$3-$H$4-$H$5)*$J$6)))) -> 0
C76: =C58 -> Xmas Gift/Leave Pay | E76: =LoanSchedule!P27 -> 0 | G76: =C76 -> Xmas Gift/Leave Pay | I76: =LoanSchedule!Q27 -> 0 | K76: =K58 -> Xmas Gift/Leave Pay | M76: =LoanSchedule!R27 -> 0 | O76: =K76 -> Xmas Gift/Leave Pay | Q76: =LoanSchedule!S27 -> 0
C77: Medical Aid Scheme | G77: Medical Aid Scheme | K77: Medical Aid Scheme | O77: Medical Aid Scheme
C78: =C60 -> Loan Instalment | D78: =LoanSchedule!P55 -> 0 | G78: =C78 -> Loan Instalment | H78: =LoanSchedule!Q55 -> 0 | K78: =K60 -> Loan Instalment | L78: =LoanSchedule!R55 -> 0 | O78: =K78 -> Loan Instalment | P78: =LoanSchedule!S55 -> 0
C79: =C61 -> Absence Deduction | D79: =ROUNDDOWN(LoanSchedule!P23,1) -> 0 | G79: =C79 -> Absence Deduction | H79: =ROUNDDOWN(LoanSchedule!Q23,1) -> 0 | K79: =K61 -> Absence Deduction | L79: =ROUNDDOWN(LoanSchedule!R23,1) -> 0 | O79: =K79 -> Absence Deduction | P79: =ROUNDDOWN(LoanSchedule!S23,1) -> 0
C80: =C62 -> Total Deductions | D80: =SUM(D75:D79) -> 0 | G80: =G62 -> Total Deductions | H80: =SUM(H75:H79) -> 0 | K80: =K62 -> Total Deductions | L80: =SUM(L75:L79) -> 0 | O80: =K80 -> Total Deductions | P80: =+P78+P79 -> 0
C81: =C63 -> Loan Balance | D81: =LoanSchedule!P54 -> 0 | G81: =C81 -> Loan Balance | H81: =LoanSchedule!Q54 -> 0 | K81: =K63 -> Loan Balance | L81: =LoanSchedule!R54 -> 0 | O81: =K81 -> Loan Balance | P81: =LoanSchedule!S54 -> 0
C83: Net Pay for the Month | E83: =SUM(E73+E74+E76-D80) -> 90000 | G83: Net Pay for the Month | I83: =SUM(I73+I74+I76-H80) -> 60000 | K83: Net Pay for the Month | M83: =SUM(M73+M74+M76-L80) -> 80000 | O83: Net Pay for the Month | Q83: =SUM(Q73+Q74+Q76-P80) -> 0
C84: =C66 -> Net Pay mid and end of Month | E84: =E83/2 -> 45000 | G84: =C84 -> Net Pay mid and end of Month | I84: =I83/2 -> 30000 | K84: =C84 -> Net Pay mid and end of Month | M84: =M83/2 -> 40000 | O84: =C84 -> Net Pay mid and end of Month | Q84: =Q83/2 -> 0
C87: Citi-Nati Shopping Centre | G87: Citi-Nati Shopping Centre | K87: Citi-Nati Shopping Centre | O87: Citi-Nati Shopping Centre
C88: Name of Employee: | D88: =CONCATENATE(+Biodata!B46,+" ",+Biodata!C46) -> Esnat Adam | G88: Name of Employee: | H88: =CONCATENATE(+Biodata!B53,+" ",+Biodata!C53) -> Martin Kandalama | K88: Name of Employee: | L88: =CONCATENATE(+Biodata!B54,+" ",+Biodata!C54) -> Daniel Mponda | O88: Name of Employee: | P88: =CONCATENATE(+Biodata!B55,+" ",+Biodata!C55) -> Elizabeth Kabudula
C89: Employee Number: | E89: =Biodata!A46 -> CITI18 | G89: Employee Number: | I89: =Biodata!A53 -> CITI19 | K89: Employee Number: | M89: =Biodata!A54 -> CITI20 | O89: Employee Number: | Q89: =Biodata!A55 -> CITI21
C90: Payslip for the Month: | E90: =$B$18 -> January 2026 | G90: Payslip for the Month: | I90: =$B$18 -> January 2026 | K90: Payslip for the Month: | M90: =$B$18 -> January 2026 | O90: Payslip for the Month: | Q90: =$B$18 -> January 2026
C91: Gross Salary | E91: =LoanSchedule!T14 -> 80000 | G91: Gross Salary | I91: =LoanSchedule!U14 -> 70000 | K91: Gross Salary | M91: =LoanSchedule!V14 -> 70000 | O91: Gross Salary | Q91: =LoanSchedule!W14 -> 20000
C92: Overtime Claim | E92: =LoanSchedule!T20 -> 0 | G92: Overtime Claim | I92: =LoanSchedule!U20 -> 0 | K92: Overtime Claim | M92: =LoanSchedule!V20 -> 0 | O92: Overtime Claim | Q92: =LoanSchedule!W20 -> 0
C93: P.A.Y.E | D93: =IF(AND(SUM(E91-$H$3)<$I$3,E91<$I$3),0,IF(AND(SUM(E91-$H$3)<$I$4,E91>$I$3),SUM((E91-$H$3)*$J$4),IF(AND(SUM(E91-$H$3)<$I$5,E91>$I$4),SUM($L$4+(E91-$H$3-$H$4)*$J$5),SUM($L$4+$L$5+(E91-$H$3-$H$4-$H$5)*$J$6)))) -> 0 | G93: =C93 -> P.A.Y.E | H93: =IF(AND(SUM(I91-$H$3)<$I$3,I91<$I$3),0,IF(AND(SUM(I91-$H$3)<$I$4,I91>$I$3),SUM((I91-$H$3)*$J$4),IF(AND(SUM(I91-$H$3)<$I$5,I91>$I$4),SUM($L$4+(I91-$H$3-$H$4)*$J$5),SUM($L$4+$L$5+(I91-$H$3-$H$4-$H$5)*$J$6)))) -> 0 | K93: =K75 -> P.A.Y.E | L93: =IF(AND(SUM(M91-$H$3)<$I$3,M91<$I$3),0,IF(AND(SUM(M91-$H$3)<$I$4,M91>$I$3),SUM((M91-$H$3)*$J$4),IF(AND(SUM(M91-$H$3)<$I$5,M91>$I$4),SUM($L$4+(M91-$H$3-$H$4)*$J$5),SUM($L$4+$L$5+(M91-$H$3-$H$4-$H$5)*$J$6)))) -> 0 | O93: =K93 -> P.A.Y.E | P93: =IF(AND(SUM(Q91-$H$3)<$I$3,Q91<$I$3),0,IF(AND(SUM(Q91-$H$3)<$I$4,Q91>$I$3),SUM((Q91-$H$3)*$J$4),IF(AND(SUM(Q91-$H$3)<$I$5,Q91>$I$4),SUM($L$4+(Q91-$H$3-$H$4)*$J$5),SUM($L$4+$L$5+(Q91-$H$3-$H$4-$H$5)*$J$6)))) -> 0
C94: =C76 -> Xmas Gift/Leave Pay | E94: =LoanSchedule!T27 -> 0 | G94: =C94 -> Xmas Gift/Leave Pay | I94: =LoanSchedule!U27 -> 0 | K94: =K76 -> Xmas Gift/Leave Pay | M94: =LoanSchedule!V27 -> 0 | O94: =K94 -> Xmas Gift/Leave Pay | Q94: =LoanSchedule!W27 -> 0
C95: Medical Aid Scheme | G95: Medical Aid Scheme | K95: Medical Aid Scheme | O95: Medical Aid Scheme
C96: =C78 -> Loan Instalment | D96: =LoanSchedule!T55 -> 0 | G96: =C96 -> Loan Instalment | H96: =LoanSchedule!U55 -> 0 | K96: =K78 -> Loan Instalment | L96: =LoanSchedule!V55 -> 0 | O96: =K96 -> Loan Instalment | P96: =LoanSchedule!W55 -> 0
C97: =C79 -> Absence Deduction | D97: =ROUNDDOWN(LoanSchedule!T23,1) -> 0 | G97: =C97 -> Absence Deduction | H97: =ROUNDDOWN(LoanSchedule!U23,1) -> 0 | K97: =K79 -> Absence Deduction | L97: =ROUNDDOWN(LoanSchedule!V23,1) -> 0 | O97: =K97 -> Absence Deduction | P97: =ROUNDDOWN(LoanSchedule!W23,1) -> 0
C98: =C80 -> Total Deductions | D98: =SUM(D93:D97) -> 0 | G98: =G80 -> Total Deductions | H98: =SUM(H93:H97) -> 0 | K98: =K80 -> Total Deductions | L98: =SUM(L93:L97) -> 0 | O98: =K98 -> Total Deductions | P98: =+P96+P97 -> 0
C99: =C81 -> Loan Balance | D99: =LoanSchedule!T54 -> 0 | G99: =C99 -> Loan Balance | H99: =LoanSchedule!U54 -> 0 | K99: =K81 -> Loan Balance | L99: =LoanSchedule!V54 -> 0 | O99: =K99 -> Loan Balance | P99: =LoanSchedule!W54 -> 0
C101: Net Pay for the Month | E101: =SUM(E91+E92+E94-D98) -> 80000 | G101: Net Pay for the Month | I101: =SUM(I91+I92+I94-H98) -> 70000 | K101: Net Pay for the Month | M101: =SUM(M91+M92+M94-L98) -> 70000 | O101: Net Pay for the Month | Q101: =SUM(Q91+Q92+Q94-P98) -> 20000
C102: =C84 -> Net Pay mid and end of Month | E102: =E101/2 -> 40000 | G102: =C102 -> Net Pay mid and end of Month | I102: =I101/2 -> 35000 | K102: =C102 -> Net Pay mid and end of Month | M102: =M101/2 -> 35000 | O102: =C102 -> Net Pay mid and end of Month | Q102: =Q101/2 -> 10000
C105: Citi-Nati Shopping Centre | G105: Citi-Nati Shopping Centre | K105: Citi-Nati Shopping Centre | O105: Citi-Nati Shopping Centre
C106: Name of Employee: | D106: =CONCATENATE(+Biodata!B56,+" ",+Biodata!C56) -> vacant | G106: Name of Employee: | H106: =CONCATENATE(+Biodata!B62,+" ",+Biodata!C62) -> William Mahinya | K106: Name of Employee: | L106: =CONCATENATE(+Biodata!B63,+" ",+Biodata!C63) -> vacant | O106: Name of Employee: | P106: =CONCATENATE(+Biodata!B64,+" ",+Biodata!C64)
C107: Employee Number: | E107: =Biodata!A56 -> CITI22 | G107: Employee Number: | I107: =Biodata!A62 -> CITI23 | K107: Employee Number: | M107: =Biodata!A63 -> CITI24 | O107: Employee Number: | Q107: =Biodata!A64 -> CITI25
C108: Payslip for the Month: | E108: =$B$18 -> January 2026 | G108: Payslip for the Month: | I108: =$B$18 -> January 2026 | K108: Payslip for the Month: | M108: =$B$18 -> January 2026 | O108: Payslip for the Month: | Q108: =$B$18 -> January 2026
C109: Gross Salary | E109: =LoanSchedule!X14 -> 0 | G109: Gross Salary | I109: =LoanSchedule!Y14 -> 150000 | K109: Gross Salary | M109: =LoanSchedule!Z14 -> 0 | O109: Gross Salary | Q109: =LoanSchedule!AA14 -> 0
C110: Overtime Claim | E110: =LoanSchedule!X20 -> 0 | G110: Overtime Claim | I110: =LoanSchedule!Y20 -> 0 | K110: Overtime Claim | O110: Overtime Claim | Q110: =LoanSchedule!AA20 -> 0
C111: P.A.Y.E | D111: =IF(AND(SUM(E109-$H$3)<$I$3,E109<$I$3),0,IF(AND(SUM(E109-$H$3)<$I$4,E109>$I$3),SUM((E109-$H$3)*$J$4),IF(AND(SUM(E109-$H$3)<$I$5,E109>$I$4),SUM($L$4+(E109-$H$3-$H$4)*$J$5),SUM($L$4+$L$5+(E109-$H$3-$H$4-$H$5)*$J$6)))) -> 0 | G111: =C111 -> P.A.Y.E | H111: =IF(AND(SUM(I109-$H$3)<$I$3,I109<$I$3),0,IF(AND(SUM(I109-$H$3)<$I$4,I109>$I$3),SUM((I109-$H$3)*$J$4),IF(AND(SUM(I109-$H$3)<$I$5,I109>$I$4),SUM($L$4+(I109-$H$3-$H$4)*$J$5),SUM($L$4+$L$5+(I109-$H$3-$H$4-$H$5)*$J$6)))) -> 0 | K111: =G111 -> P.A.Y.E | L111: =IF(AND(SUM(M109-$H$3)<$I$3,M109<$I$3),0,IF(AND(SUM(M109-$H$3)<$I$4,M109>$I$3),SUM((M109-$H$3)*$J$4),IF(AND(SUM(M109-$H$3)<$I$5,M109>$I$4),SUM($L$4+(M109-$H$3-$H$4)*$J$5),SUM($L$4+$L$5+(M109-$H$3-$H$4-$H$5)*$J$6)))) -> 0 | O111: =K111 -> P.A.Y.E | P111: =IF(AND(SUM(Q109-$H$3)<$I$3,Q109<$I$3),0,IF(AND(SUM(Q109-$H$3)<$I$4,Q109>$I$3),SUM((Q109-$H$3)*$J$4),IF(AND(SUM(Q109-$H$3)<$I$5,Q109>$I$4),SUM($L$4+(Q109-$H$3-$H$4)*$J$5),SUM($L$4+$L$5+(Q109-$H$3-$H$4-$H$5)*$J$6)))) -> 0
C112: =C94 -> Xmas Gift/Leave Pay | E112: =LoanSchedule!X27 -> 0 | G112: =C112 -> Xmas Gift/Leave Pay | I112: =LoanSchedule!Y27 -> 0 | K112: =K94 -> Xmas Gift/Leave Pay | M112: =LoanSchedule!Z27 -> 0 | O112: =K112 -> Xmas Gift/Leave Pay | Q112: =LoanSchedule!AA27 -> 0
C113: Medical Aid Scheme | G113: Medical Aid Scheme | K113: Medical Aid Scheme | O113: Medical Aid Scheme
C114: =C96 -> Loan Instalment | D114: =LoanSchedule!X55 -> 0 | G114: =C114 -> Loan Instalment | H114: =LoanSchedule!Y55 -> 0 | K114: =K96 -> Loan Instalment | L114: =LoanSchedule!Z55 -> 0 | O114: =K114 -> Loan Instalment | P114: =LoanSchedule!AA55 -> 0
C115: =C97 -> Absence Deduction | D115: =ROUNDDOWN(LoanSchedule!X23,1) -> 0 | G115: =C115 -> Absence Deduction | H115: =ROUNDDOWN(LoanSchedule!Y23,1) -> 0 | K115: =K97 -> Absence Deduction | L115: =ROUNDDOWN(LoanSchedule!Z23,1) -> 0 | O115: =K115 -> Absence Deduction | P115: =ROUNDDOWN(LoanSchedule!AA23,1) -> 0
C116: =C98 -> Total Deductions | D116: =SUM(D111:D115) -> 0 | G116: =G98 -> Total Deductions | H116: =SUM(H111:H115) -> 0 | K116: =K98 -> Total Deductions | L116: =SUM(L111:L115) -> 0 | O116: =K116 -> Total Deductions | P116: =+P114+P115 -> 0
C117: =C99 -> Loan Balance | D117: =LoanSchedule!X54 -> 0 | G117: =C117 -> Loan Balance | H117: =LoanSchedule!Y54 -> 0 | K117: =K99 -> Loan Balance | L117: =LoanSchedule!Z54 -> 0 | O117: =K117 -> Loan Balance | P117: =LoanSchedule!AA54 -> 0
C119: Net Pay for the Month | E119: =SUM(E109+E110+E112-D116) -> 0 | G119: Net Pay for the Month | I119: =SUM(I109+I110+I112-H116) -> 150000 | K119: Net Pay for the Month | M119: =SUM(M109+M110+M112-L116) -> 0 | O119: Net Pay for the Month | Q119: =SUM(Q109+Q110+Q112-P116) -> 0
C120: =C102 -> Net Pay mid and end of Month | E120: =E119/2 -> 0 | G120: =C120 -> Net Pay mid and end of Month | I120: =I119/2 -> 75000 | K120: =C120 -> Net Pay mid and end of Month | M120: =M119/2 -> 0 | O120: =C120 -> Net Pay mid and end of Month | Q120: =Q119/2 -> 0
...

Sheet Re-Engagements
L1: (

Sheet LoanSchedule
A2: Citi-Nati Supermarket
A11: Employee list | C11: =Wages!D16 -> Sapulene Mkulichi | D11: =Wages!H16 -> George Matemba | E11: =Wages!P141 -> vacant | F11: =Wages!L16 -> Alinafe James | G11: =Wages!P16 -> Chimwemwe Banda | H11: =Wages!D34 -> vacant | I11: =Wages!H34 -> Maureen Ulaya | J11: =Wages!L34 -> Francis Chatsweka | K11: =Wages!P34 -> Stenala Mponda | L11: =Wages!D52 -> Simikizani Siki | M11: =Wages!H52 -> Amini Wecha | N11: =Wages!L52 -> Tayifolo Mandowa | O11: =Wages!P52 -> Monica George | P11: =Wages!D70 -> Madalitso Baluti | Q11: =Wages!H70 -> Peter James | R11: =Wages!L70 -> Maggie Billy | S11: =Wages!P70 -> vacant | T11: =Wages!D88 -> Esnat Adam | U11: =Wages!H88 -> Martin Kandalama | V11: =Wages!L88 -> Daniel Mponda | W11: =Wages!P88 -> Elizabeth Kabudula | X11: =Wages!D106 -> vacant | Y11: =Wages!H106 -> William Mahinya | Z11: =Wages!L106 -> vacant | AA11: =Wages!P106 | AB11: =Wages!D123 -> vacant | AC11: =Wages!H123 -> Yankho Gulani | AD11: =Wages!L123 -> Agness Mponda | AE11: =Wages!P123 -> Elizabeth Chinkono | AF11: =Wages!D141 -> vacant | AG11: =Wages!H141 -> Dancan Botha | AH11: =Wages!L141 -> Ibrahim Amadu
A12: Employee Number | C12: =Biodata!A15 -> CITI01 | D12: =Biodata!A16 -> CITI02 | E12: =Biodata!A17 -> CITI03 | F12: =Biodata!A22 -> CITI04 | G12: =Biodata!A23 -> CITI05 | H12: =Biodata!A24 -> CITI06 | I12: =Biodata!A25 -> CITI07 | J12: =Biodata!A26 -> CITI08 | K12: =Biodata!A27 -> CITI09 | L12: =Biodata!A28 -> CITI10 | M12: =Biodata!A29 -> CITI11 | N12: =Biodata!A35 -> CITI12 | O12: =Biodata!A36 -> CITI13 | P12: =Biodata!A37 -> CITI14 | Q12: =Biodata!A43 -> CITI15 | R12: =Biodata!A44 -> CITI16 | S12: =Biodata!A45 -> CITI17 | T12: =Biodata!A46 -> CITI18 | U12: =Biodata!A53 -> CITI19 | V12: =Biodata!A54 -> CITI20 | W12: =Biodata!A55 -> CITI21 | X12: =Biodata!A56 -> CITI22 | Y12: =Biodata!A62 -> CITI23 | Z12: =Biodata!A63 -> CITI24 | AA12: =Biodata!A64 -> CITI25 | AB12: =Biodata!A65 -> CITI26 | AC12: =Biodata!A66 -> CITI27 | AD12: =Biodata!A73 -> CITI28 | AE12: =Biodata!A74 -> CITI29 | AF12: =Biodata!A75 -> CITI30 | AG12: =Biodata!A76 -> CITI30 | AH12: =Biodata!A77 -> CITI31
A14: Agreed Salary per Month | C14: =Biodata!F15 -> 0 | D14: =Biodata!$F16 -> 120000 | E14: =Biodata!$F17 -> 0 | F14: =Biodata!F22 -> 80000 | G14: =Biodata!$F23 -> 80000 | H14: =Biodata!$F24 -> 0 | I14: =Biodata!$F25 -> 80000 | J14: =Biodata!$F26 -> 70000 | K14: =Biodata!$F27 -> 70000 | L14: =Biodata!F28 -> 70000 | M14: =Biodata!F29 -> 70000 | N14: =Biodata!$F35 -> 120000 | O14: =Biodata!$F36 -> 80000 | P14: =Biodata!F37 -> 90000 | Q14: =Biodata!$F43 -> 60000 | R14: =Biodata!F44 -> 80000 | S14: =Biodata!F45 -> 0 | T14: =Biodata!F46 -> 80000 | U14: =Biodata!$F53 -> 70000 | V14: =Biodata!$F54 -> 70000 | W14: =Biodata!F55 -> 20000 | X14: =Biodata!F56 -> 0 | Y14: =Biodata!$F62 -> 150000 | Z14: =Biodata!$F63 -> 0 | AA14: =Biodata!$F64 -> 0 | AB14: =Biodata!$F65 -> 0 | AC14: =Biodata!$F66 -> 120000 | AD14: =Biodata!$F73 -> 80000 | AE14: =Biodata!$F74 -> 100000 | AF14: =Biodata!$F75 -> 0 | AG14: =Biodata!$F76 -> 94000 | AH14: =Biodata!$F77 -> 80000
A15: Agreed Working Days per Month | D15: 28
A16: Pressumed Daily Rate | C16: =INT(ROUND(C14/$D$15,1)) -> 0 | D16: =INT(ROUND(D14/$D$15,1)) -> 4285 | E16: =INT(ROUND(E14/$D$15,1)) -> 0 | F16: =INT(ROUND(F14/$D$15,1)) -> 2857 | G16: =INT(ROUND(G14/$D$15,1)) -> 2857 | H16: =INT(ROUND(H14/$D$15,1)) -> 0 | I16: =INT(ROUND(I14/$D$15,1)) -> 2857 | J16: =INT(ROUND(J14/$D$15,1)) -> 2500 | ... AH16: =INT(ROUND(AH14/$D$15,1)) -> 2857
A17: Presumed Hourly Rate | C17: =INT(ROUND(C16/8,1)) -> 0 | D17: =INT(ROUND(D16/8,1)) -> 535 | E17: =INT(ROUND(E16/8,1)) -> 0 | F17: =INT(ROUND(F16/8,1)) -> 357 | G17: =INT(ROUND(G16/8,1)) -> 357 | H17: =INT(ROUND(H16/8,1)) -> 0 | I17: =INT(ROUND(I16/8,1)) -> 357 | J17: =INT(ROUND(J16/8,1)) -> 312 | ... AH17: =INT(ROUND(AH16/8,1)) -> 357
A18: Normal Overtime Worked | C18: =C17*Wages!$C162 -> 0 | D18: =C17*Wages!$C163 -> 0 | E18: =D17*Wages!$C164 -> 0 | F18: =F17*Wages!$C165 -> 0 | G18: =G17*Wages!$C1656 -> 0 | H18: =H17*Wages!$C167 -> 0 | I18: =I17*Wages!$C168 -> 0 | J18: =J17*Wages!$C169 -> 0 | K18: =K17*Wages!$C170 -> 0 | L18: =L17*Wages!$C171 -> 0 | M18: =M17*Wages!$C172 -> 0 | N18: =N17*Wages!$C173 -> 0 | O18: =O17*Wages!$C174 -> 0 | P18: =P17*Wages!$C175 -> 0 | Q18: =Q17*Wages!$C176 -> 0 | R18: =R17*Wages!$C177 -> 0 | S18: =S17*Wages!$C178 -> 0 | T18: =T17*Wages!$C179 -> 0 | U18: =U17*Wages!$C180 -> 0 | V18: =V17*Wages!$C181 -> 0 | W18: =W17*Wages!$C182 -> 0 | X18: =X17*Wages!$C183 -> 0 | Y18: =Y17*Wages!$C184 -> 0 | Z18: =Z17*Wages!$C185 -> 0 | AA18: =AA17*Wages!$C186 -> 0 | AB18: =AB17*Wages!$C187 -> 0 | AC18: =AC17*Wages!$C188 -> 0 | AD18: =AD17*Wages!$C189 -> 0 | AE18: =AE17*Wages!$C190 -> 0 | AF18: =AF17*Wages!$C191 -> 0 | AG18: =AG17*Wages!$C192 -> 0 | AH18: =AH17*Wages!$C193 -> 0
A19: Double Overtime Worked | C19: =C17*Wages!$C162*1.5 -> 0 | D19: =C17*Wages!$C163*1.5 -> 0 | E19: =D17*Wages!$C164*1.5 -> 0 | F19: =F17*Wages!$C165*1.5 -> 0 | G19: =G17*Wages!$C166*1.5 -> 0 | H19: =H17*Wages!$C167*1.5 -> 0 | I19: =I17*Wages!$C168*1.5 -> 0 | J19: =J17*Wages!$C169*1.5 -> 0 | K19: =K17*Wages!$C170*1.5 -> 0 | L19: =L17*Wages!$C171*1.5 -> 0 | M19: =M17*Wages!$C172*1.5 -> 0 | N19: =N17*Wages!$C173*1.5 -> 0 | O19: =O17*Wages!$C174*1.5 -> 0 | P19: =P17*Wages!$C175*1.5 -> 0 | Q19: =Q17*Wages!$C176*1.5 -> 0 | R19: =R17*Wages!$C177*1.5 -> 0 | S19: =S17*Wages!$C178*1.5 -> 0 | T19: =T17*Wages!$C179*1.5 -> 0 | U19: =U17*Wages!$C180*1.5 -> 0 | V19: =V17*Wages!$C181*1.5 -> 0 | W19: =W17*Wages!$C182*1.5 -> 0 | X19: =X17*Wages!$C183*1.5 -> 0 | Y19: =Y17*Wages!$C184*1.5 -> 0 | Z19: =Z17*Wages!$C185*1.5 -> 0 | AA19: =AA17*Wages!$C186*1.5 -> 0 | AB19: =AB17*Wages!$C187*1.5 -> 0 | AC19: =AC17*Wages!$C188*1.5 -> 0 | AD19: =AD17*Wages!$C189*1.5 -> 0 | AE19: =AE17*Wages!$C190*1.5 -> 0 | AF19: =AF17*Wages!$C191*1.5 -> 0 | AG19: =AG17*Wages!$C192*1.5 -> 0 | AH19: =AH17*Wages!$C193*1.5 -> 0
A20: Total Overtime Claim | C20: =C18+C19 -> 0 | D20: =D18+D19 -> 0 | E20: =E18+E19 -> 0 | F20: =F18+F19 -> 0 | G20: =G18+G19 -> 0 | H20: =H18+H19 -> 0 | I20: =I18+I19 -> 0 | J20: =J18+J19 -> 0 | ... AH20: =AH18+AH19 -> 0
A21: Days absent | C21: =Wages!$E162 -> 0 | D21: =Wages!$E162 -> 0 | E21: =Wages!$E162 -> 0 | F21: =Wages!$E164 -> 0 | G21: =Wages!$E165 -> 0 | H21: =Wages!$E166 -> 0 | I21: =Wages!$E167 -> 0 | J21: =Wages!$E168 -> 0 | K21: =Wages!$E169 -> 0 | L21: =Wages!$E170 -> 0 | M21: =Wages!$E171 -> 0 | N21: =Wages!$E172 -> 0 | O21: =Wages!$E173 -> 0 | P21: =Wages!$E174 -> 0 | Q21: =Wages!$E175 -> 0 | R21: =Wages!$E176 -> 0 | S21: =Wages!$E177 -> 0 | T21: =Wages!$E178 -> 0 | U21: =Wages!$E179 -> 0 | V21: =Wages!$E180 -> 0 | W21: =Wages!$E181 -> 0 | X21: =Wages!$E178 -> 0 | Y21: =Wages!$E179 -> 0 | Z21: =Wages!$E180 -> 0 | AA21: =Wages!$E181 -> 0 | AB21: =Wages!$E181 -> 0 | AC21: =Wages!$E181 -> 0 | AD21: =Wages!$E181 -> 0 | AE21: =Wages!$E181 -> 0 | AF21: =Wages!$E181 -> 0 | AG21: =Wages!$E181 -> 0 | AH21: =Wages!$E181 -> 0
A23: Amount to deduct | C23: =C16*C21 -> 0 | D23: =D16*D21 -> 0 | E23: =E16*E21 -> 0 | F23: =F16*F21 -> 0 | G23: =G16*G21 -> 0 | H23: =H16*H21 -> 0 | I23: =I16*I21 -> 0 | J23: =J16*J21 -> 0 | ... AH23: =AH16*AH21 -> 0
A25: Gift factor | C25: 0 | D25: 0 | E25: 0 | F25: 0 | G25: 0 | H25: 0 | I25: 0 | J25: 0 | K25: 0 | L25: 0 | M25: 0 | N25: 0 | O25: 0 | P25: 0 | Q25: 0 | R25: 0 | S25: 0 | T25: 0 | U25: 0 | V25: 0 | W25: 0 | X25: 0 | Y25: 0 | Z25: 0 | AA25: 0 | AB25: 0 | AC25: 0 | AD25: 0 | AE25: 0 | AF25: 0 | AG25: 0 | AH25: 0
A27: Gifts | C27: =+C25*C14 -> 0 | D27: =+D25*D14 -> 0 | E27: =+E25*E14 -> 0 | F27: =+F25*F14 -> 0 | G27: =+G25*G14 -> 0 | H27: =+H25*H14 -> 0 | I27: =+I25*I14 -> 0 | J27: =+J25*J14 -> 0 | ... AH27: =+AH25*AH14 -> 0
A29: Month loan granted | C29: =IF(Wages!$M162="recommend for approval",Wages!$G162,0) -> 0 | D29: =IF(Wages!$M163="recommend for approval",Wages!$G163,0) -> 0 | E29: =IF(Wages!$M164="recommend for approval",Wages!$G164,0) -> 0 | F29: =IF(Wages!$M165="recommend for approval",Wages!$G165,0) -> 0 | G29: =IF(Wages!$M166="recommend for approval",Wages!$G166,0) -> 0 | H29: =IF(Wages!$M167="recommend for approval",Wages!$G167,0) -> 0 | I29: =IF(Wages!$M168="recommend for approval",Wages!$G168,0) -> 0 | J29: =IF(Wages!$M169="recommend for approval",Wages!$G169,0) -> 0 | K29: =IF(Wages!$M170="recommend for approval",Wages!$G170,0) -> 0 | L29: =IF(Wages!$M171="recommend for approval",Wages!$G171,0) -> 0 | M29: =IF(Wages!$M172="recommend for approval",Wages!$G172,0) -> 0 | N29: =IF(Wages!$M173="recommend for approval",Wages!$G173,0) -> 0 | O29: =IF(Wages!$M174="recommend for approval",Wages!$G174,0) -> 0 | P29: =IF(Wages!$M175="recommend for approval",Wages!$G175,0) -> 0 | Q29: =IF(Wages!$M176="recommend for approval",Wages!$G176,0) -> 0 | R29: =IF(Wages!$M177="recommend for approval",Wages!$G177,0) -> 0 | S29: =IF(Wages!$M178="recommend for approval",Wages!$G178,0) -> 0 | T29: =IF(Wages!$M179="recommend for approval",Wages!$G179,0) -> 0 | U29: =IF(Wages!$M180="recommend for approval",Wages!$G180,0) -> 0 | V29: =IF(Wages!$M181="recommend for approval",Wages!$G181,0) -> 0 | W29: =IF(Wages!$M182="recommend for approval",Wages!$G182,0) -> 0 | X29: =IF(Wages!$M183="recommend for approval",Wages!$G183,0) -> 0 | Y29: =IF(Wages!$M184="recommend for approval",Wages!$G184,0) -> 0 | Z29: =IF(Wages!$M185="recommend for approval",Wages!$G185,0) -> 0 | AA29: =IF(Wages!$M186="recommend for approval",Wages!$G186,0) -> 0 | AB29: =IF(Wages!$M187="recommend for approval",Wages!$G187,0) -> 0 | AC29: =IF(Wages!$M188="recommend for approval",Wages!$G188,0) -> 0 | AD29: =IF(Wages!$M189="recommend for approval",Wages!$G189,0) -> 0 | AE29: =IF(Wages!$M190="recommend for approval",Wages!$G190,0) -> 0 | AF29: =IF(Wages!$M191="recommend for approval",Wages!$G191,0) -> 0 | AG29: =IF(Wages!$M192="recommend for approval",Wages!$G192,0) -> 0 | AH29: =IF(Wages!$M193="recommend for approval",Wages!$G193,0) -> 0
A31: Agreed period to repay | C31: =IF(Wages!$M162="recommend for approval",Wages!$I162,0) -> 0 | D31: =IF(Wages!$M163="recommend for approval",Wages!$I163,0) -> 0 | E31: =IF(Wages!$M164="recommend for approval",Wages!$I164,0) -> 0 | F31: =IF(Wages!$M165="recommend for approval",Wages!$I165,0) -> 0 | G31: =IF(Wages!$M166="recommend for approval",Wages!$I166,0) -> 0 | H31: =IF(Wages!$M167="recommend for approval",Wages!$I167,0) -> 0 | I31: =IF(Wages!$M168="recommend for approval",Wages!$I168,0) -> 0 | J31: =IF(Wages!$M169="recommend for approval",Wages!$I169,0) -> 0 | K31: =IF(Wages!$M170="recommend for approval",Wages!$I170,0) -> 0 | L31: =IF(Wages!$M171="recommend for approval",Wages!$I171,0) -> 0 | M31: =IF(Wages!$M172="recommend for approval",Wages!$I172,0) -> 0 | N31: =IF(Wages!$M173="recommend for approval",Wages!$I173,0) -> 0 | O31: =IF(Wages!$M174="recommend for approval",Wages!$I174,0) -> 0 | P31: =IF(Wages!$M175="recommend for approval",Wages!$I175,0) -> 0 | Q31: =IF(Wages!$M176="recommend for approval",Wages!$I176,0) -> 0 | R31: =IF(Wages!$M177="recommend for approval",Wages!$I177,0) -> 0 | S31: =IF(Wages!$M178="recommend for approval",Wages!$I178,0) -> 0 | T31: =IF(Wages!$M179="recommend for approval",Wages!$I179,0) -> 0 | U31: =IF(Wages!$M180="recommend for approval",Wages!$I180,0) -> 0 | V31: =IF(Wages!$M181="recommend for approval",Wages!$I181,0) -> 0 | W31: =IF(Wages!$M182="recommend for approval",Wages!$I182,0) -> 0 | X31: =IF(Wages!$M183="recommend for approval",Wages!$I183,0) -> 0 | Y31: =IF(Wages!$M184="recommend for approval",Wages!$I184,0) -> 0 | Z31: =IF(Wages!$M185="recommend for approval",Wages!$I185,0) -> 0 | AA31: =IF(Wages!$M186="recommend for approval",Wages!$I186,0) -> 0 | AB31: =IF(Wages!$M187="recommend for approval",Wages!$I187,0) -> 0 | AC31: =IF(Wages!$M188="recommend for approval",Wages!$I188,0) -> 0 | AD31: =IF(Wages!$M189="recommend for approval",Wages!$I189,0) -> 0 | AE31: =IF(Wages!$M190="recommend for approval",Wages!$I190,0) -> 0 | AF31: =IF(Wages!$M191="recommend for approval",Wages!$I191,0) -> 0 | AG31: =IF(Wages!$M192="recommend for approval",Wages!$I192,0) -> 0 | AH31: =IF(Wages!$M193="recommend for approval",Wages!$I193,0) -> 0
A32: Loan interest rate applied | C32: 0.05
C33: Loan Calculations | N33: Loan Calculations
C35: =C11 -> Sapulene Mkulichi | D35: =D11 -> George Matemba | E35: =E11 -> vacant | F35: =F11 -> Alinafe James | G35: =G11 -> Chimwemwe Banda | H35: =H11 -> vacant | I35: =I11 -> Maureen Ulaya | J35: =J11 -> Francis Chatsweka | ... AH35: =AH11 -> Ibrahim Amadu
A36: Loan outstanding | C36: =IF(Wages!$M162="recommend for approval",Wages!$H162,0) -> 0 | D36: =IF(Wages!$M164="recommend for approval",Wages!$H164,0) -> 0 | E36: =IF(Wages!$M164="recommend for approval",Wages!$H164,0) -> 0 | F36: =IF(Wages!$M165="recommend for approval",Wages!$H165,0) -> 0 | G36: =IF(Wages!$M166="recommend for approval",Wages!$H166,0) -> 0 | H36: 0 | I36: =IF(Wages!$M168="recommend for approval",Wages!$H168,0) -> 0 | J36: =IF(Wages!$M169="recommend for approval",Wages!$H169,0) -> 0 | K36: =IF(Wages!$M170="recommend for approval",Wages!$H170,0) -> 0 | L36: =IF(Wages!$M171="recommend for approval",Wages!$H171,0) -> 0 | M36: =IF(Wages!$M172="recommend for approval",Wages!$H172,0) -> 0 | N36: 0 | O36: =IF(Wages!$M174="recommend for approval",Wages!$H174,0) -> 0 | P36: 0 | Q36: =IF(Wages!$M176="recommend for approval",Wages!$H176,0) -> 0 | R36: =IF(Wages!$M177="recommend for approval",Wages!$H177,0) -> 0 | S36: =IF(Wages!$M178="recommend for approval",Wages!$H178,0) -> 0 | T36: 0 | U36: =IF(Wages!$M180="recommend for approval",Wages!$H180,0) -> 0 | V36: =IF(Wages!$M181="recommend for approval",Wages!$H181,0) -> 0 | W36: =IF(Wages!$M182="recommend for approval",Wages!$H182,0) -> 0 | X36: =IF(Wages!$M183="recommend for approval",Wages!$H183,0) -> 0 | Y36: =IF(Wages!$M184="recommend for approval",Wages!$H184,0) -> 0 | Z36: =IF(Wages!$M185="recommend for approval",Wages!$H184,0) -> 0 | AA36: =IF(Wages!$M186="recommend for approval",Wages!$H186,0) -> 0 | AB36: =IF(Wages!$M187="recommend for approval",Wages!$H187,0) -> 0 | AC36: =IF(Wages!$M188="recommend for approval",Wages!$H188,0) -> 0 | AD36: =IF(Wages!$M189="recommend for approval",Wages!$H189,0) -> 0 | AE36: =IF(Wages!$M190="recommend for approval",Wages!$H190,0) -> 0 | AF36: =IF(Wages!$M191="recommend for approval",Wages!$H191,0) -> 0 | AG36: =IF(Wages!$M192="recommend for approval",Wages!$H192,0) -> 0 | AH36: =IF(Wages!$M193="recommend for approval",Wages!$H193,0) -> 0
A37: Top-Up | C37: 0 | D37: 0 | E37: 0 | F37: 0 | G37: 0 | H37: 0 | I37: 0 | J37: 0 | K37: 0 | L37: 0 | M37: 0 | N37: 0 | O37: 0 | P37: 0 | Q37: 0 | R37: 0 | S37: 0 | T37: 0 | U37: 0 | V37: 0 | W37: 0 | X37: 0 | Y37: 0 | Z37: 0 | AA37: 0 | AB37: 0 | AC37: 0 | AD37: 0 | AE37: 0 | AF37: 0 | AG37: 0 | AH37: 0
A38: Month loan granted | C38: =C29 -> 0 | D38: =D29 -> 0 | E38: =E29 -> 0 | F38: =F29 -> 0 | G38: =G29 -> 0 | H38: =H29 -> 0 | I38: =I29 -> 0 | J38: =J29 -> 0 | ... AH38: =AH29 -> 0
A39: Total before deduction | C39: =+SUM(C36:C37) -> 0 | D39: =+SUM(D36:D37) -> 0 | E39: =+SUM(E36:E37) -> 0 | F39: =+SUM(F36:F37) -> 0 | G39: =+SUM(G36:G37) -> 0 | H39: =+SUM(H36:H37) -> 0 | I39: =+SUM(I36:I37) -> 0 | J39: =+SUM(J36:J37) -> 0 | ... AH39: =+SUM(AH36:AH37) -> 0
A40: Agreed period to repay | C40: =C31 -> 0 | D40: =D31 -> 0 | E40: =E31 -> 0 | F40: =F31 -> 0 | G40: =G31 -> 0 | H40: =H31 -> 0 | I40: =I31 -> 0 | J40: =J31 -> 0 | ... AH40: =AH31 -> 0
A41: Month repayment starts | C41: =+IF(C38=1,"February",IF(C38=2,"March",IF(C38=3,"April",IF(C38=4,"May",IF(C38=5,"June",IF(C38=6,"July",IF(C38=7,"August",IF(C38=8,"September",IF(C38=9,"October",IF(C38=10,"November",IF(C38=11,"December",IF(C38=12,"January","N/A")))))))))))) -> N/A | D41: =+IF(D38=1,"February",IF(D38=2,"March",IF(D38=3,"April",IF(D38=4,"May",IF(D38=5,"June",IF(D38=6,"July",IF(D38=7,"August",IF(D38=8,"September",IF(D38=9,"October",IF(D38=10,"November",IF(D38=11,"December",IF(D38=12,"January","N/A")))))))))))) -> N/A | E41: =+IF(E38=1,"February",IF(E38=2,"March",IF(E38=3,"April",IF(E38=4,"May",IF(E38=5,"June",IF(E38=6,"July",IF(E38=7,"August",IF(E38=8,"September",IF(E38=9,"October",IF(E38=10,"November",IF(E38=11,"December",IF(E38=12,"January","N/A")))))))))))) -> N/A | F41: =+IF(F38=1,"February",IF(F38=2,"March",IF(F38=3,"April",IF(F38=4,"May",IF(F38=5,"June",IF(F38=6,"July",IF(F38=7,"August",IF(F38=8,"September",IF(F38=9,"October",IF(F38=10,"November",IF(F38=11,"December",IF(F38=12,"January","N/A")))))))))))) -> N/A | G41: =+IF(G38=1,"February",IF(G38=2,"March",IF(G38=3,"April",IF(G38=4,"May",IF(G38=5,"June",IF(G38=6,"July",IF(G38=7,"August",IF(G38=8,"September",IF(G38=9,"October",IF(G38=10,"November",IF(G38=11,"December",IF(G38=12,"January","N/A")))))))))))) -> N/A | H41: =+IF(H38=1,"February",IF(H38=2,"March",IF(H38=3,"April",IF(H38=4,"May",IF(H38=5,"June",IF(H38=6,"July",IF(H38=7,"August",IF(H38=8,"September",IF(H38=9,"October",IF(H38=10,"November",IF(H38=11,"December",IF(H38=12,"January","N/A")))))))))))) -> N/A | I41: =+IF(I38=1,"February",IF(I38=2,"March",IF(I38=3,"April",IF(I38=4,"May",IF(I38=5,"June",IF(I38=6,"July",IF(I38=7,"August",IF(I38=8,"September",IF(I38=9,"October",IF(I38=10,"November",IF(I38=11,"December",IF(I38=12,"January","N/A")))))))))))) -> N/A | J41: =+IF(J38=1,"February",IF(J38=2,"March",IF(J38=3,"April",IF(J38=4,"May",IF(J38=5,"June",IF(J38=6,"July",IF(J38=7,"August",IF(J38=8,"September",IF(J38=9,"October",IF(J38=10,"November",IF(J38=11,"December",IF(J38=12,"January","N/A")))))))))))) -> N/A | ... AH41: =+IF(AH38=1,"February",IF(AH38=2,"March",IF(AH38=3,"April",IF(AH38=4,"May",IF(AH38=5,"June",IF(AH38=6,"July",IF(AH38=7,"August",IF(AH38=8,"September",IF(AH38=9,"October",IF(AH38=10,"November",IF(AH38=11,"December",IF(AH38=12,"January","N/A")))))))))))) -> N/A
A42: Month repayment ends | C42: =+IF(C38=0,"N/A",IF(SUM(C38+C40)>12,SUM(C38+C40-12),SUM(C38+C40))) -> N/A | D42: =+IF(D38=0,"N/A",IF(SUM(D38+D40)>12,SUM(D38+D40-12),SUM(D38+D40))) -> N/A | E42: =+IF(E38=0,"N/A",IF(SUM(E38+E40)>12,SUM(E38+E40-12),SUM(E38+E40))) -> N/A | F42: =+IF(F38=0,"N/A",IF(SUM(F38+F40)>12,SUM(F38+F40-12),SUM(F38+F40))) -> N/A | G42: =+IF(G38=0,"N/A",IF(SUM(G38+G40)>12,SUM(G38+G40-12),SUM(G38+G40))) -> N/A | H42: =+IF(H38=0,"N/A",IF(SUM(H38+H40)>12,SUM(H38+H40-12),SUM(H38+H40))) -> N/A | I42: =+IF(I38=0,"N/A",IF(SUM(I38+I40)>12,SUM(I38+I40-12),SUM(I38+I40))) -> N/A | J42: =+IF(J38=0,"N/A",IF(SUM(J38+J40)>12,SUM(J38+J40-12),SUM(J38+J40))) -> N/A | ... AH42: =+IF(AH38=0,"N/A",IF(SUM(AH38+AH40)>12,SUM(AH38+AH40-12),SUM(AH38+AH40))) -> N/A
A43: Month repayment ends | C43: =IF(C42=1,"January ",IF(C42=2,"February ",IF(C42=3,"March ",IF(C42=4,"April ",IF(C42=5,"May ",IF(C42=6,"June ",IF(C42=7,"July ",IF(C42=8,"August ",IF(C42=9,"September ",IF(C42=10,"October ",IF(C42=11,"November ",IF(C42=12,"December ","N/A")))))))))))) -> N/A | D43: =IF(D42=1,"January ",IF(D42=2,"February ",IF(D42=3,"March ",IF(D42=4,"April ",IF(D42=5,"May ",IF(D42=6,"June ",IF(D42=7,"July ",IF(D42=8,"August ",IF(D42=9,"September ",IF(D42=10,"October ",IF(D42=11,"November ",IF(D42=12,"December ","N/A")))))))))))) -> N/A | E43: =IF(E42=1,"January ",IF(E42=2,"February ",IF(E42=3,"March ",IF(E42=4,"April ",IF(E42=5,"May ",IF(E42=6,"June ",IF(E42=7,"July ",IF(E42=8,"August ",IF(E42=9,"September ",IF(E42=10,"October ",IF(E42=11,"November ",IF(E42=12,"December ","N/A")))))))))))) -> N/A | F43: =IF(F42=1,"January ",IF(F42=2,"February ",IF(F42=3,"March ",IF(F42=4,"April ",IF(F42=5,"May ",IF(F42=6,"June ",IF(F42=7,"July ",IF(F42=8,"August ",IF(F42=9,"September ",IF(F42=10,"October ",IF(F42=11,"November ",IF(F42=12,"December ","N/A")))))))))))) -> N/A | G43: =IF(G42=1,"January ",IF(G42=2,"February ",IF(G42=3,"March ",IF(G42=4,"April ",IF(G42=5,"May ",IF(G42=6,"June ",IF(G42=7,"July ",IF(G42=8,"August ",IF(G42=9,"September ",IF(G42=10,"October ",IF(G42=11,"November ",IF(G42=12,"December ","N/A")))))))))))) -> N/A | H43: =IF(H42=1,"January ",IF(H42=2,"February ",IF(H42=3,"March ",IF(H42=4,"April ",IF(H42=5,"May ",IF(H42=6,"June ",IF(H42=7,"July ",IF(H42=8,"August ",IF(H42=9,"September ",IF(H42=10,"October ",IF(H42=11,"November ",IF(H42=12,"December ","N/A")))))))))))) -> N/A | I43: =IF(I42=1,"January ",IF(I42=2,"February ",IF(I42=3,"March ",IF(I42=4,"April ",IF(I42=5,"May ",IF(I42=6,"June ",IF(I42=7,"July ",IF(I42=8,"August ",IF(I42=9,"September ",IF(I42=10,"October ",IF(I42=11,"November ",IF(I42=12,"December ","N/A")))))))))))) -> N/A | J43: =IF(J42=1,"January ",IF(J42=2,"February ",IF(J42=3,"March ",IF(J42=4,"April ",IF(J42=5,"May ",IF(J42=6,"June ",IF(J42=7,"July ",IF(J42=8,"August ",IF(J42=9,"September ",IF(J42=10,"October ",IF(J42=11,"November ",IF(J42=12,"December ","N/A")))))))))))) -> N/A | ... AH43: =IF(AH42=1,"January ",IF(AH42=2,"February ",IF(AH42=3,"March ",IF(AH42=4,"April ",IF(AH42=5,"May ",IF(AH42=6,"June ",IF(AH42=7,"July ",IF(AH42=8,"August ",IF(AH42=9,"September ",IF(AH42=10,"October ",IF(AH42=11,"November ",IF(AH42=12,"December ","N/A")))))))))))) -> N/A
A44: Year repayment ends | C44: =IF(C38>C42,$B$71,IF(C38=C42,$B$71,$B$59)) -> 2026 | D44: =IF(D38>D42,$B$71,IF(D38=D42,$B$71,$B$59)) -> 2026 | E44: =IF(E38>E42,$B$71,IF(E38=E42,$B$71,$B$59)) -> 2026 | F44: =IF(F38>F42,$B$71,IF(F38=F42,$B$71,$B$59)) -> 2026 | G44: =IF(G38>G42,$B$71,IF(G38=G42,$B$71,$B$59)) -> 2026 | H44: =IF(H38>H42,$B$71,IF(H38=H42,$B$71,$B$59)) -> 2026 | I44: =IF(I38>I42,$B$71,IF(I38=I42,$B$71,$B$59)) -> 2026 | J44: =IF(J38>J42,$B$71,IF(J38=J42,$B$71,$B$59)) -> 2026 | ... AH44: =IF(AH38>AH42,$B$71,IF(AH38=AH42,$B$71,$B$59)) -> 2026
A45: Month repayment ends | C45: =IF(C39=0,"N/A",CONCATENATE(C43,C44)) -> N/A | D45: =IF(D39=0,"N/A",CONCATENATE(D43,D44)) -> N/A | E45: =IF(E39=0,"N/A",CONCATENATE(E43,E44)) -> N/A | F45: =IF(F39=0,"N/A",CONCATENATE(F43,F44)) -> N/A | G45: =IF(G39=0,"N/A",CONCATENATE(G43,G44)) -> N/A | H45: =IF(H39=0,"N/A",CONCATENATE(H43,H44)) -> N/A | I45: =IF(I39=0,"N/A",CONCATENATE(I43,I44)) -> N/A | J45: =IF(J39=0,"N/A",CONCATENATE(J43,J44)) -> N/A | ... AH45: =IF(AH39=0,"N/A",CONCATENATE(AH43,AH44)) -> N/A
A46: Total amount borrowed | C46: =+C36+C37 -> 0 | D46: =+D36+D37 -> 0 | E46: =+E36+E37 -> 0 | F46: =+F36+F37 -> 0 | G46: =+G36+G37 -> 0 | H46: =+H36+H37 -> 0 | I46: =+I36+I37 -> 0 | J46: =+J36+J37 -> 0 | ... AH46: =+AH36+AH37 -> 0
A47: Repayment amount | C47: =+IF(C39=0,"N/A",SUM(C46/C40+C46/C40*C32)) -> N/A | D47: =+IF(D39=0,"N/A",SUM(D46/D40+D46/D40*$C$32)) -> N/A | E47: =+IF(E39=0,"N/A",SUM(E46/E40+E46/E40*$C$32)) -> N/A | F47: =+IF(F39=0,"N/A",SUM(F46/F40+F46/F40*$C$32)) -> N/A | G47: =+IF(G39=0,"N/A",SUM(G46/G40+G46/G40*$C$32)) -> N/A | H47: =+IF(H39=0,"N/A",SUM(H46/H40+H46/H40*$C$32)) -> N/A | I47: =+IF(I39=0,"N/A",SUM(I46/I40+I46/I40*$C$32)) -> N/A | J47: =+IF(J39=0,"N/A",SUM(J46/J40+J46/J40*$C$32)) -> N/A | K47: =+IF(K39=0,"N/A",SUM(K46/K40+K46/K40*$C$32)) -> N/A | ... AH47: =+IF(AH39=0,"N/A",SUM(AH46/AH40+AH46/AH40*$C$32)) -> N/A
A48: Of which accrued interest | C48: =+IF(C39=0,"N/A",C46/C40*$C$32*C50) -> N/A | D48: =+IF(D39=0,"N/A",D46/D40*$C$32*D50) -> N/A | E48: =+IF(E39=0,"N/A",E46/E40*$C$32*E50) -> N/A | F48: =+IF(F39=0,"N/A",F46/F40*$C$32*F50) -> N/A | G48: =+IF(G39=0,"N/A",G46/G40*$C$32*G50) -> N/A | H48: =+IF(H39=0,"N/A",H46/H40*$C$32*H50) -> N/A | I48: =+IF(I39=0,"N/A",I46/I40*$C$32*I50) -> N/A | J48: =+IF(J39=0,"N/A",J46/J40*$C$32*J50) -> N/A | ... AH48: =+IF(AH39=0,"N/A",AH46/AH40*$C$32*AH50) -> N/A
A49: Month wages being paid | C49: =+Wages!$C$4 -> 1 | D49: =+Wages!$C$4 -> 1 | E49: =+Wages!$C$4 -> 1 | F49: =+Wages!$C$4 -> 1 | G49: =+Wages!$C$4 -> 1 | H49: =+Wages!$C$4 -> 1 | I49: =+Wages!$C$4 -> 1 | J49: =+Wages!$C$4 -> 1 | ... AH49: =+Wages!$C$4 -> 1
A50: Months repaid counter | C50: =IF(C39=0,0,IF(C49=C38,0,IF(SUM(C49-C38)>C40,C40,SUM(C49-C38)))) -> 0 | D50: =IF(D39=0,0,IF(D49=D38,0,IF(SUM(D49-D38)>D40,D40,SUM(D49-D38)))) -> 0 | E50: =IF(E39=0,0,IF(E49=E38,0,IF(SUM(E49-E38)>E40,E40,SUM(E49-E38)))) -> 0 | F50: =IF(F39=0,0,IF(F49=F38,0,IF(SUM(F49-F38)>F40,F40,SUM(F49-F38)))) -> 0 | G50: =IF(G39=0,0,IF(G49=G38,0,IF(SUM(G49-G38)>G40,G40,SUM(G49-G38)))) -> 0 | H50: =IF(H39=0,0,IF(H49=H38,0,IF(SUM(H49-H38)>H40,H40,SUM(H49-H38)))) -> 0 | I50: =IF(I39=0,0,IF(I49=I38,0,IF(SUM(I49-I38)>I40,I40,SUM(I49-I38)))) -> 0 | J50: =IF(J39=0,0,IF(J49=J38,0,IF(SUM(J49-J38)>J40,J40,SUM(J49-J38)))) -> 0 | ... AH50: =IF(AH39=0,0,IF(AH49=AH38,0,IF(SUM(AH49-AH38)>AH40,AH40,SUM(AH49-AH38)))) -> 0
A51: Months repaid | C51: =IF(C40=0,0,IF(OR(C50>C40,C50=C40),"Loan repaid",C50)) -> 0 | D51: =IF(D40=0,0,IF(OR(D50>D40,D50=D40),"Loan repaid",D50)) -> 0 | E51: =IF(E40=0,0,IF(OR(E50>E40,E50=E40),"Loan repaid",E50)) -> 0 | F51: =IF(F40=0,0,IF(OR(F50>F40,F50=F40),"Loan repaid",F50)) -> 0 | G51: =IF(G40=0,0,IF(OR(G50>G40,G50=G40),"Loan repaid",G50)) -> 0 | H51: =IF(H40=0,0,IF(OR(H50>H40,H50=H40),"Loan repaid",H50)) -> 0 | I51: =IF(I40=0,0,IF(OR(I50>I40,I50=I40),"Loan repaid",I50)) -> 0 | J51: =IF(J40=0,0,IF(OR(J50>J40,J50=J40),"Loan repaid",J50)) -> 0 | ... AH51: =IF(AH40=0,0,IF(OR(AH50>AH40,AH50=AH40),"Loan repaid",AH50)) -> 0
A52: Months remaining | C52: =IF(OR(C39=0,C38=0),"N/A",IF(C51="Loan repaid",0,IF(SUM(C40-C50)<0,0,SUM(C40-C51)))) -> N/A | D52: =IF(OR(D39=0,D38=0),"N/A",IF(D51="Loan repaid",0,IF(SUM(D40-D50)<0,0,SUM(D40-D51)))) -> N/A | E52: =IF(OR(E39=0,E38=0),"N/A",IF(E51="Loan repaid",0,IF(SUM(E40-E50)<0,0,SUM(E40-E51)))) -> N/A | F52: =IF(OR(F39=0,F38=0),"N/A",IF(F51="Loan repaid",0,IF(SUM(F40-F50)<0,0,SUM(F40-F51)))) -> N/A | G52: =IF(OR(G39=0,G38=0),"N/A",IF(G51="Loan repaid",0,IF(SUM(G40-G50)<0,0,SUM(G40-G51)))) -> N/A | H52: =IF(OR(H39=0,H38=0),"N/A",IF(H51="Loan repaid",0,IF(SUM(H40-H50)<0,0,SUM(H40-H51)))) -> N/A | I52: =IF(OR(I39=0,I38=0),"N/A",IF(I51="Loan repaid",0,IF(SUM(I40-I50)<0,0,SUM(I40-I51)))) -> N/A | J52: =IF(OR(J39=0,J38=0),"N/A",IF(J51="Loan repaid",0,IF(SUM(J40-J50)<0,0,SUM(J40-J51)))) -> N/A | ... AH52: =IF(OR(AH39=0,AH38=0),"N/A",IF(AH51="Loan repaid",0,IF(SUM(AH40-AH50)<0,0,SUM(AH40-AH51)))) -> N/A
A53: Amount repaid | C53: =IF(OR(C39=0,C38=0),0,IF(OR(C51="Loan repaid",(C50>C40)),SUM(C47*C40),SUM(C47*C51))) -> 0 | D53: =IF(OR(D39=0,D38=0),0,IF(OR(D51="Loan repaid",(D50>D40)),SUM(D47*D40),SUM(D47*D51))) -> 0 | E53: =IF(OR(E39=0,E38=0),0,IF(OR(E51="Loan repaid",(E50>E40)),SUM(E47*E40),SUM(E47*E51))) -> 0 | F53: =IF(OR(F39=0,F38=0),0,IF(OR(F51="Loan repaid",(F50>F40)),SUM(F47*F40),SUM(F47*F51))) -> 0 | G53: =IF(OR(G39=0,G38=0),0,IF(OR(G51="Loan repaid",(G50>G40)),SUM(G47*G40),SUM(G47*G51))) -> 0 | H53: =IF(OR(H39=0,H38=0),0,IF(OR(H51="Loan repaid",(H50>H40)),SUM(H47*H40),SUM(H47*H51))) -> 0 | I53: =IF(OR(I39=0,I38=0),0,IF(OR(I51="Loan repaid",(I50>I40)),SUM(I47*I40),SUM(I47*I51))) -> 0 | J53: =IF(OR(J39=0,J38=0),0,IF(OR(J51="Loan repaid",(J50>J40)),SUM(J47*J40),SUM(J47*J51))) -> 0 | ... AH53: =IF(OR(AH39=0,AH38=0),0,IF(OR(AH51="Loan repaid",(AH50>AH40)),SUM(AH47*AH40),SUM(AH47*AH51))) -> 0
A54: Outstanding amount | C54: =IF(OR(C39=0,C38=0,C52=0,C51="Loan repaid"),0,SUM(C46-C53)) -> 0 | D54: =IF(OR(D39=0,D38=0,D52=0,D51="Loan repaid"),0,SUM(D46-D53)) -> 0 | E54: =IF(OR(E39=0,E38=0,E52=0,E51="Loan repaid"),0,SUM(E46-E53)) -> 0 | F54: =IF(OR(F39=0,F38=0,F52=0,F51="Loan repaid"),0,SUM(F46-F53)) -> 0 | G54: =IF(OR(G39=0,G38=0,G52=0,G51="Loan repaid"),0,SUM(G46-G53)) -> 0 | H54: =IF(OR(H39=0,H38=0,H52=0,H51="Loan repaid"),0,SUM(H46-H53)) -> 0 | I54: =IF(OR(I39=0,I38=0,I52=0,I51="Loan repaid"),0,SUM(I46-I53)) -> 0 | J54: =IF(OR(J39=0,J38=0,J52=0,J51="Loan repaid"),0,SUM(J46-J53)) -> 0 | ... AH54: =IF(OR(AH39=0,AH38=0,AH52=0,AH51="Loan repaid"),0,SUM(AH46-AH53)) -> 0
A55: Deduction for the month | C55: =+IF(OR(C50=0,SUM(C49-C38)>C40),0,IF(SUM(C49-C38)=C40,C47,C47)) -> 0 | D55: =+IF(OR(D50=0,SUM(D49-D38)>D40),0,IF(SUM(D49-D38)=D40,D47,D47)) -> 0 | E55: =+IF(OR(E50=0,SUM(E49-E38)>E40),0,IF(SUM(E49-E38)=E40,E47,E47)) -> 0 | F55: =+IF(OR(F50=0,SUM(F49-F38)>F40),0,IF(SUM(F49-F38)=F40,F47,F47)) -> 0 | G55: =+IF(OR(G50=0,SUM(G49-G38)>G40),0,IF(SUM(G49-G38)=G40,G47,G47)) -> 0 | H55: =+IF(OR(H50=0,SUM(H49-H38)>H40),0,IF(SUM(H49-H38)=H40,H47,H47)) -> 0 | I55: =+IF(OR(I50=0,SUM(I49-I38)>I40),0,IF(SUM(I49-I38)=I40,I47,I47)) -> 0 | J55: =+IF(OR(J50=0,SUM(J49-J38)>J40),0,IF(SUM(J49-J38)=J40,J47,J47)) -> 0 | ... AH55: =+IF(OR(AH50=0,SUM(AH49-AH38)>AH40),0,IF(SUM(AH49-AH38)=AH40,AH47,AH47)) -> 0
A57: Calendar | D57: Concanation of Calendar Months and year
A58: December | B58: 2025 | D58: =CONCATENATE(A58,B58) -> December 2025
A59: January | B59: =+B58+1 -> 2026 | D59: =CONCATENATE(A59,B59) -> January 2026
A60: February | B60: =+B59 -> 2026 | D60: =CONCATENATE(A60,B60) -> February 2026
A61: March | B61: =+B60 -> 2026 | D61: =CONCATENATE(A61,B61) -> March 2026
A62: April | B62: =+B61 -> 2026 | D62: =CONCATENATE(A62,B62) -> April 2026
A63: May | B63: =+B62 -> 2026 | D63: =CONCATENATE(A63,B63) -> May 2026
A64: June | B64: =+B63 -> 2026 | D64: =CONCATENATE(A64,B64) -> June 2026
A65: July | B65: =+B64 -> 2026 | D65: =CONCATENATE(A65,B65) -> July 2026
A66: August | B66: =+B65 -> 2026 | D66: =CONCATENATE(A66,B66) -> August 2026
A67: September | B67: =+B66 -> 2026 | D67: =CONCATENATE(A67,B67) -> September 2026
A68: October | B68: =+B67 -> 2026 | D68: =CONCATENATE(A68,B68) -> October 2026
A69: November | B69: =+B68 -> 2026 | D69: =CONCATENATE(A69,B69) -> November 2026
A70: December | B70: =+B69 -> 2026 | D70: =CONCATENATE(A70,B70) -> December 2026
B71: =B59+1 -> 2027
B74: password | C74: wag3s

Sheet Combined Pay
B2: Citi-Nati Supermarket
A4: Wages for Residences, Supermarkets, Stop-Over and Restaurant
B6: Month for Payment of Wages: | C6: ='Res-Workers'!B81 -> Mid | D6: ='Res-Workers'!C81 -> January 2026
D9: Amount Due | E9: Loan Outstanding | F9: Accrued Interest
B10: Total Wages Due | D10: =D22+D49 -> 967000 | E10: =E22+E49 -> 0 | F10: =F22+F49 -> 0
A12: Count | B12: Nyambadwe and Domasi Residence
A13: 1 | B13: ='Res-Workers'!B68 -> Martin Kandalama | D13: ='Res-Workers'!G68 -> 35000 | E13: ='Res-Workers'!F68 -> 0 | F13: ='Res-Workers'!H68 -> 0
A14: =A13+1 -> 2 | B14: ='Res-Workers'!B69 -> Daniel Mponda | D14: ='Res-Workers'!G69 -> 35000 | E14: ='Res-Workers'!F69 -> 0 | F14: ='Res-Workers'!H69 -> 0
A15: =A14+1 -> 3 | B15: ='Res-Workers'!B70 -> Elizabeth Kabudula | D15: ='Res-Workers'!G70 -> 10000 | E15: ='Res-Workers'!F70 -> 0 | F15: ='Res-Workers'!H70 -> 0
A16: =A15+1 -> 4 | B16: ='Res-Workers'!B71 -> vacant | D16: ='Res-Workers'!G71 -> 0 | E16: ='Res-Workers'!F71 -> 0 | F16: ='Res-Workers'!H71 -> 0
A17: =A16+1 -> 5 | B17: ='Res-Workers'!B72 -> William Mahinya | D17: ='Res-Workers'!G72 -> 75000 | E17: ='Res-Workers'!F72 -> 0 | F17: ='Res-Workers'!H72 -> 0
A18: =A17+1 -> 6 | B18: ='Res-Workers'!B73 -> vacant | D18: ='Res-Workers'!G73 -> 0 | E18: ='Res-Workers'!F73 -> 0 | F18: ='Res-Workers'!H73 -> 0
A19: =A18+1 -> 7 | B19: ='Res-Workers'!B74 | D19: ='Res-Workers'!G74 -> 0 | E19: ='Res-Workers'!F74 -> 0 | F19: ='Res-Workers'!H74 -> 0
A20: =A19+1 -> 8 | B20: ='Res-Workers'!B75 -> vacant | D20: ='Res-Workers'!G75 -> 0 | E20: ='Res-Workers'!F75 -> 0 | F20: ='Res-Workers'!H75 -> 0
A21: =A20+1 -> 9 | B21: ='Res-Workers'!B76 -> Yankho Gulani | D21: ='Res-Workers'!G76 -> 60000 | E21: ='Res-Workers'!F76 -> 0 | F21: ='Res-Workers'!H76 -> 0
B22: Sub-Total | D22: =SUM(D13:D21) -> 215000 | E22: =SUM(E13:E21) -> 0 | F22: =SUM(F13:F21) -> 0
A24: Count | B24: Citi-Nati Supermarkets, Resturant and Stop Over
A25: 1 | B25: ='Shop-Workers'!B121 -> Sapulene Mkulichi | D25: ='Shop-Workers'!G121 -> 0 | E25: ='Shop-Workers'!F121 -> 0 | F25: ='Shop-Workers'!H121 -> 0
A26: =A25+1 -> 2 | B26: ='Shop-Workers'!B122 -> George Matemba | D26: ='Shop-Workers'!G122 -> 60000 | E26: ='Shop-Workers'!F122 -> 0 | F26: ='Shop-Workers'!H122 -> 0
A27: =A26+1 -> 3 | B27: ='Shop-Workers'!B123 -> vacant | D27: ='Shop-Workers'!G123 -> 0 | E27: ='Shop-Workers'!F123 -> 0 | F27: ='Shop-Workers'!H123 -> 0
A28: =A27+1 -> 4 | B28: ='Shop-Workers'!B124 -> Alinafe James | D28: ='Shop-Workers'!G124 -> 40000 | E28: ='Shop-Workers'!F124 -> 0 | F28: ='Shop-Workers'!H124 -> 0
A29: =A28+1 -> 5 | B29: ='Shop-Workers'!B125 -> Chimwemwe Banda | D29: ='Shop-Workers'!G125 -> 40000 | E29: ='Shop-Workers'!F125 -> 0 | F29: ='Shop-Workers'!H125 -> 0
A30: =A29+1 -> 6 | B30: ='Shop-Workers'!B126 -> vacant | D30: ='Shop-Workers'!G126 -> 0 | E30: ='Shop-Workers'!F126 -> 0 | F30: ='Shop-Workers'!H126 -> 0
A31: =A30+1 -> 7 | B31: ='Shop-Workers'!B127 -> Maureen Ulaya | D31: ='Shop-Workers'!G127 -> 40000 | E31: ='Shop-Workers'!F127 -> 0 | F31: ='Shop-Workers'!H127 -> 0
A32: =A31+1 -> 8 | B32: ='Shop-Workers'!B128 -> Francis Chatsweka | D32: ='Shop-Workers'!G128 -> 35000 | E32: ='Shop-Workers'!F128 -> 0 | F32: ='Shop-Workers'!H128 -> 0
A33: =A32+1 -> 9 | B33: ='Shop-Workers'!B129 -> Stenala Mponda | D33: ='Shop-Workers'!G129 -> 35000 | E33: ='Shop-Workers'!F129 -> 0 | F33: ='Shop-Workers'!H129 -> 0
A34: =A33+1 -> 10 | B34: ='Shop-Workers'!B130 -> Simikizani Siki | D34: ='Shop-Workers'!G130 -> 35000 | E34: ='Shop-Workers'!F130 -> 0 | F34: ='Shop-Workers'!H130 -> 0
A35: =A34+1 -> 11 | B35: ='Shop-Workers'!B131 -> Amini Wecha | D35: ='Shop-Workers'!G131 -> 35000 | E35: ='Shop-Workers'!F131 -> 0 | F35: ='Shop-Workers'!H131 -> 0
A36: =A35+1 -> 12 | B36: ='Shop-Workers'!B132 -> Tayifolo Mandowa | D36: ='Shop-Workers'!G132 -> 60000 | E36: ='Shop-Workers'!F132 -> 0 | F36: ='Shop-Workers'!H132 -> 0
A37: =A36+1 -> 13 | B37: ='Shop-Workers'!B133 -> Monica George | D37: ='Shop-Workers'!G133 -> 40000 | E37: ='Shop-Workers'!F133 -> 0 | F37: ='Shop-Workers'!H133 -> 0
... A47: =A46+1 -> 23 | B47: ='Shop-Workers'!B143 -> Ibrahim Amadu | D47: ='Shop-Workers'!G143 -> 40000 | E47: ='Shop-Workers'!F143 -> 0 | F47: ='Shop-Workers'!H143 -> 0
B49: Sub-Total | D49: =SUM(D25:D47) -> 752000 | E49: =SUM(E25:E47) -> 0 | F49: =SUM(F25:F47) -> 0
D51: =Wages!G13-'Combined Pay'!D10 -> 0

Sheet Res-Workers
A1: Wages for Nyambadwe and Domasi Residences
E3: Half Pay | G3: Full Pay
A4: Gross Wages | E4: =G4/2 -> 215000 | G4: =C14+G14+K14+O14+C32+G32+K32+O32+C52 -> 430000
A5: P.A.Y.E. | E5: =G5/2 -> 0 | G5: =B16+F16+J16+N16+B34+F34+J34+N34+B54 -> 0
A6: Christimas Gift/Leave Pay | E6: =G6/2 -> 0 | G6: =C17+G17+K17+O17+C35+G35+K35+O35+C55 -> 0
A7: Total Deductions for this Month | E7: =G7/2 -> 0 | G7: =B21+F21+J21+N21+B39+F39+J39+N39+B59 -> 0
A8: Total Wages for this Month (net of P.A.Y.E) | E8: =E4-E5+E6-E7 -> 215000 | G8: =G4+G6-G7 -> 430000
A10: Citi-Nati Shopping Centre | E10: Citi-Nati Shopping Centre | I10: Citi-Nati Shopping Centre | M10: Citi-Nati Shopping Centre
A11: =Wages!G88 -> Name of Employee: | B11: =Wages!H88 -> Martin Kandalama | E11: =Wages!K88 -> Name of Employee: | F11: =Wages!L88 -> Daniel Mponda | I11: =Wages!O88 -> Name of Employee: | J11: =Wages!P88 -> Elizabeth Kabudula | M11: =Wages!C106 -> Name of Employee: | N11: =Wages!D106 -> vacant
A12: =Wages!G89 -> Employee Number: | C12: =Wages!I89 -> CITI19 | E12: =Wages!K89 -> Employee Number: | G12: =Wages!M89 -> CITI20 | I12: =Wages!O89 -> Employee Number: | K12: =Wages!Q89 -> CITI21 | M12: =Wages!C107 -> Employee Number: | O12: =Wages!E107 -> CITI22
C13: =Wages!E18 -> January 2026 | G13: =$C$13 -> January 2026 | K13: =$C$13 -> January 2026 | O13: =$C$13 -> January 2026
A14: Gross Salary | C14: =Wages!I91 -> 70000 | E14: Gross Salary | G14: =Wages!M91 -> 70000 | I14: Gross Salary | K14: =Wages!Q91 -> 20000 | M14: Gross Salary | O14: =Wages!E109 -> 0
A15: =Wages!G92 -> Overtime Claim | C15: =Wages!I92 -> 0 | E15: =Wages!K92 -> Overtime Claim | G15: =Wages!M92 -> 0 | I15: =Wages!O92 -> Overtime Claim | K15: =Wages!Q92 -> 0 | M15: =Wages!C110 -> Overtime Claim | O15: =Wages!E110 -> 0
A16: =Wages!G93 -> P.A.Y.E | B16: =Wages!H93 -> 0 | E16: =Wages!K93 -> P.A.Y.E | F16: =Wages!L93 -> 0 | I16: =Wages!O93 -> P.A.Y.E | J16: =Wages!P93 -> 0 | M16: =Wages!C111 -> P.A.Y.E | N16: =Wages!D111 -> 0
A17: =Wages!G94 -> Xmas Gift/Leave Pay | C17: =Wages!I94 -> 0 | E17: =Wages!K94 -> Xmas Gift/Leave Pay | G17: =Wages!M94 -> 0 | I17: =Wages!O94 -> Xmas Gift/Leave Pay | K17: =Wages!Q94 -> 0 | M17: =Wages!C112 -> Xmas Gift/Leave Pay | O17: =Wages!E112 -> 0
A18: =Wages!G95 -> Medical Aid Scheme | E18: =Wages!K95 -> Medical Aid Scheme | I18: =Wages!O95 -> Medical Aid Scheme | M18: =Wages!C113 -> Medical Aid Scheme
A19: =Wages!G96 -> Loan Instalment | B19: =Wages!H96 -> 0 | E19: =Wages!K96 -> Loan Instalment | F19: =Wages!L96 -> 0 | I19: =Wages!O96 -> Loan Instalment | J19: =Wages!P96 -> 0 | M19: =Wages!C114 -> Loan Instalment | N19: =Wages!D114 -> 0
A20: =Wages!G97 -> Absence Deduction | B20: =Wages!H97 -> 0 | E20: =Wages!K97 -> Absence Deduction | F20: =Wages!L97 -> 0 | I20: =Wages!O97 -> Absence Deduction | J20: =Wages!P97 -> 0 | M20: =Wages!C115 -> Absence Deduction | N20: =Wages!D115 -> 0
A21: =Wages!G98 -> Total Deductions | B21: =Wages!H98 -> 0 | E21: =Wages!K98 -> Total Deductions | F21: =Wages!L98 -> 0 | I21: =Wages!O98 -> Total Deductions | J21: =Wages!P98 -> 0 | M21: =Wages!C116 -> Total Deductions | N21: =Wages!D116 -> 0
A22: =Wages!G99 -> Loan Balance | B22: =Wages!H99 -> 0 | E22: =Wages!K99 -> Loan Balance | F22: =Wages!L99 -> 0 | I22: =Wages!O99 -> Loan Balance | J22: =Wages!P99 -> 0 | M22: =Wages!C117 -> Loan Balance | N22: =Wages!D117 -> 0
A24: =Wages!G101 -> Net Pay for the Month | C24: =SUM(C14+C15+C17-B21) -> 70000 | E24: =Wages!K101 -> Net Pay for the Month | G24: =SUM(G14+G15+G17-F21) -> 70000 | I24: =Wages!O101 -> Net Pay for the Month | K24: =SUM(K14+K15+K17-J21) -> 20000 | M24: =Wages!C119 -> Net Pay for the Month | O24: =SUM(O14+O15+O17-N21) -> 0
A25: =Wages!G102 -> Net Pay mid and end of Month | C25: =C24/2 -> 35000 | E25: =Wages!K102 -> Net Pay mid and end of Month | G25: =G24/2 -> 35000 | I25: =Wages!O102 -> Net Pay mid and end of Month | K25: =K24/2 -> 10000 | M25: =Wages!C120 -> Net Pay mid and end of Month | O25: =O24/2 -> 0
A28: Citi-Nati Shopping Centre | E28: Citi-Nati Shopping Centre | I28: Citi-Nati Shopping Centre | M28: Citi-Nati Shopping Centre
A29: =Wages!G106 -> Name of Employee: | B29: =Wages!H106 -> William Mahinya | E29: =Wages!K106 -> Name of Employee: | F29: =Wages!L106 -> vacant | I29: =Wages!O106 -> Name of Employee: | J29: =Wages!P106 | M29: =Wages!C123 -> Name of Employee: | N29: =Wages!D123 -> vacant
A30: =Wages!G107 -> Employee Number: | C30: =Wages!I107 -> CITI23 | E30: =Wages!K107 -> Employee Number: | G30: =Wages!M107 -> CITI24 | I30: =Wages!O107 -> Employee Number: | K30: =Wages!Q107 -> CITI25 | M30: =Wages!C124 -> Employee Number: | O30: =Wages!E124 -> CITI26
C31: =$C$13 -> January 2026 | G31: =$C$13 -> January 2026 | K31: =$C$13 -> January 2026 | O31: =$C$13 -> January 2026
A32: Gross Salary | C32: =Wages!I109 -> 150000 | E32: Gross Salary | G32: =Wages!M109 -> 0 | I32: Gross Salary | K32: =Wages!Q109 -> 0 | M32: Gross Salary | O32: =Wages!E126 -> 0
A33: =Wages!G110 -> Overtime Claim | C33: =Wages!I110 -> 0 | E33: =Wages!K110 -> Overtime Claim | G33: 0 | I33: =Wages!O110 -> Overtime Claim | K33: =Wages!Q110 -> 0 | M33: =Wages!C127 -> Overtime Claim | O33: =Wages!E127 -> 0
A34: =Wages!G111 -> P.A.Y.E | B34: =Wages!H111 -> 0 | E34: =Wages!K111 -> P.A.Y.E | F34: =Wages!L111 -> 0 | I34: =Wages!O111 -> P.A.Y.E | J34: =Wages!P111 -> 0 | M34: =Wages!C128 -> P.A.Y.E | N34: =Wages!D128 -> 0
A35: =Wages!G112 -> Xmas Gift/Leave Pay | C35: =Wages!I112 -> 0 | E35: =Wages!K112 -> Xmas Gift/Leave Pay | G35: =Wages!M112 -> 0 | I35: =Wages!O112 -> Xmas Gift/Leave Pay | K35: =Wages!Q112 -> 0 | M35: =Wages!C129 -> Xmas Gift/Leave Pay | O35: =Wages!E129 -> 0
A36: =Wages!G113 -> Medical Aid Scheme | E36: =Wages!K113 -> Medical Aid Scheme | I36: =Wages!O113 -> Medical Aid Scheme | M36: =Wages!C130 -> Medical Aid Scheme
A37: =Wages!G114 -> Loan Instalment | B37: =Wages!H114 -> 0 | E37: =Wages!K114 -> Loan Instalment | F37: =Wages!L114 -> 0 | I37: =Wages!O114 -> Loan Instalment | J37: =Wages!P114 -> 0 | M37: =Wages!C131 -> Loan Instalment | N37: =Wages!D131 -> 0
A38: =Wages!G115 -> Absence Deduction | B38: =Wages!H115 -> 0 | E38: =Wages!K115 -> Absence Deduction | F38: =Wages!L115 -> 0 | I38: =Wages!O115 -> Absence Deduction | J38: =Wages!P115 -> 0 | M38: =Wages!C132 -> Absence Deduction | N38: =Wages!D132 -> 0
A39: =Wages!G116 -> Total Deductions | B39: =Wages!H116 -> 0 | E39: =Wages!K116 -> Total Deductions | F39: =Wages!L116 -> 0 | I39: =Wages!O116 -> Total Deductions | J39: =Wages!P116 -> 0 | M39: =Wages!C133 -> Total Deductions | N39: =Wages!D133 -> 0
A40: =Wages!G117 -> Loan Balance | B40: =Wages!H117 -> 0 | E40: =Wages!K117 -> Loan Balance | F40: =Wages!L117 -> 0 | I40: =Wages!O117 -> Loan Balance | J40: =Wages!P117 -> 0 | M40: =Wages!C134 -> Loan Balance | N40: =Wages!D134 -> 0
A42: =Wages!G119 -> Net Pay for the Month | C42: =SUM(C32+C33+C35-B39) -> 150000 | E42: =Wages!K119 -> Net Pay for the Month | G42: =SUM(G32+G33+G35-F39) -> 0 | I42: =Wages!O119 -> Net Pay for the Month | K42: =SUM(K32+K33+K35-J39) -> 0 | M42: =Wages!C136 -> Net Pay for the Month | O42: =SUM(O32+O33+O35-N39) -> 0
A43: =Wages!G120 -> Net Pay mid and end of Month | C43: =C42/2 -> 75000 | E43: =Wages!K120 -> Net Pay mid and end of Month | G43: =G42/2 -> 0 | I43: =Wages!O120 -> Net Pay mid and end of Month | K43: =K42/2 -> 0 | M43: =Wages!C137 -> Net Pay mid and end of Month | O43: =O42/2 -> 0
A48: Citi-Nati Shopping Centre
A49: =Wages!G123 -> Name of Employee: | B49: =Wages!H123 -> Yankho Gulani
A50: =Wages!G124 -> Employee Number: | C50: =Wages!I124 -> CITI27
A51: =Wages!G125 -> Payslip for the Month: | C51: =$C$13 -> January 2026
A52: =Wages!G126 -> Gross Salary | C52: =Wages!I126 -> 120000
A53: =Wages!G127 -> Overtime Claim | C53: =Wages!I127 -> 0
A54: =Wages!G128 -> P.A.Y.E | B54: =Wages!H128 -> 0
A55: =Wages!G129 -> Xmas Gift/Leave Pay | C55: =Wages!I129 -> 0
A56: =Wages!G130 -> Medical Aid Scheme | B56: =Wages!H131 -> 0
A57: =Wages!G131 -> Loan Instalment | B57: =Wages!H132 -> 0
A58: =Wages!G132 -> Absence Deduction | B58: =Wages!H133 -> 0
A59: =Wages!G133 -> Total Deductions | B59: =Wages!H133 -> 0
A60: =Wages!G134 -> Loan Balance | B60: =Wages!H134 -> 0
A62: =Wages!G136 -> Net Pay for the Month | C62: =Wages!I136 -> 120000
A63: =Wages!G137 -> Net Pay mid and end of Month | C63: =Wages!I137 -> 60000
A66: List of Employees and their dues
A67: Eployee Number | B67: Name | D67: Month | E67: Loan Deduction | F67: Loan Outstanding | G67: Amount Due | H67: Accrued Interest To-Date
A68: =C12 -> CITI19 | B68: =B11 -> Martin Kandalama | D68: =$C$13 -> January 2026 | E68: =B21 -> 0 | F68: =B22 -> 0 | G68: =C25 -> 35000 | H68: =IF(Wages!V239="N/A",0,Wages!V239) -> 0
A69: =G12 -> CITI20 | B69: =F11 -> Daniel Mponda | D69: =$C$13 -> January 2026 | E69: =F21 -> 0 | F69: =F22 -> 0 | G69: =G25 -> 35000 | H69: =IF(Wages!V240="N/A",0,Wages!V240) -> 0
A70: =K12 -> CITI21 | B70: =J11 -> Elizabeth Kabudula | D70: =$C$13 -> January 2026 | E70: =J21 -> 0 | F70: =J22 -> 0 | G70: =K25 -> 10000 | H70: =IF(Wages!V241="N/A",0,Wages!V241) -> 0
A71: =O12 -> CITI22 | B71: =N11 -> vacant | D71: =$C$13 -> January 2026 | E71: =N21 -> 0 | F71: =N22 -> 0 | G71: =O25 -> 0 | H71: =IF(Wages!V242="N/A",0,Wages!V242) -> 0
A72: =C30 -> CITI23 | B72: =B29 -> William Mahinya | D72: =$C$13 -> January 2026 | E72: =B39 -> 0 | F72: =B40 -> 0 | G72: =C43 -> 75000 | H72: =IF(Wages!V244="N/A",0,Wages!V244) -> 0
A73: =G30 -> CITI24 | B73: =F29 -> vacant | D73: =$C$13 -> January 2026 | E73: =F39 -> 0 | F73: =F40 -> 0 | G73: =G43 -> 0 | H73: =IF(Wages!V245="N/A",0,Wages!V245) -> 0
A74: =K30 -> CITI25 | B74: =J29 | D74: =$C$13 -> January 2026 | E74: =J39 -> 0 | F74: =J40 -> 0 | G74: =K43 -> 0 | H74: =IF(Wages!V246="N/A",0,Wages!V246) -> 0
A75: =O30 -> CITI26 | B75: =N29 -> vacant | D75: =$C$13 -> January 2026 | E75: =N39 -> 0 | F75: =N40 -> 0 | G75: =O43 -> 0 | H75: =IF(Wages!V247="N/A",0,Wages!V247) -> 0
A76: =C50 -> CITI27 | B76: =B49 -> Yankho Gulani | D76: =$C$13 -> January 2026 | E76: =B59 -> 0 | F76: =B60 -> 0 | G76: =C63 -> 60000 | H76: =IF(Wages!V248="N/A",0,Wages!V248) -> 0
A77: Totals | E77: =SUM(E68:E75) -> 0 | F77: =SUM(F68:F75) -> 0 | G77: =SUM(G68:G76) -> 215000 | H77: =SUM(H68:I76) -> 0
A79: Totals from Shop Workers | G79: ='Shop-Workers'!G145 -> 752000
A81: Totals to Pay | B81: =Wages!B8 -> Mid | C81: =Wages!E18 -> January 2026 | G81: =G77+'Shop-Workers'!G145 -> 967000

Sheet Shop-Workers
A1: Wages for Supermarket, Stop-Over and Restaurant
E3: Half Pay | G3: Full Pay
A4: Gross Wages | E4: =G4/2 -> 575000 | G4: =C14+G14+K14+O14+C32+G32+K32+O32+C50+G50+K50+O50+C68+G68+K68+O68+C86 -> 1150000
A5: P.A.Y.E. | E5: =G5/2 -> 0 | G5: =B16+F16+J16+N16+B34+F34+J34+N34+B52+F52+J52+N52+B70+F70+J70+N70+B88 -> 0
A6: Christmas Gift/Leave Pay | E6: =G6/2 -> 0 | G6: =C17+G17+K17+O17+C35+G35+K35+O35+C53+G53+K53+O53+C71+G71+K71+O71+C89 -> 0
A7: Total Deductions for the Month | E7: =G7/2 -> 0 | G7: =B21+F21+J21+N21+B39+F39+J39+N39+B57+F57+J57+N57+B75+F75+J75+N75+B93 -> 0
A8: Total Wages for this Month (net of P.A.Y.E) | E8: =E4+E6-E7 -> 575000 | G8: =G4+G6-G7 -> 1150000
A10: Citi-Nati Shopping Centre | E10: Citi-Nati Shopping Centre | I10: Citi-Nati Shopping Centre | M10: Citi-Nati Shopping Centre
A11: =Wages!C16 -> Name of Employee: | B11: =Wages!D16 -> Sapulene Mkulichi | E11: =A11 -> Name of Employee: | F11: =Wages!H16 -> George Matemba | I11: Name of Employee: | J11: =Wages!L16 -> Alinafe James | M11: Name of Employee: | N11: =Wages!P16 -> Chimwemwe Banda
A12: Employee Number: | C12: =Wages!E17 -> CITI01 | E12: Employee Number: | G12: =Wages!I17 -> CITI02 | I12: Employee Number: | K12: =Wages!M17 -> CITI04 | M12: Employee Number: | O12: =Wages!Q17 -> CITI05
A13: Payslip for the Month: | C13: =Wages!E18 -> January 2026 | E13: Payslip for the Month: | G13: =$C$13 -> January 2026 | I13: Payslip for the Month: | K13: =$C$13 -> January 2026 | M13: Payslip for the Month: | O13: =$C$13 -> January 2026
A14: Gross Salary | C14: =Wages!E19 -> 0 | E14: =E32 -> Gross Salary | G14: =Wages!I19 -> 120000 | I14: =E14 -> Gross Salary | K14: =Wages!M19 -> 80000 | M14: =I14 -> Gross Salary | O14: =Wages!Q19 -> 80000
A15: Overtime Claim | C15: =Wages!E20 -> 0 | E15: Overtime Claim | G15: =Wages!I20 -> 0 | I15: Overtime Claim | K15: =Wages!M20 -> 0 | M15: Overtime Claim | O15: =Wages!Q20 -> 0
A16: P.A.Y.E | B16: =Wages!D21 -> 0 | E16: P.A.Y.E | F16: =Wages!H21 -> 0 | I16: =E16 -> P.A.Y.E | J16: =Wages!L21 -> 0 | M16: =I16 -> P.A.Y.E | N16: =Wages!P21 -> 0
A17: Xmas Gift/Leave Pay | C17: =Wages!E22 -> 0 | E17: Xmas Gift/Leave Pay | G17: =Wages!I22 -> 0 | I17: =E17 -> Xmas Gift/Leave Pay | K17: =Wages!M22 -> 0 | M17: =I17 -> Xmas Gift/Leave Pay | O17: =Wages!Q22 -> 0
A18: Medical Aid Scheme | B18: =Wages!D23 | E18: Medical Aid Scheme | F18: =Wages!H23 | I18: Medical Aid Scheme | J18: =Wages!L23 -> 0 | M18: Medical Aid Scheme | N18: =Wages!P23 -> 0
A19: Loan Instalment | B19: =Wages!D24 -> 0 | E19: Loan Instalment | F19: =Wages!H24 -> 0 | I19: =E19 -> Loan Instalment | J19: =Wages!L24 -> 0 | M19: =I19 -> Loan Instalment | N19: =Wages!P24 -> 0
A20: Absence Deduction | B20: =Wages!D25 -> 0 | E20: Absence Deduction | F20: =Wages!H25 -> 0 | I20: =E20 -> Absence Deduction | J20: =Wages!L25 -> 0 | M20: =I20 -> Absence Deduction | N20: =Wages!P25 -> 0
A21: Total Deductions | B21: =SUM(B16:B20) -> 0 | E21: Total Deductions | F21: =SUM(F16:F20) -> 0 | I21: =E21 -> Total Deductions | J21: =SUM(J16:J20) -> 0 | M21: =I21 -> Total Deductions | N21: =+N19+N20 -> 0
A22: Loan Balance | B22: =Wages!D27 -> 0 | E22: Loan Balance | F22: =Wages!H27 -> 0 | I22: =E22 -> Loan Balance | J22: =Wages!L27 -> 0 | M22: =I22 -> Loan Balance | N22: =Wages!P27 -> 0
A24: Net Pay for the Month | C24: =SUM(C14+C15+C17-B21) -> 0 | E24: Net Pay for the Month | G24: =SUM(G14+G15+G17-F21) -> 120000 | I24: Net Pay for the Month | K24: =SUM(K14+K15+K17-J21) -> 80000 | M24: Net Pay for the Month | O24: =SUM(O14+O15+O17-N21) -> 80000
A25: Net Pay mid and end of Month | C25: =C24/2 -> 0 | E25: =A25 -> Net Pay mid and end of Month | G25: =G24/2 -> 60000 | I25: =A25 -> Net Pay mid and end of Month | K25: =K24/2 -> 40000 | M25: =A25 -> Net Pay mid and end of Month | O25: =O24/2 -> 40000
A28: Citi-Nati Shopping Centre | E28: Citi-Nati Shopping Centre | I28: Citi-Nati Shopping Centre | M28: Citi-Nati Shopping Centre
A29: Name of Employee: | B29: =Wages!D34 -> vacant | E29: Name of Employee: | F29: =Wages!H34 -> Maureen Ulaya | I29: =E29 -> Name of Employee: | J29: =Wages!L34 -> Francis Chatsweka | M29: Name of Employee: | N29: =Wages!P34 -> Stenala Mponda
A30: Employee Number: | C30: =Wages!E35 -> CITI06 | E30: Employee Number: | G30: =Wages!I35 -> CITI07 | I30: Employee Number: | K30: =Wages!M35 -> CITI08 | M30: Employee Number: | O30: =Wages!Q35 -> CITI09
A31: Payslip for the Month: | C31: =$C$13 -> January 2026 | E31: Payslip for the Month: | G31: =$C$13 -> January 2026 | I31: Payslip for the Month: | K31: =$C$13 -> January 2026 | M31: Payslip for the Month: | O31: =$C$13 -> January 2026
A32: Gross Salary | C32: =Wages!E37 -> 0 | E32: =A32 -> Gross Salary | G32: =Wages!I37 -> 80000 | I32: =E32 -> Gross Salary | K32: =Wages!M37 -> 70000 | M32: =I32 -> Gross Salary | O32: =Wages!Q37 -> 70000
A33: Overtime Claim | C33: =Wages!E38 -> 0 | E33: Overtime Claim | G33: =Wages!I38 -> 0 | I33: Overtime Claim | K33: =Wages!M38 -> 0 | M33: Overtime Claim | O33: =Wages!Q38 -> 0
A34: P.A.Y.E | B34: =Wages!D39 -> 0 | E34: P.A.Y.E | F34: =Wages!H39 -> 0 | I34: =E34 -> P.A.Y.E | J34: =Wages!L39 -> 0 | M34: =I16 -> P.A.Y.E | N34: =Wages!P39 -> 0
A35: =A17 -> Xmas Gift/Leave Pay | C35: =Wages!E40 -> 0 | E35: =A17 -> Xmas Gift/Leave Pay | G35: =Wages!I40 -> 0 | I35: =E35 -> Xmas Gift/Leave Pay | K35: =Wages!M40 -> 0 | M35: =I17 -> Xmas Gift/Leave Pay | O35: =Wages!Q40 -> 0
A36: Medical Aid Scheme | B36: =Wages!D41 -> 0 | E36: Medical Aid Scheme | I36: Medical Aid Scheme | M36: Medical Aid Scheme
A37: =A19 -> Loan Instalment | B37: =Wages!D42 -> 0 | E37: =A19 -> Loan Instalment | F37: =Wages!H42 -> 0 | I37: =E37 -> Loan Instalment | J37: =Wages!L42 -> 0 | M37: =I19 -> Loan Instalment | N37: =Wages!P42 -> 0
A38: =A20 -> Absence Deduction | B38: =Wages!D43 -> 0 | E38: =A20 -> Absence Deduction | F38: =Wages!H43 -> 0 | I38: =E38 -> Absence Deduction | J38: =Wages!L43 -> 0 | M38: =I20 -> Absence Deduction | N38: =Wages!P43 -> 0
A39: =A21 -> Total Deductions | B39: =SUM(B34:B38) -> 0 | E39: =A21 -> Total Deductions | F39: =SUM(F34:F38) -> 0 | I39: =E21 -> Total Deductions | J39: =SUM(J34:J38) -> 0 | M39: =I21 -> Total Deductions | N39: =SUM(N34:N38) -> 0
A40: =A22 -> Loan Balance | B40: =Wages!D45 -> 0 | E40: =A22 -> Loan Balance | F40: =Wages!H45 -> 0 | I40: =E40 -> Loan Balance | J40: =Wages!L45 -> 0 | M40: =I22 -> Loan Balance | N40: =Wages!P45 -> 0
A42: Net Pay for the Month | C42: =SUM(C32+C33+C35-B39) -> 0 | E42: Net Pay for the Month | G42: =SUM(G32+G33+G35-F39) -> 80000 | I42: Net Pay for the Month | K42: =SUM(K32+K33+K35-J39) -> 70000 | M42: Net Pay for the Month | O42: =SUM(O32+O33+O35-N39) -> 70000
A43: Net Pay mid and end of Month | C43: =C42/2 -> 0 | E43: Net Pay mid and end of Month | G43: =G42/2 -> 40000 | I43: =E43 -> Net Pay mid and end of Month | K43: =K42/2 -> 35000 | M43: =E43 -> Net Pay mid and end of Month | O43: =O42/2 -> 35000
A46: Citi-Nati Shopping Centre | E46: Citi-Nati Shopping Centre | I46: Citi-Nati Shopping Centre | M46: Citi-Nati Shopping Centre
A47: Name of Employee: | B47: =Wages!D52 -> Simikizani Siki | E47: =A47 -> Name of Employee: | F47: =Wages!H52 -> Amini Wecha | I47: Name of Employee: | J47: =Wages!L52 -> Tayifolo Mandowa | M47: Name of Employee: | N47: =Wages!P52 -> Monica George
A48: Employee Number: | C48: =Wages!E53 -> CITI10 | E48: Employee Number: | G48: =Wages!I53 -> CITI11 | I48: Employee Number: | K48: =Wages!M53 -> CITI12 | M48: Employee Number: | O48: =Wages!Q53 -> CITI13
A49: Payslip for the Month: | C49: =$C$13 -> January 2026 | E49: Payslip for the Month: | G49: =$C$13 -> January 2026 | I49: Payslip for the Month: | K49: =$C$13 -> January 2026 | M49: Payslip for the Month: | O49: =$C$13 -> January 2026
A50: Gross Salary | C50: =Wages!E55 -> 70000 | E50: =A50 -> Gross Salary | G50: =Wages!I55 -> 70000 | I50: =E50 -> Gross Salary | K50: =Wages!M55 -> 120000 | M50: =I50 -> Gross Salary | O50: =Wages!Q55 -> 80000
A51: Overtime Claim | C51: =Wages!E56 -> 0 | E51: Overtime Claim | G51: =Wages!I56 -> 0 | I51: Overtime Claim | K51: =Wages!M56 -> 0 | M51: Overtime Claim | O51: =Wages!Q56 -> 0
A52: P.A.Y.E | B52: =Wages!D57 -> 0 | E52: =A52 -> P.A.Y.E | F52: =Wages!H57 -> 0 | I52: =M34 -> P.A.Y.E | J52: =Wages!L57 -> 0 | M52: =A126 -> CITI06 | N52: =Wages!P57 -> 0
A53: =E35 -> Xmas Gift/Leave Pay | C53: =Wages!E58 -> 0 | E53: =A53 -> Xmas Gift/Leave Pay | G53: =Wages!I58 -> 0 | I53: =M35 -> Xmas Gift/Leave Pay | K53: =Wages!M58 -> 0 | M53: =I53 -> Xmas Gift/Leave Pay | O53: =Wages!Q58 -> 0
A54: Medical Aid Scheme | E54: Medical Aid Scheme | I54: Medical Aid Scheme | M54: Medical Aid Scheme
A55: =E37 -> Loan Instalment | B55: =Wages!D60 -> 0 | E55: =A55 -> Loan Instalment | F55: =Wages!H60 -> 0 | I55: =M37 -> Loan Instalment | J55: =Wages!L60 -> 0 | M55: =I55 -> Loan Instalment | N55: =Wages!P60 -> 0
A56: =E38 -> Absence Deduction | B56: =Wages!D61 -> 0 | E56: =A56 -> Absence Deduction | F56: =Wages!H61 -> 0 | I56: =M38 -> Absence Deduction | J56: =Wages!L61 -> 0 | M56: =I56 -> Absence Deduction | N56: =Wages!P61 -> 0
A57: =E39 -> Total Deductions | B57: =SUM(B52:B56) -> 0 | E57: =I39 -> Total Deductions | F57: =SUM(F52:F56) -> 0 | I57: =M39 -> Total Deductions | J57: =SUM(J52:J56) -> 0 | M57: =I57 -> Total Deductions | N57: =+N55+N56 -> 0
A58: =E40 -> Loan Balance | B58: =Wages!D63 -> 0 | E58: =A58 -> Loan Balance | F58: =Wages!H63 -> 0 | I58: =M40 -> Loan Balance | J58: =Wages!L63 -> 0 | M58: =I58 -> Loan Balance | N58: =Wages!P63 -> 0
A60: Net Pay for the Month | C60: =SUM(C50+C51+C53-B57) -> 70000 | E60: Net Pay for the Month | G60: =SUM(G50+G51+G53-F57) -> 70000 | I60: Net Pay for the Month | K60: =SUM(K50+K51+K53-J57) -> 120000 | M60: Net Pay for the Month | O60: =SUM(O50+O51+O53-N57) -> 80000
A61: Net Pay mid and end of Month | C61: =C60/2 -> 35000 | E61: =A61 -> Net Pay mid and end of Month | G61: =G60/2 -> 35000 | I61: =A61 -> Net Pay mid and end of Month | K61: =K60/2 -> 60000 | M61: =A61 -> Net Pay mid and end of Month | O61: =O60/2 -> 40000
A64: Citi-Nati Shopping Centre | E64: Citi-Nati Shopping Centre | I64: Citi-Nati Shopping Centre | M64: Citi-Nati Shopping Centre
A65: Name of Employee: | B65: =Wages!D70 -> Madalitso Baluti | E65: =A65 -> Name of Employee: | F65: =Wages!H70 -> Peter James | I65: Name of Employee: | J65: =Wages!L70 -> Maggie Billy | M65: Name of Employee: | N65: =Wages!P70 -> vacant
A66: Employee Number: | C66: =Wages!E71 -> CITI14 | E66: Employee Number: | G66: =Wages!I71 -> CITI15 | I66: Employee Number: | K66: =Wages!M71 -> CITI16 | M66: Employee Number: | O66: =Wages!Q71 -> CITI17
A67: Payslip for the Month: | C67: =$C$13 -> January 2026 | E67: Payslip for the Month: | G67: =$C$13 -> January 2026 | I67: Payslip for the Month: | K67: =$C$13 -> January 2026 | M67: Payslip for the Month: | O67: =$C$13 -> January 2026
A68: Gross Salary | C68: =Wages!E73 -> 90000 | E68: =A68 -> Gross Salary | G68: =Wages!I73 -> 60000 | I68: =E68 -> Gross Salary | K68: =Wages!M73 -> 80000 | M68: =I68 -> Gross Salary | O68: =Wages!Q73 -> 0
A69: Overtime Claim | C69: =Wages!E74 -> 0 | E69: Overtime Claim | G69: =Wages!I74 -> 0 | I69: Overtime Claim | K69: =Wages!M74 -> 0 | M69: Overtime Claim | O69: =Wages!Q74 -> 0
A70: P.A.Y.E | B70: =Wages!D75 -> 0 | E70: =A70 -> P.A.Y.E | F70: =Wages!H75 -> 0 | I70: =I52 -> P.A.Y.E | J70: =Wages!L75 -> 0 | M70: =M52 -> CITI06 | N70: =Wages!P75 -> 0
A71: =A53 -> Xmas Gift/Leave Pay | C71: =Wages!E76 -> 0 | E71: =A71 -> Xmas Gift/Leave Pay | G71: =Wages!I76 -> 0 | I71: =I53 -> Xmas Gift/Leave Pay | K71: =Wages!M76 -> 0 | M71: =I71 -> Xmas Gift/Leave Pay | O71: =Wages!Q76 -> 0
A72: Medical Aid Scheme | E72: Medical Aid Scheme | I72: Medical Aid Scheme | M72: Medical Aid Scheme
A73: =A55 -> Loan Instalment | B73: =Wages!D78 -> 0 | E73: =A73 -> Loan Instalment | F73: =Wages!H78 -> 0 | I73: =I55 -> Loan Instalment | J73: =Wages!L78 -> 0 | M73: =I73 -> Loan Instalment | N73: =Wages!P78 -> 0
A74: =A56 -> Absence Deduction | B74: =Wages!D79 -> 0 | E74: =A74 -> Absence Deduction | F74: =Wages!I79 -> 0 | I74: =I56 -> Absence Deduction | J74: =Wages!L79 -> 0 | M74: =I74 -> Absence Deduction | N74: =Wages!P79 -> 0
A75: =A57 -> Total Deductions | B75: =SUM(B70:B74) -> 0 | E75: =E57 -> Total Deductions | F75: =SUM(F70:F74) -> 0 | I75: =I57 -> Total Deductions | J75: =SUM(J70:J74) -> 0 | M75: =I75 -> Total Deductions | N75: =+N73+N74 -> 0
A76: =A58 -> Loan Balance | B76: =Wages!D81 -> 0 | E76: =A76 -> Loan Balance | F76: =Wages!H81 -> 0 | I76: =I58 -> Loan Balance | J76: =Wages!L81 -> 0 | M76: =I76 -> Loan Balance | N76: =Wages!P81 -> 0
A78: Net Pay for the Month | C78: =SUM(C68+C69+C71-B75) -> 90000 | E78: Net Pay for the Month | G78: =SUM(G68+G69+G71-F75) -> 60000 | I78: Net Pay for the Month | K78: =SUM(K68+K69+K71-J75) -> 80000 | M78: Net Pay for the Month | O78: =SUM(O68+O69+O71-N75) -> 0
A79: Net Pay mid and end of Month | C79: =C78/2 -> 45000 | E79: =A79 -> Net Pay mid and end of Month | G79: =G78/2 -> 30000 | I79: =A79 -> Net Pay mid and end of Month | K79: =K78/2 -> 40000 | M79: =A79 -> Net Pay mid and end of Month | O79: =O78/2 -> 0
A82: Citi-Nati Shopping Centre | E82: Citi-Nati Shopping Centre | I82: Citi-Nati Shopping Centre | M82: Citi-Nati Shopping Centre
A83: Name of Employee: | B83: =Wages!D88 -> Esnat Adam | E83: Name of Employee: | F83: =Wages!L123 -> Agness Mponda | I83: Name of Employee: | J83: =Wages!P123 -> Elizabeth Chinkono | M83: Name of Employee: | N83: =Wages!D141 -> vacant
A84: Employee Number: | C84: =Wages!E89 -> CITI18 | E84: Employee Number: | G84: =Wages!M124 -> CITI28 | I84: Employee Number: | K84: =Wages!Q124 -> CITI29 | M84: Employee Number: | O84: =Wages!E142 -> CITI30
A85: Payslip for the Month: | C85: =$C$13 -> January 2026 | E85: Payslip for the Month: | G85: =$C$13 -> January 2026 | I85: Payslip for the Month: | K85: =$C$13 -> January 2026 | M85: Payslip for the Month: | O85: =$C$13 -> January 2026
A86: Gross Salary | C86: =Wages!E91 -> 80000 | E86: Gross Salary | G86: =Wages!M126 -> 80000 | I86: Gross Salary | K86: =Wages!Q126 -> 100000 | M86: Gross Salary | O86: =Wages!E144 -> 0
A87: Overtime Claim | C87: =Wages!E92 -> 0 | E87: Overtime Claim | G87: =Wages!M127 -> 0 | I87: Overtime Claim | K87: =Wages!Q127 -> 0 | M87: Overtime Claim | O87: =Wages!E145 -> 0
A88: P.A.Y.E | B88: =Wages!D93 -> 0 | E88: P.A.Y.E | F88: =Wages!L128 -> 0 | I88: P.A.Y.E | J88: =Wages!P128 -> 0 | M88: P.A.Y.E | N88: =Wages!D146 -> 0
A89: =A71 -> Xmas Gift/Leave Pay | C89: =Wages!E94 -> 0 | E89: =E71 -> Xmas Gift/Leave Pay | G89: =Wages!M129 -> 0 | I89: =I71 -> Xmas Gift/Leave Pay | K89: =Wages!Q129 -> 0 | M89: =M71 -> Xmas Gift/Leave Pay
A90: Medical Aid Scheme | E90: Medical Aid Scheme | I90: Medical Aid Scheme | M90: Medical Aid Scheme
A91: =A73 -> Loan Instalment | B91: =Wages!D96 -> 0 | E91: =E73 -> Loan Instalment | F91: =Wages!L131 -> 0 | I91: =I73 -> Loan Instalment | J91: =Wages!P131 -> 0 | M91: =M73 -> Loan Instalment | N91: =Wages!D149 -> 0
A92: =A74 -> Absence Deduction | B92: =Wages!D97 -> 0 | E92: =E74 -> Absence Deduction | F92: =Wages!L132 -> 0 | I92: =I74 -> Absence Deduction | J92: =Wages!P132 -> 0 | M92: =M74 -> Absence Deduction | N92: =Wages!D150 -> 0
A93: =A75 -> Total Deductions | B93: =Wages!D98 -> 0 | E93: =E75 -> Total Deductions | F93: =Wages!L133 -> 0 | I93: =I75 -> Total Deductions | J93: =Wages!P133 -> 0 | M93: =M75 -> Total Deductions | N93: =Wages!D151 -> 0
A94: =A76 -> Loan Balance | B94: =Wages!D99 -> 0 | E94: =E76 -> Loan Balance | F94: =Wages!L134 -> 0 | I94: =I76 -> Loan Balance | J94: =Wages!P134 -> 0 | M94: =M76 -> Loan Balance | N94: =Wages!D152 -> 0
A96: Net Pay for the Month | C96: =Wages!E101 -> 80000 | E96: Net Pay for the Month | G96: =Wages!M136 -> 80000 | I96: Net Pay for the Month | K96: =Wages!Q136 -> 100000 | M96: Net Pay for the Month | O96: =Wages!E154 -> 0
A97: Net Pay mid and end of Month | C97: =Wages!E102 -> 40000 | E97: Net Pay mid and end of Month | G97: =Wages!M137 -> 40000 | I97: Net Pay mid and end of Month | K97: =Wages!Q137 -> 50000 | M97: Net Pay mid and end of Month | O97: =Wages!E155 -> 0
A100: Citi-Nati Shopping Centre | E100: Citi-Nati Shopping Centre | I100: Citi-Nati Shopping Centre
A101: Name of Employee: | B101: =Wages!H141 -> Dancan Botha | E101: Name of Employee: | F101: =Wages!L141 -> Ibrahim Amadu | I101: Name of Employee: | J101: =Wages!P141 -> vacant
A102: Employee Number: | C102: =Wages!I142 -> CITI30 | E102: Employee Number: | G102: =Wages!M142 -> CITI31 | I102: Employee Number: | K102: =Wages!Q142 -> CITI03
A103: Payslip for the Month: | C103: =$C$13 -> January 2026 | E103: Payslip for the Month: | G103: =$C$13 -> January 2026 | I103: Payslip for the Month: | K103: =$C$13 -> January 2026
A104: Gross Salary | C104: =Wages!I144 -> 94000 | E104: Gross Salary | G104: =Wages!M144 -> 80000 | I104: Gross Salary | K104: =Wages!Q144 -> 0
A105: Overtime Claim | C105: =Wages!I145 -> 0 | E105: Overtime Claim | G105: =Wages!M145 -> 0 | I105: Overtime Claim | K105: =Wages!Q145 -> 0
A106: P.A.Y.E | B106: =Wages!H146 -> 0 | E106: P.A.Y.E | F106: =Wages!L146 -> 0 | I106: P.A.Y.E | J106: =Wages!P146 -> 0
A107: =A89 -> Xmas Gift/Leave Pay | C107: =Wages!I147 -> 0 | E107: =E89 -> Xmas Gift/Leave Pay | G107: =Wages!M147 -> 0 | I107: =I89 -> Xmas Gift/Leave Pay | K107: =Wages!Q147 -> 0
A108: Medical Aid Scheme | C108: =Wages!I147 -> 0 | E108: Medical Aid Scheme | I108: Medical Aid Scheme
A109: =A91 -> Loan Instalment | B109: =Wages!H149 -> 0 | E109: =E91 -> Loan Instalment | F109: =Wages!L149 -> 0 | I109: =I91 -> Loan Instalment | J109: =Wages!P149 -> 0
A110: =A92 -> Absence Deduction | B110: =Wages!H150 -> 0 | E110: =E92 -> Absence Deduction | F110: =Wages!L150 -> 0 | I110: =I92 -> Absence Deduction | J110: =Wages!P150 -> 0
A111: =A93 -> Total Deductions | B111: =Wages!H151 -> 0 | E111: =E93 -> Total Deductions | F111: =Wages!L151 -> 0 | I111: =I93 -> Total Deductions | J111: =Wages!P151 -> 0
A112: =A94 -> Loan Balance | B112: =Wages!H152 -> 0 | E112: =E94 -> Loan Balance | F112: =Wages!L152 -> 0 | I112: =I94 -> Loan Balance | J112: =Wages!P152 -> 0
A114: Net Pay for the Month | C114: =Wages!I154 -> 94000 | E114: Net Pay for the Month | G114: =Wages!M154 -> 80000 | I114: Net Pay for the Month | K114: =Wages!Q154 -> 0
A115: Net Pay mid and end of Month | C115: =Wages!I155 -> 47000 | E115: Net Pay mid and end of Month | G115: =Wages!M155 -> 40000 | I115: Net Pay mid and end of Month | K115: =Wages!Q155 -> 0
A119: List of Employees and their dues
A120: Eployee Number | B120: Name | D120: Month | E120: Loan Deduction | F120: Loan Outstanding | G120: Amount Due | H120: Accrued Interest To-Date
A121: =C12 -> CITI01 | B121: =B11 -> Sapulene Mkulichi | D121: =$C$13 -> January 2026 | E121: =B21 -> 0 | F121: =B22 -> 0 | G121: =C25 -> 0 | H121: =IF(Wages!V217="N/A",0,Wages!V217) -> 0
...

Sheet Reengagement Wages 
D12: Wages on retrenchment | F12: Wages as at 30/09/25 | G12: New Wage from 1/10/25 | H12: Occupation | I12: Date Employed | J12: Expiry of Contract
C14: Total Wages Due upon Termination | D14: =D23+D45 -> 2483870 | F14: =F23+F45 -> 1840000 | G14: =G23+G45 -> 1890000
B16: Nyambadwe and Domasi Residence
A17: 1 | B17: Daniel Mponda | D17: 0 | F17: 60000 | G17: 60000 | H17: Nati Villa Guard | I17: 45658 | J17: 46022
A18: =+A17+1 -> 2 | B18: Martin Kandalama | D18: 0 | F18: 70000 | G18: 70000 | H18: Nati Villa Gardener | I18: 45870 | J18: 46022
A19: =+A18+1 -> 3 | B19: Elizabeth Kabudula | D19: 0 | F19: 30000 | G19: 30000 | H19: Nati Villa Cleaner | I19: 45870 | J19: 46022
A20: =+A19+1 -> 4 | B20: Henry Saona | D20: 0 | F20: 150000 | G20: 150000 | H20: Nyambadwe Chef | I20: 45688 | J20: 46022
A21: =+A20+1 -> 5 | B21: James Bongwe | D21: 0 | F21: 100000 | G21: 100000 | H21: Nyambadwe Gardener | I21: 45694 | J21: 46022
A22: =+A21+1 -> 6 | B22: Yankho Gulani | D22: 0 | F22: 100000 | G22: 100000 | H22: Nyambadwe Gardener
B23: Sub-Total | D23: =SUM(D17:D22) -> 0 | F23: =SUM(F17:F22) -> 510000 | G23: =SUM(G17:G22) -> 510000
B25: Citi-Nati Supermarkets, Resturant and Stop Over
A26: 1 | B26: George Matemba | D26: 974200 | F26: 140000 | G26: 140000 | H26: Compnay Administrator | I26: 45931 | J26: 47057
A27: =A26+1 -> 2 | B27: Alinafe James | D27: 157150 | F27: 0 | I27: 45931 | J27: 46326
A28: =A27+1 -> 3 | B28: Francis Nebert | D28: 83183.34 | F28: 0 | I28: 45931 | J28: 46326
A29: =A28+1 -> 4 | B29: Chimwemwe Banda | D29: 151316.67 | F29: 70000 | G29: 90000 | H29: Shop Merchandiser | I29: =Biodata!M23 -> 45204 | J29: 46326
A30: =A29+1 -> 5 | B30: Francis Chatsweka | D30: 126000 | F30: 60000 | G30: 80000 | H30: Shop Assistant | I30: 45931 | J30: 46326
A31: =A30+1 -> 6 | B31: Stenala Mponda | D31: 96800 | F31: 60000 | G31: 70000 | H31: Gardener and Grill Chef | I31: 45931 | J31: 46326
A32: =A31+1 -> 7 | B32: Simikizani Siki | D32: 133800 | F32: 60000 | G32: 70000 | H32: Supermarket Guard | I32: 45931 | J32: 46326
A33: =A32+1 -> 8 | B33: Tayifolo Mandowa | D33: 193600 | F33: 120000 | G33: 120000 | H33: Barman | I33: 45931 | J33: 46326
A34: =A33+1 -> 9 | B34: Monica George | D34: 148800 | F34: 80000 | G34: 90000 | H34: Bartender | I34: 45931 | J34: 46326
A35: =A34+1 -> 10 | B35: Madalitso Baluti | D35: 85320 | F35: 90000 | G35: 90000 | H35: Bartender | I35: 45663 | J35: 46326
A36: =A35+1 -> 11 | B36: Peter James | D36: 94300 | F36: 60000 | G36: 70000 | H36: Supermarket Guard | I36: 45931 | J36: 46326
A37: =A36+1 -> 12 | B37: Maggie Billy | D37: 10800 | F37: 60000 | G37: 80000 | H37: Shop Assistant | I37: 45931 | J37: 46326
A38: =A37+1 -> 13 | B38: Amini Wecha | F38: 60000 | G38: 70000 | H38: Supermarket Cleaner | I38: 45838 | J38: 46022
A39: =A38+1 -> 14 | B39: James Bwanali | D39: 136333.33 | F39: 50000 | G39: 0 | H39: Nati Villa Guard | I39: 43696 | J39: 45626
A40: =A39+1 -> 15 | B40: Agness Mponda | D40: 0 | F40: =Biodata!F73 -> 80000 | G40: 80000 | H40: Chinyonga Shop Assistant | I40: 45853 | J40: 46022
A41: =A40+1 -> 16 | B41: Elizabeth Chinkono | D41: 0 | F41: 100000 | G41: 100000 | H41: Chinyonga Shop Assistant | I41: 45890 | J41: 46022
A42: =A41+1 -> 17 | B42: Maureen Ulaya | D42: 92266.67 | F42: 80000 | G42: 80000 | H42: Domasi Cashier | I42: 45931 | J42: 46326
A43: =A42+1 -> 18 | B43: Leonard Stephano | D43: 0 | F43: 80000 | G43: 70000 | H43: Chinyonga Guard | I43: 45823 | J43: 46022
A44: =A43+1 -> 19 | B44: Ibrahim Amadu | D44: 0 | F44: 80000 | G44: 80000 | H44: Chinyonga Guard | I44: 45839 | J44: 46022
B45: Sub-Total | D45: =SUM(D26:D44) -> 2483870 | F45: =SUM(F26:F44) -> 1330000 | G45: =SUM(G26:G44) -> 1380000
B47: Less already paid | D47: =D27+D28 -> 240333.34
B49: Balance to Pay | D49: =D45-D47 -> 2243536.7
