Workbook

Sheet Sales Input
A1: Use This Sheet to Input Figures For Each Complete Month
A3: Month being reported upon | C3: January | D3: February | E3: March | F3: April | G3: May | H3: June | I3: July | J3: August | K3: September | L3: October | M3: November | N3: December | O3: Totals
A5: POS SALES REPORT
B6: Domasi POS end of Month | C6: 7458030 | D6: 0 | E6: 0 | F6: 0 | G6: 0 | H6: 0 | I6: 0 | J6: 0 | K6: 0 | L6: 0 | M6: 0 | N6: 0 | O6: =SUM(C6:N6) -> 7458030
B7: Chinyonga POS end of Month | C7: 0 | D7: 0 | E7: 0 | F7: 0 | G7: 0 | H7: 0 | I7: 0 | J7: 0 | K7: 0 | L7: 0 | M7: 0 | N7: 0 | O7: =SUM(C7:N7) -> 0
A9: CASH SALES REPORT
A10: 1 | B10: Domasi Supermarket | C10: 5014630 | D10: 0 | E10: 0 | F10: 0 | G10: 0 | H10: 0 | I10: 0 | J10: 4715460 | K10: 0 | L10: 0 | M10: 0 | N10: 0 | O10: =SUM(C10:N10) -> 9730090
A11: =A10+1 -> 2 | B11: Chinyonga Supermarket | C11: 0 | D11: 0 | E11: 0 | F11: 0 | G11: 0 | H11: 0 | I11: 0 | J11: 0 | K11: 0 | L11: 0 | M11: 0 | N11: 0 | O11: =SUM(C11:N11) -> 0
A12: =A11+1 -> 3 | B12: Stop Over | C12: 1354050 | D12: 0 | E12: 0 | F12: 0 | G12: 0 | H12: 0 | I12: 0 | J12: 3303950 | K12: 0 | L12: 0 | M12: 0 | N12: 0 | O12: =SUM(C12:N12) -> 4658000
A13: =A12+1 -> 4 | B13: Nati-Foods | C13: 0 | D13: 0 | E13: 0 | F13: 0 | G13: 0 | H13: 0 | I13: 0 | J13: 0 | K13: 0 | L13: 0 | M13: 0 | N13: 0 | O13: =SUM(C13:N13) -> 0
A14: =A13+1 -> 5 | B14: Braai | C14: 75200 | D14: 0 | E14: 0 | F14: 0 | G14: 0 | H14: 0 | I14: 0 | J14: 120000 | K14: 0 | L14: 0 | M14: 0 | N14: 0 | O14: =SUM(C14:N14) -> 195200
A15: =A14+1 -> 6 | B15: Pool Table | C15: 102500 | D15: 0 | E15: 0 | F15: 0 | G15: 0 | H15: 0 | I15: 0 | J15: 236500 | K15: 0 | L15: 0 | M15: 0 | N15: 0 | O15: =SUM(C15:N15) -> 339000
A16: =A15+1 -> 7 | B16: AirTime | C16: 0 | D16: 0 | E16: 0 | F16: 0 | G16: 0 | H16: 0 | I16: 0 | J16: 0 | K16: 0 | L16: 0 | M16: 0 | N16: 0 | O16: =SUM(C16:N16) -> 0
A17: =A16+1 -> 8 | B17: Student Accommodation | C17: 0 | D17: 0 | E17: 0 | F17: 0 | G17: 0 | H17: 0 | I17: 0 | J17: 460000 | K17: 0 | L17: 0 | M17: 0 | N17: 0 | O17: =SUM(C17:N17) -> 460000
A19: SALES THRU GADGETS REPORT
A20: 1 | B20: Domasi Supermarket
B21: a. Airtel Money | C21: 412090 | D21: 0 | E21: 0 | F21: 0 | G21: 0 | H21: 0 | I21: 0 | J21: 784650 | K21: 0 | L21: 0 | M21: 0 | N21: 0 | O21: =SUM(C21:N21) -> 1196740
B22: b. MO626 | C22: 0 | D22: 0 | E22: 0 | F22: 0 | G22: 0 | H22: 0 | I22: 0 | J22: 205650 | K22: 0 | L22: 0 | M22: 0 | N22: 0 | O22: =SUM(C22:N22) -> 205650
B23: c. TNM Mpamba | C23: 0 | D23: 0 | E23: 0 | F23: 0 | G23: 0 | H23: 0 | I23: 0 | J23: 74900 | K23: 0 | L23: 0 | M23: 0 | N23: 0 | O23: =SUM(C23:N23) -> 74900
B24: d. FDH Bank | C24: 0 | D24: 0 | E24: 0 | F24: 0 | G24: 0 | H24: 0 | I24: 0 | J24: 0 | K24: 0 | L24: 0 | M24: 0 | N24: 0 | O24: =SUM(C24:N24) -> 0
A25: 1 | B25: Chinyonga Supermarket
B26: a. Airtel Money | C26: 0 | D26: 0 | E26: 0 | F26: 0 | G26: 0 | H26: 0 | I26: 0 | J26: 0 | K26: 0 | L26: 0 | M26: 0 | N26: 0 | O26: =SUM(C26:N26) -> 0
B27: b. MO626 | C27: 0 | D27: 0 | E27: 0 | F27: 0 | G27: 0 | H27: 0 | I27: 0 | J27: 0 | K27: 0 | L27: 0 | M27: 0 | N27: 0 | O27: =SUM(C27:N27) -> 0
B28: c. TNM Mpamba | C28: 0 | D28: 0 | E28: 0 | F28: 0 | G28: 0 | H28: 0 | I28: 0 | J28: 0 | K28: 0 | L28: 0 | M28: 0 | N28: 0 | O28: =SUM(C28:N28) -> 0
B29: d. FDH Bank | C29: 0 | D29: 0 | E29: 0 | F29: 0 | G29: 0 | H29: 0 | I29: 0 | J29: 0 | K29: 0 | L29: 0 | M29: 0 | N29: 0 | O29: =SUM(C29:N29) -> 0
A30: 2 | B30: Stop Over
B31: a. Airtel Money | C31: 600550 | D31: 0 | E31: 0 | F31: 0 | G31: 0 | H31: 0 | I31: 0 | J31: 1526450 | K31: 0 | L31: 0 | M31: 0 | N31: 0 | O31: =SUM(C31:N31) -> 2127000
B32: b. MO626 | C32: 0 | D32: 0 | E32: 0 | F32: 0 | G32: 0 | H32: 0 | I32: 0 | J32: 566700 | K32: 0 | L32: 0 | M32: 0 | N32: 0 | O32: =SUM(C32:N32) -> 566700
B33: c. TNM Mpamba | C33: 0 | D33: 0 | E33: 0 | F33: 0 | G33: 0 | H33: 0 | I33: 0 | J33: 223700 | K33: 0 | L33: 0 | M33: 0 | N33: 0 | O33: =SUM(C33:N33) -> 223700
B34: d. FDH Bank | C34: 0 | D34: 0 | E34: 0 | F34: 0 | G34: 0 | H34: 0 | I34: 0 | J34: 0 | K34: 0 | L34: 0 | M34: 0 | N34: 0 | O34: =SUM(C34:N34) -> 0
A35: 3 | B35: Nati-Foods
B36: a. Airtel Money | C36: 0 | D36: 0 | E36: 0 | F36: 0 | G36: 0 | H36: 0 | I36: 0 | J36: 0 | K36: 0 | L36: 0 | M36: 0 | N36: 0 | O36: =SUM(C36:N36) -> 0
B37: b. MO626 | C37: 0 | D37: 0 | E37: 0 | F37: 0 | G37: 0 | H37: 0 | I37: 0 | J37: 0 | K37: 0 | L37: 0 | M37: 0 | N37: 0 | O37: =SUM(C37:N37) -> 0
B38: c. TNM Mpamba | C38: 0 | D38: 0 | E38: 0 | F38: 0 | G38: 0 | H38: 0 | I38: 0 | J38: 0 | K38: 0 | L38: 0 | M38: 0 | N38: 0 | O38: =SUM(C38:N38) -> 0
B39: d. FDH Bank | C39: 0 | D39: 0 | E39: 0 | F39: 0 | G39: 0 | H39: 0 | I39: 0 | J39: 0 | K39: 0 | L39: 0 | M39: 0 | N39: 0 | O39: =SUM(C39:N39) -> 0
A40: 4 | B40: Braai
B41: a. Airtel Money | C41: 0 | D41: 0 | E41: 0 | F41: 0 | G41: 0 | H41: 0 | I41: 0 | J41: 0 | K41: 0 | L41: 0 | M41: 0 | N41: 0 | O41: =SUM(C41:N41) -> 0
B42: b. MO626 | C42: 0 | D42: 0 | E42: 0 | F42: 0 | G42: 0 | H42: 0 | I42: 0 | J42: 0 | K42: 0 | L42: 0 | M42: 0 | N42: 0 | O42: =SUM(C42:N42) -> 0
B43: c. TNM Mpamba | C43: 0 | D43: 0 | E43: 0 | F43: 0 | G43: 0 | H43: 0 | I43: 0 | J43: 0 | K43: 0 | L43: 0 | M43: 0 | N43: 0 | O43: =SUM(C43:N43) -> 0
B44: d. FDH Bank | C44: 0 | D44: 0 | E44: 0 | F44: 0 | G44: 0 | H44: 0 | I44: 0 | J44: 0 | K44: 0 | L44: 0 | M44: 0 | N44: 0 | O44: =SUM(C44:N44) -> 0
A45: 5 | B45: Pool Table
B46: a. Airtel Money | C46: 0 | D46: 0 | E46: 0 | F46: 0 | G46: 0 | H46: 0 | I46: 0 | J46: 0 | K46: 0 | L46: 0 | M46: 0 | N46: 0 | O46: =SUM(C46:N46) -> 0
B47: b. MO626 | C47: 0 | D47: 0 | E47: 0 | F47: 0 | G47: 0 | H47: 0 | I47: 0 | J47: 0 | K47: 0 | L47: 0 | M47: 0 | N47: 0 | O47: =SUM(C47:N47) -> 0
B48: c. TNM Mpamba | C48: 0 | D48: 0 | E48: 0 | F48: 0 | G48: 0 | H48: 0 | I48: 0 | J48: 0 | K48: 0 | L48: 0 | M48: 0 | N48: 0 | O48: =SUM(C48:N48) -> 0
B49: d. FDH Bank | C49: 0 | D49: 0 | E49: 0 | F49: 0 | G49: 0 | H49: 0 | I49: 0 | J49: 0 | K49: 0 | L49: 0 | M49: 0 | N49: 0 | O49: =SUM(C49:N49) -> 0
A50: 6 | B50: AirTime | O50: =SUM(C50:N50) -> 0
B51: a. Airtel Money | C51: 0 | D51: 0 | E51: 0 | F51: 0 | G51: 0 | H51: 0 | I51: 0 | J51: 0 | K51: 0 | L51: 0 | M51: 0 | N51: 0 | O51: =SUM(C51:N51) -> 0
B52: b. MO626 | C52: 0 | D52: 0 | E52: 0 | F52: 0 | G52: 0 | H52: 0 | I52: 0 | J52: 0 | K52: 0 | L52: 0 | M52: 0 | N52: 0 | O52: =SUM(C52:N52) -> 0
B53: c. TNM Mpamba | C53: 0 | D53: 0 | E53: 0 | F53: 0 | G53: 0 | H53: 0 | I53: 0 | J53: 0 | K53: 0 | L53: 0 | M53: 0 | N53: 0 | O53: =SUM(C53:N53) -> 0
B54: d. FDH Bank | C54: 0 | D54: 0 | E54: 0 | F54: 0 | G54: 0 | H54: 0 | I54: 0 | J54: 0 | K54: 0 | L54: 0 | M54: 0 | N54: 0 | O54: =SUM(C54:N54) -> 0
A55: 7 | B55: Student Accomodation
B56: a. Airtel Money | C56: 0 | D56: 0 | E56: 0 | F56: 0 | G56: 0 | H56: 0 | I56: 0 | J56: 0 | K56: 0 | L56: 0 | M56: 0 | N56: 0 | O56: =SUM(C56:N56) -> 0
B57: b. MO626 | C57: 0 | D57: 0 | E57: 0 | F57: 0 | G57: 0 | H57: 0 | I57: 0 | J57: 0 | K57: 0 | L57: 0 | M57: 0 | N57: 0 | O57: =SUM(C57:N57) -> 0
B58: c. TNM Mpamba | C58: 0 | D58: 0 | E58: 0 | F58: 0 | G58: 0 | H58: 0 | I58: 0 | J58: 0 | K58: 0 | L58: 0 | M58: 0 | N58: 0 | O58: =SUM(C58:N58) -> 0
B59: d. FDH Bank | C59: 0 | D59: 0 | E59: 0 | F59: 0 | G59: 0 | H59: 0 | I59: 0 | J59: 0 | K59: 0 | L59: 0 | M59: 0 | N59: 0 | O59: =SUM(C59:N59) -> 0
A61: CASH DEPOSITS TO ACCOUNTS REPORT | O61: =SUM(C61:N61) -> 0
A62: 1 | B62: NBM | C62: 0 | D62: 0 | E62: 0 | F62: 0 | G62: 0 | H62: 0 | I62: 0 | J62: 0 | K62: 0 | L62: 0 | M62: 0 | N62: 0 | O62: =SUM(C62:N62) -> 0
A63: 2 | B63: FDH Bank | C63: 6471180 | D63: 0 | E63: 0 | F63: 0 | G63: 0 | H63: 0 | I63: 0 | J63: 8255910 | K63: 0 | L63: 0 | M63: 0 | N63: 0 | O63: =SUM(C63:N63) -> 14727090
A64: 2 | B64: Airtel Money | C64: 0 | D64: 0 | E64: 0 | F64: 0 | G64: 0 | H64: 0 | I64: 0 | J64: 0 | K64: 0 | L64: 0 | M64: 0 | N64: 0 | O64: =SUM(C64:N64) -> 0
A65: 3 | B65: TNM Mpamba | C65: 0 | D65: 0 | E65: 0 | F65: 0 | G65: 0 | H65: 0 | I65: 0 | J65: 0 | K65: 0 | L65: 0 | M65: 0 | N65: 0 | O65: =SUM(C65:N65) -> 0
A66: 4 | B66: Company Contribution | C66: 0 | D66: 0 | E66: 0 | F66: 0 | G66: 0 | H66: 0 | I66: 0 | J66: 0 | K66: 0 | L66: 0 | M66: 0 | N66: 0 | O66: =SUM(C66:N66) -> 0
A68: GOODS SUPPLIED REPORT
A69: 1 | B69: =+'Suppliers Report'!B6 -> Universal Industries | C69: 208900 | D69: 0 | E69: 0 | F69: 0 | G69: 0 | H69: 0 | I69: 0 | J69: 323500.02 | K69: 0 | L69: 0 | M69: 0 | N69: 0 | O69: =SUM(C69:N69) -> 532400.02
A70: =SUM(A69+1) -> 2 | B70: =+'Suppliers Report'!B7 -> Bottled Water | C70: =SUM(C71:C76) -> 333954 | D70: =SUM(D71:D76) -> 0 | E70: =SUM(E71:E76) -> 0 | F70: =SUM(F71:F76) -> 0 | G70: =SUM(G71:G76) -> 0 | H70: =SUM(H71:H76) -> 0 | I70: =SUM(I71:I76) -> 0 | J70: =SUM(J71:J76) -> 0 | ... N70: =SUM(N71:N76) -> 0 | O70: =SUM(C70:N70) -> 333954
B71: i. Aqua Pure | C71: 191954 | D71: 0 | E71: 0 | F71: 0 | G71: 0 | H71: 0 | I71: 0 | J71: 0 | K71: 0 | L71: 0 | M71: 0 | N71: 0 | O71: =SUM(C71:N71) -> 191954
B72: ii. Cool Drop | C72: 0 | D72: 0 | E72: 0 | F72: 0 | G72: 0 | H72: 0 | I72: 0 | J72: 0 | K72: 0 | L72: 0 | M72: 0 | N72: 0 | O72: =SUM(C72:N72) -> 0
B73: iii. Kick Water | C73: 0 | D73: 0 | E73: 0 | F73: 0 | G73: 0 | H73: 0 | I73: 0 | J73: 0 | K73: 0 | L73: 0 | M73: 0 | N73: 0 | O73: =SUM(C73:N73) -> 0
B74: iv. Namadzi Water | C74: 0 | D74: 0 | E74: 0 | F74: 0 | G74: 0 | H74: 0 | I74: 0 | J74: 0 | K74: 0 | L74: 0 | M74: 0 | N74: 0 | O74: =SUM(C74:N74) -> 0
B75: v. Omega Water | C75: 142000 | D75: 0 | E75: 0 | F75: 0 | G75: 0 | H75: 0 | I75: 0 | J75: 0 | K75: 0 | L75: 0 | M75: 0 | N75: 0 | O75: =SUM(C75:N75) -> 142000
B76: vi. Other | C76: 0 | D76: 0 | E76: 0 | F76: 0 | G76: 0 | H76: 0 | I76: 0 | J76: 0 | K76: 0 | L76: 0 | M76: 0 | N76: 0 | O76: =SUM(C76:N76) -> 0
A77: =SUM(A70+1) -> 3 | B77: =+'Suppliers Report'!B8 -> Bakeries | C77: 128300 | D77: 0 | E77: 0 | F77: 0 | G77: 0 | H77: 0 | I77: 0 | J77: 104700 | K77: 0 | L77: 0 | M77: 0 | N77: 0 | O77: =SUM(C77:N77) -> 233000
A78: =SUM(A77+1) -> 4 | B78: =+'Suppliers Report'!B9 -> Suncrest Ltd | C78: 192050 | D78: 0 | E78: 0 | F78: 0 | G78: 0 | H78: 0 | I78: 0 | J78: 0 | K78: 0 | L78: 0 | M78: 0 | N78: 0 | O78: =SUM(C78:N78) -> 192050
A79: =SUM(A78+1) -> 5 | B79: =+'Suppliers Report'!B10 -> Cold Chain | C79: 0 | D79: 0 | E79: 0 | F79: 0 | G79: 0 | H79: 0 | I79: 0 | J79: 0 | K79: 0 | L79: 0 | M79: 0 | N79: 0 | O79: =SUM(C79:N79) -> 0
A80: =SUM(A79+1) -> 6 | B80: =+'Suppliers Report'!B11 -> Unilever | C80: 0 | D80: 0 | E80: 0 | F80: 0 | G80: 0 | H80: 0 | I80: 0 | J80: 0 | K80: 0 | L80: 0 | M80: 0 | N80: 0 | O80: =SUM(C80:N80) -> 0
A81: =SUM(A80+1) -> 7 | B81: =+'Suppliers Report'!B12 -> Rab Processors | C81: 0 | D81: 0 | E81: 0 | F81: 0 | G81: 0 | H81: 0 | I81: 0 | J81: 0 | K81: 0 | L81: 0 | M81: 0 | N81: 0 | O81: =SUM(C81:N81) -> 0
A82: =SUM(A81+1) -> 8 | B82: =+'Suppliers Report'!B13 -> Kwacha Fund | C82: 1464353 | D82: 0 | E82: 0 | F82: 0 | G82: 0 | H82: 0 | I82: 0 | J82: 3323620.5 | K82: 0 | L82: 0 | M82: 0 | N82: 0 | O82: =SUM(C82:N82) -> 4787973.5
A83: =SUM(A82+1) -> 9 | B83: =+'Suppliers Report'!B14 -> Ekhaya Farms | C83: 0 | D83: 0 | E83: 0 | F83: 0 | G83: 0 | H83: 0 | I83: 0 | J83: 0 | K83: 0 | L83: 0 | M83: 0 | N83: 0 | O83: =SUM(C83:N83) -> 0
A84: =SUM(A83+1) -> 10 | B84: =+'Suppliers Report'!B15 -> Central Poultry | C84: 0 | D84: 0 | E84: 0 | F84: 0 | G84: 0 | H84: 0 | I84: 0 | J84: 0 | K84: 0 | L84: 0 | M84: 0 | N84: 0 | O84: =SUM(C84:N84) -> 0
A85: =SUM(A84+1) -> 11 | B85: =+'Suppliers Report'!B16 -> Licorice Investment (Burundi Shop) | C85: 0 | D85: 0 | E85: 0 | F85: 0 | G85: 0 | H85: 0 | I85: 0 | J85: 0 | K85: 0 | L85: 0 | M85: 0 | N85: 0 | O85: =SUM(C85:N85) -> 0
A86: =SUM(A85+1) -> 12 | B86: =+'Suppliers Report'!B17 -> Insco Trading | C86: 0 | D86: 0 | E86: 0 | F86: 0 | G86: 0 | H86: 0 | I86: 0 | J86: 647850 | K86: 0 | L86: 0 | M86: 0 | N86: 0 | O86: =SUM(C86:N86) -> 647850
A87: =SUM(A86+1) -> 13 | B87: =+'Suppliers Report'!B18 -> Chimwemwe Mafeni Trading | C87: 309150 | D87: 0 | E87: 0 | F87: 0 | G87: 0 | H87: 0 | I87: 0 | J87: 736199.99 | K87: 0 | L87: 0 | M87: 0 | N87: 0 | O87: =SUM(C87:N87) -> 1045350
A88: =SUM(A87+1) -> 14 | B88: =+'Suppliers Report'!B19 -> Lilongwe Dairy | C88: 0 | D88: 0 | E88: 0 | F88: 0 | G88: 0 | H88: 0 | I88: 0 | J88: 0 | K88: 0 | L88: 0 | M88: 0 | N88: 0 | O88: =SUM(C88:N88) -> 0
A89: =SUM(A88+1) -> 15 | B89: =+'Suppliers Report'!B20 -> Limbe Products | C89: 0 | D89: 0 | E89: 0 | F89: 0 | G89: 0 | H89: 0 | I89: 0 | J89: 1563800 | K89: 0 | L89: 0 | M89: 0 | N89: 0 | O89: =SUM(C89:N89) -> 1563800
... A93: =SUM(A92+1) -> 19 | B93: =+'Suppliers Report'!B24 -> Siera Shop (Burundi Shop) | C93: 0 | D93: 0 | E93: 0 | F93: 0 | G93: 0 | H93: 0 | I93: 0 | J93: 0 | K93: 0 | L93: 0 | M93: 0 | N93: 0 | O93: =SUM(C93:N93) -> 0
A94: =SUM(A93+1) -> 20 | B94: =+'Suppliers Report'!B25 -> Other Products | C94: =+SUM(C95:C100) -> 88000 | D94: =+SUM(D95:D100) -> 0 | E94: =+SUM(E95:E100) -> 0 | F94: =+SUM(F95:F100) -> 0 | G94: =+SUM(G95:G100) -> 0 | H94: =+SUM(H95:H100) -> 0 | I94: =+SUM(I95:I100) -> 0 | J94: =+SUM(J95:J100) -> 64000 | ... N94: =+SUM(N95:N100) -> 0 | O94: =SUM(C94:N94) -> 152000
B95: i. Naturals Limited | C95: 0 | D95: 0 | E95: 0 | F95: 0 | G95: 0 | H95: 0 | I95: 0 | J95: 0 | K95: 0 | L95: 0 | M95: 0 | N95: 0 | O95: =SUM(C95:N95) -> 0
B96: ii. Osman Foods Ltd | C96: 0 | D96: 0 | E96: 0 | F96: 0 | G96: 0 | H96: 0 | I96: 0 | J96: 0 | K96: 0 | L96: 0 | M96: 0 | N96: 0 | O96: =SUM(C96:N96) -> 0
B97: iii. Chibale Investments | C97: 0 | D97: 0 | E97: 0 | F97: 0 | G97: 0 | H97: 0 | I97: 0 | J97: 0 | K97: 0 | L97: 0 | M97: 0 | N97: 0 | O97: =SUM(C97:N97) -> 0
B98: iv. Harbison Global Trading | C98: 56000 | D98: 0 | E98: 0 | F98: 0 | G98: 0 | H98: 0 | I98: 0 | J98: 0 | K98: 0 | L98: 0 | M98: 0 | N98: 0 | O98: =SUM(C98:N98) -> 56000
B99: v. H Adams | C99: 0 | D99: 0 | E99: 0 | F99: 0 | G99: 0 | H99: 0 | I99: 0 | J99: 0 | K99: 0 | L99: 0 | M99: 0 | N99: 0 | O99: =SUM(C99:N99) -> 0
B100: vi. Other | C100: 32000 | D100: 0 | E100: 0 | F100: 0 | G100: 0 | H100: 0 | I100: 0 | J100: 64000 | K100: 0 | L100: 0 | M100: 0 | N100: 0 | O100: =SUM(C100:N100) -> 96000
A102: a. | B102: Suppliers Paid by Cash-In-Hand
A103: =A69 -> 1 | B103: =B69 -> Universal Industries | C103: 0 | D103: 0 | E103: 0 | F103: 0 | G103: 0 | H103: 0 | I103: 0 | J103: 0 | K103: 0 | L103: 0 | M103: 0 | N103: 0 | O103: =SUM(C103:N103) -> 0
A104: =A70 -> 2 | B104: =B70 -> Bottled Water | C104: 0 | D104: 0 | E104: 0 | F104: 0 | G104: 0 | H104: 0 | I104: 0 | J104: 0 | K104: 0 | L104: 0 | M104: 0 | N104: 0 | O104: =SUM(C104:N104) -> 0
A105: =A77 -> 3 | B105: =B77 -> Bakeries | C105: 0 | D105: 0 | E105: 0 | F105: 0 | G105: 0 | H105: 0 | I105: 0 | J105: 0 | K105: 0 | L105: 0 | M105: 0 | N105: 0 | O105: =SUM(C105:N105) -> 0
A106: =A78 -> 4 | B106: =B78 -> Suncrest Ltd | C106: 0 | D106: 0 | E106: 0 | F106: 0 | G106: 0 | H106: 0 | I106: 0 | J106: 0 | K106: 0 | L106: 0 | M106: 0 | N106: 0 | O106: =SUM(C106:N106) -> 0
A107: =A79 -> 5 | B107: =B79 -> Cold Chain | C107: 0 | D107: 0 | E107: 0 | F107: 0 | G107: 0 | H107: 0 | I107: 0 | J107: 0 | K107: 0 | L107: 0 | M107: 0 | N107: 0 | O107: =SUM(C107:N107) -> 0
A108: =A80 -> 6 | B108: =B80 -> Unilever | C108: 0 | D108: 0 | E108: 0 | F108: 0 | G108: 0 | H108: 0 | I108: 0 | J108: 0 | K108: 0 | L108: 0 | M108: 0 | N108: 0 | O108: =SUM(C108:N108) -> 0
A109: =A81 -> 7 | B109: =B81 -> Rab Processors | C109: 0 | D109: 0 | E109: 0 | F109: 0 | G109: 0 | H109: 0 | I109: 0 | J109: 0 | K109: 0 | L109: 0 | M109: 0 | N109: 0 | O109: =SUM(C109:N109) -> 0
A110: =A82 -> 8 | B110: =B82 -> Kwacha Fund | C110: 0 | D110: 0 | E110: 0 | F110: 0 | G110: 0 | H110: 0 | I110: 0 | J110: 0 | K110: 0 | L110: 0 | M110: 0 | N110: 0 | O110: =SUM(C110:N110) -> 0
...

Sheet Consolidated Sales
A1: Sales Report for Supermarket, Stop-Over and Restaurant
B2: Month of Report | C2: =Summary!C3 -> 8
B4: Sales as at | C4: =IF($C$2=1,I6,IF($C$2=2,I7,IF($C$2=3,I8,IF($C$2=4,I9,IF($C$2=5,I11,IF($C$2=6,I12,IF($C$2=7,I13,IF($C$2=8,I14,IF($C$2=9,I15,IF($C$2=10,I16,IF($C$2=11,I17,IF($C$2=12,I18,IF($C$2=13,"Cummulative Totals","Enter correct month"))))))))))))) -> August 2025 | F4: Calendar | I4: Concanation of Calendar Months and year
F5: December | G5: 2024 | I5: =CONCATENATE(F5,G5) -> December 2024
F6: January | G6: =+G5+1 -> 2025 | I6: =CONCATENATE(F6,G6) -> January 2025
C7: Amount Paid | D7: Outstanding Amount | F7: February | G7: =+G6 -> 2025 | I7: =CONCATENATE(F7,G7) -> February 2025
A8: CASH SALES REPORT | F8: March | G8: =+G7 -> 2025 | I8: =CONCATENATE(F8,G8) -> March 2025
A9: 1 | B9: ='Sales Input'!B10 -> Domasi Supermarket | C9: =IF($C$2=1,'Sales Input'!C10,IF($C$2=2,'Sales Input'!D10,IF($C$2=3,'Sales Input'!E10,IF($C$2=4,'Sales Input'!F10,IF($C$2=5,'Sales Input'!G10,IF($C$2=6,'Sales Input'!H10,IF($C$2=7,'Sales Input'!I10,IF($C$2=8,'Sales Input'!J10,IF($C$2=9,'Sales Input'!K10,IF($C$2=10,'Sales Input'!L10,IF($C$2=11,'Sales Input'!M10,IF($C$2=12,'Sales Input'!N10,IF($C$2=13,'Sales Input'!O10,0))))))))))))) -> 4715460 | F9: April | G9: =+G8 -> 2025 | I9: =CONCATENATE(F9,G9) -> April 2025
A10: =A9+1 -> 2 | B10: ='Sales Input'!B11 -> Chinyonga Supermarket | C10: =IF($C$2=1,'Sales Input'!C11,IF($C$2=2,'Sales Input'!D11,IF($C$2=3,'Sales Input'!E11,IF($C$2=4,'Sales Input'!F11,IF($C$2=5,'Sales Input'!G11,IF($C$2=6,'Sales Input'!H11,IF($C$2=7,'Sales Input'!I11,IF($C$2=8,'Sales Input'!J11,IF('Consolidated Sales'!$C$2=9,'Sales Input'!K11,IF($C$2=10,'Sales Input'!L11,IF($C$2=11,'Sales Input'!M11,IF($C$2=12,'Sales Input'!N11,IF($C$2=13,'Sales Input'!O11,0))))))))))))) -> 0
A11: =A10+1 -> 3 | B11: Stop Over | C11: =IF($C$2=1,'Sales Input'!C12,IF($C$2=2,'Sales Input'!D12,IF($C$2=3,'Sales Input'!E12,IF($C$2=4,'Sales Input'!F12,IF($C$2=5,'Sales Input'!G12,IF($C$2=6,'Sales Input'!H12,IF($C$2=7,'Sales Input'!I12,IF($C$2=8,'Sales Input'!J12,IF($C$2=9,'Sales Input'!K12,IF($C$2=10,'Sales Input'!L12,IF($C$2=11,'Sales Input'!M12,IF($C$2=12,'Sales Input'!N12,IF($C$2=13,'Sales Input'!O12,0))))))))))))) -> 3303950 | F11: May | G11: =+G9 -> 2025 | I11: =CONCATENATE(F11,G11) -> May 2025
A12: =A11+1 -> 4 | B12: Nati-Foods | C12: =IF($C$2=1,'Sales Input'!C13,IF($C$2=2,'Sales Input'!D13,IF($C$2=3,'Sales Input'!E13,IF($C$2=4,'Sales Input'!F13,IF($C$2=5,'Sales Input'!G13,IF($C$2=6,'Sales Input'!H13,IF($C$2=7,'Sales Input'!I13,IF($C$2=8,'Sales Input'!J13,IF($C$2=9,'Sales Input'!K13,IF($C$2=10,'Sales Input'!L13,IF($C$2=11,'Sales Input'!M13,IF($C$2=12,'Sales Input'!N13,IF($C$2=13,'Sales Input'!O13,0))))))))))))) -> 0 | F12: June | G12: =+G11 -> 2025 | I12: =CONCATENATE(F12,G12) -> June 2025
A13: =A12+1 -> 5 | B13: Braai | C13: =IF($C$2=1,'Sales Input'!C14,IF($C$2=2,'Sales Input'!D14,IF($C$2=3,'Sales Input'!E14,IF($C$2=4,'Sales Input'!F14,IF($C$2=5,'Sales Input'!G14,IF($C$2=6,'Sales Input'!H14,IF($C$2=7,'Sales Input'!I14,IF($C$2=8,'Sales Input'!J14,IF($C$2=9,'Sales Input'!K14,IF($C$2=10,'Sales Input'!L14,IF($C$2=11,'Sales Input'!M14,IF($C$2=12,'Sales Input'!N14,IF($C$2=13,'Sales Input'!O14,0))))))))))))) -> 120000 | F13: July | G13: =+G12 -> 2025 | I13: =CONCATENATE(F13,G13) -> July 2025
A14: =A13+1 -> 6 | B14: Pool Table | C14: =IF($C$2=1,'Sales Input'!C15,IF($C$2=2,'Sales Input'!D15,IF($C$2=3,'Sales Input'!E15,IF($C$2=4,'Sales Input'!F15,IF($C$2=5,'Sales Input'!G15,IF($C$2=6,'Sales Input'!H15,IF($C$2=7,'Sales Input'!I15,IF($C$2=8,'Sales Input'!J15,IF($C$2=9,'Sales Input'!K15,IF($C$2=10,'Sales Input'!L15,IF($C$2=11,'Sales Input'!M15,IF($C$2=12,'Sales Input'!N15,IF($C$2=13,'Sales Input'!O15,0))))))))))))) -> 236500 | F14: August | G14: =+G13 -> 2025 | I14: =CONCATENATE(F14,G14) -> August 2025
A15: =A14+1 -> 7 | B15: AirTime | C15: =IF($C$2=1,'Sales Input'!C16,IF($C$2=2,'Sales Input'!D16,IF($C$2=3,'Sales Input'!E16,IF($C$2=4,'Sales Input'!F16,IF($C$2=5,'Sales Input'!G16,IF($C$2=6,'Sales Input'!H16,IF($C$2=7,'Sales Input'!I16,IF($C$2=8,'Sales Input'!J16,IF($C$2=9,'Sales Input'!K16,IF($C$2=10,'Sales Input'!L16,IF($C$2=11,'Sales Input'!M16,IF($C$2=12,'Sales Input'!N16,IF($C$2=13,'Sales Input'!O16,0))))))))))))) -> 0 | F15: September | G15: =+G14 -> 2025 | I15: =CONCATENATE(F15,G15) -> September 2025
A16: =A15+1 -> 8 | B16: Student Accommodation | C16: =IF($C$2=1,'Sales Input'!C17,IF($C$2=2,'Sales Input'!D17,IF($C$2=3,'Sales Input'!E17,IF($C$2=4,'Sales Input'!F17,IF($C$2=5,'Sales Input'!G17,IF($C$2=6,'Sales Input'!H17,IF($C$2=7,'Sales Input'!I17,IF($C$2=8,'Sales Input'!J17,IF($C$2=9,'Sales Input'!K17,IF($C$2=10,'Sales Input'!L17,IF($C$2=11,'Sales Input'!M17,IF($C$2=12,'Sales Input'!N17,IF($C$2=13,'Sales Input'!O17,0))))))))))))) -> 460000 | F16: October | G16: =+G15 -> 2025 | I16: =CONCATENATE(F16,G16) -> October 2025
B17: Total Cash in Hand | C17: =SUM(C9:C16) -> 8835910 | F17: November | G17: =+G16 -> 2025 | I17: =CONCATENATE(F17,G17) -> November 2025
F18: December | G18: =+G17 -> 2025 | I18: =CONCATENATE(F18,G18) -> December 2025
A19: SALES THRU GADGETS REPORT | G19: =G6+1 -> 2026
A20: 1 | B20: ='Sales Input'!B20 -> Domasi Supermarket
B21: a. Airtel Money | C21: =IF($C$2=1,'Sales Input'!C21,IF($C$2=2,'Sales Input'!D21,IF($C$2=3,'Sales Input'!E21,IF($C$2=4,'Sales Input'!F21,IF($C$2=5,'Sales Input'!G21,IF($C$2=6,'Sales Input'!H21,IF($C$2=7,'Sales Input'!I21,IF($C$2=8,'Sales Input'!J21,IF($C$2=9,'Sales Input'!K21,IF($C$2=10,'Sales Input'!L21,IF($C$2=11,'Sales Input'!M21,IF($C$2=12,'Sales Input'!N21,IF($C$2=13,'Sales Input'!O21,0))))))))))))) -> 784650
B22: b. MO626 | C22: =IF($C$2=1,'Sales Input'!C22,IF($C$2=2,'Sales Input'!D22,IF($C$2=3,'Sales Input'!E22,IF($C$2=4,'Sales Input'!F22,IF($C$2=5,'Sales Input'!G22,IF($C$2=6,'Sales Input'!H22,IF($C$2=7,'Sales Input'!I22,IF($C$2=8,'Sales Input'!J22,IF($C$2=9,'Sales Input'!K22,IF($C$2=10,'Sales Input'!L22,IF($C$2=11,'Sales Input'!M22,IF($C$2=12,'Sales Input'!N22,IF($C$2=13,'Sales Input'!O22,0))))))))))))) -> 205650 | G22: password | H22: wag3s
B23: c. TNM Mpamba | C23: =IF($C$2=1,'Sales Input'!C23,IF($C$2=2,'Sales Input'!D23,IF($C$2=3,'Sales Input'!E23,IF($C$2=4,'Sales Input'!F23,IF($C$2=5,'Sales Input'!G23,IF($C$2=6,'Sales Input'!H23,IF($C$2=7,'Sales Input'!I23,IF($C$2=8,'Sales Input'!J23,IF($C$2=9,'Sales Input'!K23,IF($C$2=10,'Sales Input'!L23,IF($C$2=11,'Sales Input'!M23,IF($C$2=12,'Sales Input'!N23,IF($C$2=13,'Sales Input'!O23,0))))))))))))) -> 74900
B24: d. FDH Bank | C24: =IF($C$2=1,'Sales Input'!C24,IF($C$2=2,'Sales Input'!D24,IF($C$2=3,'Sales Input'!E24,IF($C$2=4,'Sales Input'!F24,IF($C$2=5,'Sales Input'!G24,IF($C$2=6,'Sales Input'!H24,IF($C$2=7,'Sales Input'!I24,IF($C$2=8,'Sales Input'!J24,IF($C$2=9,'Sales Input'!K24,IF($C$2=10,'Sales Input'!L24,IF($C$2=11,'Sales Input'!M24,IF($C$2=12,'Sales Input'!N24,IF($C$2=13,'Sales Input'!O24,0))))))))))))) -> 0
B25: Sub-Total | C25: =SUM(C21:C24) -> 1065200
A26: 2 | B26: ='Sales Input'!B25 -> Chinyonga Supermarket
B27: a. Airtel Money | C27: =IF($C$2=1,'Sales Input'!C26,IF($C$2=2,'Sales Input'!D26,IF($C$2=3,'Sales Input'!E26,IF($C$2=4,'Sales Input'!F26,IF($C$2=5,'Sales Input'!G26,IF($C$2=6,'Sales Input'!H26,IF($C$2=7,'Sales Input'!I26,IF($C$2=8,'Sales Input'!J26,IF($C$2=9,'Sales Input'!K26,IF($C$2=10,'Sales Input'!L26,IF($C$2=11,'Sales Input'!M26,IF($C$2=12,'Sales Input'!N26,IF($C$2=13,'Sales Input'!O26,0))))))))))))) -> 0
B28: b. MO626 | C28: =IF($C$2=1,'Sales Input'!C27,IF($C$2=2,'Sales Input'!D27,IF($C$2=3,'Sales Input'!E27,IF($C$2=4,'Sales Input'!F27,IF($C$2=5,'Sales Input'!G27,IF($C$2=6,'Sales Input'!H27,IF($C$2=7,'Sales Input'!I27,IF($C$2=8,'Sales Input'!J27,IF($C$2=9,'Sales Input'!K27,IF($C$2=10,'Sales Input'!L27,IF($C$2=11,'Sales Input'!M27,IF($C$2=12,'Sales Input'!N27,IF($C$2=13,'Sales Input'!O27,0))))))))))))) -> 0
B29: c. TNM Mpamba | C29: =IF($C$2=1,'Sales Input'!C28,IF($C$2=2,'Sales Input'!D28,IF($C$2=3,'Sales Input'!E28,IF($C$2=4,'Sales Input'!F28,IF($C$2=5,'Sales Input'!G28,IF($C$2=6,'Sales Input'!H28,IF($C$2=7,'Sales Input'!I28,IF($C$2=8,'Sales Input'!J28,IF($C$2=9,'Sales Input'!K28,IF($C$2=10,'Sales Input'!L28,IF($C$2=11,'Sales Input'!M28,IF($C$2=12,'Sales Input'!N28,IF($C$2=13,'Sales Input'!O28,0))))))))))))) -> 0
B30: d. FDH Bank | C30: =IF($C$2=1,'Sales Input'!C29,IF($C$2=2,'Sales Input'!D29,IF($C$2=3,'Sales Input'!E29,IF($C$2=4,'Sales Input'!F29,IF($C$2=5,'Sales Input'!G29,IF($C$2=6,'Sales Input'!H29,IF($C$2=7,'Sales Input'!I29,IF($C$2=8,'Sales Input'!J29,IF($C$2=9,'Sales Input'!K29,IF($C$2=10,'Sales Input'!L29,IF($C$2=11,'Sales Input'!M29,IF($C$2=12,'Sales Input'!N29,IF($C$2=13,'Sales Input'!O29,0))))))))))))) -> 0
B31: Sub-Total | C31: =SUM(C27:C30) -> 0
A32: 3 | B32: Stop Over
B33: a. Airtel Money | C33: =IF($C$2=1,'Sales Input'!C31,IF($C$2=2,'Sales Input'!D31,IF($C$2=3,'Sales Input'!E31,IF($C$2=4,'Sales Input'!F31,IF($C$2=5,'Sales Input'!G31,IF($C$2=6,'Sales Input'!H31,IF($C$2=7,'Sales Input'!I31,IF($C$2=8,'Sales Input'!J31,IF($C$2=9,'Sales Input'!K31,IF($C$2=10,'Sales Input'!L31,IF($C$2=11,'Sales Input'!M31,IF($C$2=12,'Sales Input'!N31,IF($C$2=13,'Sales Input'!O31,0))))))))))))) -> 1526450
B34: b. MO626 | C34: =IF($C$2=1,'Sales Input'!C32,IF($C$2=2,'Sales Input'!D32,IF($C$2=3,'Sales Input'!E32,IF($C$2=4,'Sales Input'!F32,IF($C$2=5,'Sales Input'!G32,IF($C$2=6,'Sales Input'!H32,IF($C$2=7,'Sales Input'!I32,IF($C$2=8,'Sales Input'!J32,IF($C$2=9,'Sales Input'!K32,IF($C$2=10,'Sales Input'!L32,IF($C$2=11,'Sales Input'!M32,IF($C$2=12,'Sales Input'!N32,IF($C$2=13,'Sales Input'!O32,0))))))))))))) -> 566700
B35: c. TNM Mpamba | C35: =IF($C$2=1,'Sales Input'!C33,IF($C$2=2,'Sales Input'!D33,IF($C$2=3,'Sales Input'!E33,IF($C$2=4,'Sales Input'!F33,IF($C$2=5,'Sales Input'!G33,IF($C$2=6,'Sales Input'!H33,IF($C$2=7,'Sales Input'!I33,IF($C$2=8,'Sales Input'!J33,IF($C$2=9,'Sales Input'!K33,IF($C$2=10,'Sales Input'!L33,IF($C$2=11,'Sales Input'!M33,IF($C$2=12,'Sales Input'!N33,IF($C$2=13,'Sales Input'!O33,0))))))))))))) -> 223700
B36: d. FDH Bank | C36: =IF($C$2=1,'Sales Input'!C34,IF($C$2=2,'Sales Input'!D34,IF($C$2=3,'Sales Input'!E34,IF($C$2=4,'Sales Input'!F34,IF($C$2=5,'Sales Input'!G34,IF($C$2=6,'Sales Input'!H34,IF($C$2=7,'Sales Input'!I34,IF($C$2=8,'Sales Input'!J34,IF($C$2=9,'Sales Input'!K34,IF($C$2=10,'Sales Input'!L34,IF($C$2=11,'Sales Input'!M34,IF($C$2=12,'Sales Input'!N34,IF($C$2=13,'Sales Input'!O34,0))))))))))))) -> 0
B37: Sub-Total | C37: =SUM(C33:C36) -> 2316850
A38: 4 | B38: Nati-Foods
B39: a. Airtel Money | C39: =IF($C$2=1,'Sales Input'!C36,IF($C$2=2,'Sales Input'!D36,IF($C$2=3,'Sales Input'!E36,IF($C$2=4,'Sales Input'!F36,IF($C$2=5,'Sales Input'!G36,IF($C$2=6,'Sales Input'!H36,IF($C$2=7,'Sales Input'!I36,IF($C$2=8,'Sales Input'!J36,IF($C$2=9,'Sales Input'!K36,IF($C$2=10,'Sales Input'!L36,IF($C$2=11,'Sales Input'!M36,IF($C$2=12,'Sales Input'!N36,IF($C$2=13,'Sales Input'!O36,0))))))))))))) -> 0
B40: b. MO626 | C40: =IF($C$2=1,'Sales Input'!C37,IF($C$2=2,'Sales Input'!D37,IF($C$2=3,'Sales Input'!E37,IF($C$2=4,'Sales Input'!F37,IF($C$2=5,'Sales Input'!G37,IF($C$2=6,'Sales Input'!H37,IF($C$2=7,'Sales Input'!I37,IF($C$2=8,'Sales Input'!J37,IF($C$2=9,'Sales Input'!K37,IF($C$2=10,'Sales Input'!L37,IF($C$2=11,'Sales Input'!M37,IF($C$2=12,'Sales Input'!N37,IF($C$2=13,'Sales Input'!O37,0))))))))))))) -> 0
B41: c. TNM Mpamba | C41: =IF($C$2=1,'Sales Input'!C38,IF($C$2=2,'Sales Input'!D38,IF($C$2=3,'Sales Input'!E38,IF($C$2=4,'Sales Input'!F38,IF($C$2=5,'Sales Input'!G38,IF($C$2=6,'Sales Input'!H38,IF($C$2=7,'Sales Input'!I38,IF($C$2=8,'Sales Input'!J38,IF($C$2=9,'Sales Input'!K38,IF($C$2=10,'Sales Input'!L38,IF($C$2=11,'Sales Input'!M38,IF($C$2=12,'Sales Input'!N38,IF($C$2=13,'Sales Input'!O38,0))))))))))))) -> 0 | E41: `
B42: d. FDH Bank | C42: =IF($C$2=1,'Sales Input'!C39,IF($C$2=2,'Sales Input'!D39,IF($C$2=3,'Sales Input'!E39,IF($C$2=4,'Sales Input'!F39,IF($C$2=5,'Sales Input'!G39,IF($C$2=6,'Sales Input'!H39,IF($C$2=7,'Sales Input'!I39,IF($C$2=8,'Sales Input'!J39,IF($C$2=9,'Sales Input'!K39,IF($C$2=10,'Sales Input'!L39,IF($C$2=11,'Sales Input'!M39,IF($C$2=12,'Sales Input'!N39,IF($C$2=13,'Sales Input'!O39,0))))))))))))) -> 0
B43: Sub-Total | C43: =SUM(C39:C42) -> 0
A44: 5 | B44: Braai
B45: a. Airtel Money | C45: =IF($C$2=1,'Sales Input'!C41,IF($C$2=2,'Sales Input'!D41,IF($C$2=3,'Sales Input'!E41,IF($C$2=4,'Sales Input'!F41,IF($C$2=5,'Sales Input'!G41,IF($C$2=6,'Sales Input'!H41,IF($C$2=7,'Sales Input'!I41,IF($C$2=8,'Sales Input'!J41,IF($C$2=9,'Sales Input'!K41,IF($C$2=10,'Sales Input'!L41,IF($C$2=11,'Sales Input'!M41,IF($C$2=12,'Sales Input'!N41,IF($C$2=13,'Sales Input'!O41,0))))))))))))) -> 0
B46: b. MO626 | C46: =IF($C$2=1,'Sales Input'!C42,IF($C$2=2,'Sales Input'!D42,IF($C$2=3,'Sales Input'!E42,IF($C$2=4,'Sales Input'!F42,IF($C$2=5,'Sales Input'!G42,IF($C$2=6,'Sales Input'!H42,IF($C$2=7,'Sales Input'!I42,IF($C$2=8,'Sales Input'!J42,IF($C$2=9,'Sales Input'!K42,IF($C$2=10,'Sales Input'!L42,IF($C$2=11,'Sales Input'!M42,IF($C$2=12,'Sales Input'!N42,IF($C$2=13,'Sales Input'!O42,0))))))))))))) -> 0
B47: c. TNM Mpamba | C47: =IF($C$2=1,'Sales Input'!C43,IF($C$2=2,'Sales Input'!D43,IF($C$2=3,'Sales Input'!E43,IF($C$2=4,'Sales Input'!F43,IF($C$2=5,'Sales Input'!G43,IF($C$2=6,'Sales Input'!H43,IF($C$2=7,'Sales Input'!I43,IF($C$2=8,'Sales Input'!J43,IF($C$2=9,'Sales Input'!K43,IF($C$2=10,'Sales Input'!L43,IF($C$2=11,'Sales Input'!M43,IF($C$2=12,'Sales Input'!N43,IF($C$2=13,'Sales Input'!O43,0))))))))))))) -> 0
B48: d. FDH Bank | C48: =IF($C$2=1,'Sales Input'!C44,IF($C$2=2,'Sales Input'!D44,IF($C$2=3,'Sales Input'!E44,IF($C$2=4,'Sales Input'!F44,IF($C$2=5,'Sales Input'!G44,IF($C$2=6,'Sales Input'!H44,IF($C$2=7,'Sales Input'!I44,IF($C$2=8,'Sales Input'!J44,IF($C$2=9,'Sales Input'!K44,IF($C$2=10,'Sales Input'!L44,IF($C$2=11,'Sales Input'!M44,IF($C$2=12,'Sales Input'!N44,IF($C$2=13,'Sales Input'!O44,0))))))))))))) -> 0
B49: Sub-Total | C49: =SUM(C45:C48) -> 0
A50: 6 | B50: Pool Table
B51: a. Airtel Money | C51: =IF($C$2=1,'Sales Input'!C46,IF($C$2=2,'Sales Input'!D46,IF($C$2=3,'Sales Input'!E46,IF($C$2=4,'Sales Input'!F46,IF($C$2=5,'Sales Input'!G46,IF($C$2=6,'Sales Input'!H46,IF($C$2=7,'Sales Input'!I46,IF($C$2=8,'Sales Input'!J46,IF($C$2=9,'Sales Input'!K46,IF($C$2=10,'Sales Input'!L46,IF($C$2=11,'Sales Input'!M46,IF($C$2=12,'Sales Input'!N46,IF($C$2=13,'Sales Input'!O46,0))))))))))))) -> 0
B52: b. MO626 | C52: =IF($C$2=1,'Sales Input'!C47,IF($C$2=2,'Sales Input'!D47,IF($C$2=3,'Sales Input'!E47,IF($C$2=4,'Sales Input'!F47,IF($C$2=5,'Sales Input'!G47,IF($C$2=6,'Sales Input'!H47,IF($C$2=7,'Sales Input'!I47,IF($C$2=8,'Sales Input'!J47,IF($C$2=9,'Sales Input'!K47,IF($C$2=10,'Sales Input'!L47,IF($C$2=11,'Sales Input'!M47,IF($C$2=12,'Sales Input'!N47,IF($C$2=13,'Sales Input'!O47,0))))))))))))) -> 0
B53: c. TNM Mpamba | C53: =IF($C$2=1,'Sales Input'!C48,IF($C$2=2,'Sales Input'!D48,IF($C$2=3,'Sales Input'!E48,IF($C$2=4,'Sales Input'!F48,IF($C$2=5,'Sales Input'!G48,IF($C$2=6,'Sales Input'!H48,IF($C$2=7,'Sales Input'!I48,IF($C$2=8,'Sales Input'!J48,IF($C$2=9,'Sales Input'!K48,IF($C$2=10,'Sales Input'!L48,IF($C$2=11,'Sales Input'!M48,IF($C$2=12,'Sales Input'!N48,IF($C$2=13,'Sales Input'!O48,0))))))))))))) -> 0
B54: d. FDH Bank | C54: =IF($C$2=1,'Sales Input'!C49,IF($C$2=2,'Sales Input'!D49,IF($C$2=3,'Sales Input'!E49,IF($C$2=4,'Sales Input'!F49,IF($C$2=5,'Sales Input'!G49,IF($C$2=6,'Sales Input'!H49,IF($C$2=7,'Sales Input'!I49,IF($C$2=8,'Sales Input'!J49,IF($C$2=9,'Sales Input'!K49,IF($C$2=10,'Sales Input'!L49,IF($C$2=11,'Sales Input'!M49,IF($C$2=12,'Sales Input'!N49,IF($C$2=13,'Sales Input'!O49,0))))))))))))) -> 0
B55: Sub-Total | C55: =SUM(C51:C54) -> 0
A56: 7 | B56: AirTime
B57: a. Airtel Money | C57: =IF($C$2=1,'Sales Input'!C51,IF($C$2=2,'Sales Input'!D51,IF($C$2=3,'Sales Input'!E51,IF($C$2=4,'Sales Input'!F51,IF($C$2=5,'Sales Input'!G51,IF($C$2=6,'Sales Input'!H51,IF($C$2=7,'Sales Input'!I51,IF($C$2=8,'Sales Input'!J51,IF($C$2=9,'Sales Input'!K51,IF($C$2=10,'Sales Input'!L51,IF($C$2=11,'Sales Input'!M51,IF($C$2=12,'Sales Input'!N51,IF($C$2=13,'Sales Input'!O51,0))))))))))))) -> 0
B58: b. MO626 | C58: =IF($C$2=1,'Sales Input'!C52,IF($C$2=2,'Sales Input'!D52,IF($C$2=3,'Sales Input'!E52,IF($C$2=4,'Sales Input'!F52,IF($C$2=5,'Sales Input'!G52,IF($C$2=6,'Sales Input'!H52,IF($C$2=7,'Sales Input'!I52,IF($C$2=8,'Sales Input'!J52,IF($C$2=9,'Sales Input'!K52,IF($C$2=10,'Sales Input'!L52,IF($C$2=11,'Sales Input'!M52,IF($C$2=12,'Sales Input'!N52,IF($C$2=13,'Sales Input'!O52,0))))))))))))) -> 0
B59: c. TNM Mpamba | C59: =IF($C$2=1,'Sales Input'!C53,IF($C$2=2,'Sales Input'!D53,IF($C$2=3,'Sales Input'!E53,IF($C$2=4,'Sales Input'!F53,IF($C$2=5,'Sales Input'!G53,IF($C$2=6,'Sales Input'!H53,IF($C$2=7,'Sales Input'!I53,IF($C$2=8,'Sales Input'!J53,IF($C$2=9,'Sales Input'!K53,IF($C$2=10,'Sales Input'!L53,IF($C$2=11,'Sales Input'!M53,IF($C$2=12,'Sales Input'!N53,IF($C$2=13,'Sales Input'!O53,0))))))))))))) -> 0
B60: d. FDH Bank | C60: =IF($C$2=1,'Sales Input'!C54,IF($C$2=2,'Sales Input'!D54,IF($C$2=3,'Sales Input'!E54,IF($C$2=4,'Sales Input'!F54,IF($C$2=5,'Sales Input'!G54,IF($C$2=6,'Sales Input'!H54,IF($C$2=7,'Sales Input'!I54,IF($C$2=8,'Sales Input'!J54,IF($C$2=9,'Sales Input'!K54,IF($C$2=10,'Sales Input'!L54,IF($C$2=11,'Sales Input'!M54,IF($C$2=12,'Sales Input'!N54,IF($C$2=13,'Sales Input'!O54,0))))))))))))) -> 0
B61: Sub-Total | C61: =SUM(C57:C60) -> 0
A62: 8 | B62: Student Accomodation
B63: a. Airtel Money | C63: =IF($C$2=1,'Sales Input'!C56,IF($C$2=2,'Sales Input'!D56,IF($C$2=3,'Sales Input'!E56,IF($C$2=4,'Sales Input'!F56,IF($C$2=5,'Sales Input'!G56,IF($C$2=6,'Sales Input'!H56,IF($C$2=7,'Sales Input'!I56,IF($C$2=8,'Sales Input'!J56,IF($C$2=9,'Sales Input'!K56,IF($C$2=10,'Sales Input'!L56,IF($C$2=11,'Sales Input'!M56,IF($C$2=12,'Sales Input'!N56,IF($C$2=13,'Sales Input'!O56,0))))))))))))) -> 0
B64: b. MO626 | C64: =IF($C$2=1,'Sales Input'!C57,IF($C$2=2,'Sales Input'!D57,IF($C$2=3,'Sales Input'!E57,IF($C$2=4,'Sales Input'!F57,IF($C$2=5,'Sales Input'!G57,IF($C$2=6,'Sales Input'!H57,IF($C$2=7,'Sales Input'!I57,IF($C$2=8,'Sales Input'!J57,IF($C$2=9,'Sales Input'!K57,IF($C$2=10,'Sales Input'!L57,IF($C$2=11,'Sales Input'!M57,IF($C$2=12,'Sales Input'!N57,IF($C$2=13,'Sales Input'!O57,0))))))))))))) -> 0
B65: c. TNM Mpamba | C65: =IF($C$2=1,'Sales Input'!C58,IF($C$2=2,'Sales Input'!D58,IF($C$2=3,'Sales Input'!E58,IF($C$2=4,'Sales Input'!F58,IF($C$2=5,'Sales Input'!G58,IF($C$2=6,'Sales Input'!H58,IF($C$2=7,'Sales Input'!I58,IF($C$2=8,'Sales Input'!J58,IF($C$2=9,'Sales Input'!K58,IF($C$2=10,'Sales Input'!L58,IF($C$2=11,'Sales Input'!M58,IF($C$2=12,'Sales Input'!N58,IF($C$2=13,'Sales Input'!O58,0))))))))))))) -> 0
B66: d. FDH Bank | C66: =IF($C$2=1,'Sales Input'!C59,IF($C$2=2,'Sales Input'!D59,IF($C$2=3,'Sales Input'!E59,IF($C$2=4,'Sales Input'!F59,IF($C$2=5,'Sales Input'!G59,IF($C$2=6,'Sales Input'!H59,IF($C$2=7,'Sales Input'!I59,IF($C$2=8,'Sales Input'!J59,IF($C$2=9,'Sales Input'!K59,IF($C$2=10,'Sales Input'!L59,IF($C$2=11,'Sales Input'!M59,IF($C$2=12,'Sales Input'!N59,IF($C$2=13,'Sales Input'!O59,0))))))))))))) -> 0
B67: Sub-Total | C67: =SUM(C63:C66) -> 0
B68: Total Domasi Sales Thru Mobile Gadgets | C68: =C25+C37+C43+C49+C55+C61+C67 -> 3382050
B69: Total Chinyonga Sales Thru Mobile Gadgets | C69: =C31 -> 0
B71: Total Domasi Cash and Sales Thru Gadgets | C71: =+C17-C10+C68 -> 12217960
B72: Total Chinyonga Cash and Sales Thru Gadgets | C72: =+C10+C69 -> 0
B74: Total Domasi POS Sales | C74: =IF($C$2=1,'Sales Input'!C6,IF($C$2=2,'Sales Input'!D6,IF($C$2=3,'Sales Input'!E6,IF($C$2=4,'Sales Input'!F6,IF($C$2=5,'Sales Input'!G6,IF($C$2=6,'Sales Input'!H6,IF($C$2=7,'Sales Input'!I6,IF($C$2=8,'Sales Input'!J6,IF($C$2=9,'Sales Input'!K6,IF($C$2=10,'Sales Input'!L6,IF($C$2=11,'Sales Input'!M6,IF($C$2=12,'Sales Input'!N6,IF($C$2=13,'Sales Input'!O6,0))))))))))))) -> 0
B75: Total Chinyonga POS Sales | C75: =IF($C$2=1,'Sales Input'!C7,IF($C$2=2,'Sales Input'!D7,IF($C$2=3,'Sales Input'!E7,IF($C$2=4,'Sales Input'!F7,IF($C$2=5,'Sales Input'!G7,IF($C$2=6,'Sales Input'!H7,IF($C$2=7,'Sales Input'!I7,IF($C$2=8,'Sales Input'!J7,IF($C$2=9,'Sales Input'!K7,IF($C$2=10,'Sales Input'!L7,IF($C$2=11,'Sales Input'!M7,IF($C$2=12,'Sales Input'!N7,IF($C$2=13,'Sales Input'!O7,0))))))))))))) -> 0
B76: Domasi Overage/Shortfall | C76: =IF(C71=0,0,C71-C74) -> 12217960
B77: Chinyonga Overage/Shortfall | C77: =IF(C72=0,0,C72-C75) -> 0
A80: CASH DEPOSITS TO ACCOUNTS REPORT
A81: 1 | B81: NBM | C81: =IF($C$2=1,'Sales Input'!C62+$E$81,IF($C$2=2,'Sales Input'!D62+$E$81,IF($C$2=3,'Sales Input'!E62+$E$81,IF($C$2=4,'Sales Input'!F62+$E$81,IF($C$2=5,'Sales Input'!G62+$E$81,IF($C$2=6,'Sales Input'!H62+$E$81,IF($C$2=7,'Sales Input'!I62+$E$81,IF($C$2=8,'Sales Input'!J62+$E$81,IF($C$2=9,'Sales Input'!K62+$E$81,IF($C$2=10,'Sales Input'!L62+$E$81,IF($C$2=11,'Sales Input'!M62+$E$81,IF($C$2=12,'Sales Input'!N62+$E$81,IF($C$2=13,'Sales Input'!O62+$E$81,0))))))))))))) -> 772350 | E81: =+C22+C34+C40+C46+C52+C58+C64 -> 772350
A82: 2 | B82: FDH Bank | C82: =IF($C$2=1,'Sales Input'!C63+$E$82,IF($C$2=2,'Sales Input'!D63+$E$82,IF($C$2=3,'Sales Input'!E63+$E$82,IF($C$2=4,'Sales Input'!F63+$E$82,IF($C$2=5,'Sales Input'!G63+$E$82,IF($C$2=6,'Sales Input'!H63+$E$82,IF($C$2=7,'Sales Input'!I63+$E$82,IF($C$2=8,'Sales Input'!J63+$E$82,IF($C$2=9,'Sales Input'!K63+$E$82,IF($C$2=10,'Sales Input'!L63+$E$82,IF($C$2=11,'Sales Input'!M63+$E$82,IF($C$2=12,'Sales Input'!N63+$E$82,IF($C$2=13,'Sales Input'!O63+$E$82,0))))))))))))) -> 8255910 | E82: =+C24+C36+C42+C48+C54+C60+C66 -> 0
A83: 2 | B83: Airtel Money | C83: =IF($C$2=1,'Sales Input'!C64+$E$83,IF($C$2=2,'Sales Input'!D64+$E$83,IF($C$2=3,'Sales Input'!E64+$E$83,IF($C$2=4,'Sales Input'!F64+$E$83,IF($C$2=5,'Sales Input'!G64+$E$83,IF($C$2=6,'Sales Input'!H64+$E$83,IF($C$2=7,'Sales Input'!I64+$E$83,IF($C$2=8,'Sales Input'!J64+$E$83,IF($C$2=9,'Sales Input'!K64+$E$83,IF($C$2=10,'Sales Input'!L64+$E$83,IF($C$2=11,'Sales Input'!M64+$E$83,IF($C$2=12,'Sales Input'!N64+$E$83,IF($C$2=13,'Sales Input'!O64+$E$83,0))))))))))))) -> 2311100 | E83: =+C21+C27+C33+C39+C45+C51+C57+C63 -> 2311100
A84: 3 | B84: TNM Mpamba | C84: =IF($C$2=1,'Sales Input'!C65+$E$84,IF($C$2=2,'Sales Input'!D65+$E$84,IF($C$2=3,'Sales Input'!E65+$E$84,IF($C$2=4,'Sales Input'!F65+$E$84,IF($C$2=5,'Sales Input'!G65+$E$84,IF($C$2=6,'Sales Input'!H65+$E$84,IF($C$2=7,'Sales Input'!I65+$E$84,IF($C$2=8,'Sales Input'!J65+$E$84,IF($C$2=9,'Sales Input'!K65+$E$84,IF($C$2=10,'Sales Input'!L65+$E$84,IF($C$2=11,'Sales Input'!M65+$E$84,IF($C$2=12,'Sales Input'!N65+$E$84,IF($C$2=13,'Sales Input'!O65+$E$84,0))))))))))))) -> 298600 | E84: =+C23+C35+C41+C47+C53+C59+C65 -> 298600
A85: 4 | B85: Company Contributions | C85: =IF($C$2=1,'Sales Input'!C66,IF($C$2=2,'Sales Input'!D66,IF($C$2=3,'Sales Input'!E66,IF($C$2=4,'Sales Input'!F66,IF($C$2=5,'Sales Input'!G66,IF($C$2=6,'Sales Input'!H66,IF($C$2=7,'Sales Input'!I66,IF($C$2=8,'Sales Input'!J66,IF($C$2=9,'Sales Input'!K66,IF($C$2=10,'Sales Input'!L66,IF($C$2=11,'Sales Input'!M66,IF($C$2=12,'Sales Input'!N66,IF($C$2=13,'Sales Input'!O66,0))))))))))))) -> 0
B86: Total Bank, wallets and Contributions | C86: =+SUM(C81:C85) -> 11637960
B87: Net Cash-in-Hand | C87: =SUM(C17-C81-C82-C83-C84+E81+E82+E83+E84+C85) -> 580000
C89: Amount Paid | D89: Outstanding Amount
B90: Repayments to Company Contribution | C90: =IF($C$2=1,'Sales Input'!C190,IF($C$2=2,'Sales Input'!D190,IF($C$2=3,'Sales Input'!E190,IF($C$2=4,'Sales Input'!F190,IF($C$2=5,'Sales Input'!G190,IF($C$2=6,'Sales Input'!H190,IF($C$2=7,'Sales Input'!I190,IF($C$2=8,'Sales Input'!J190,IF($C$2=9,'Sales Input'!K190,IF($C$2=10,'Sales Input'!L190,IF($C$2=11,'Sales Input'!M190,IF($C$2=12,'Sales Input'!N190,IF($C$2=13,'Sales Input'!O190,0))))))))))))) -> 0 | D90: =C85-C90 -> 0
B92: Balances Remaining after All Payments
B93: =B4 -> Sales as at | C93: =C4 -> August 2025
B94: Total POS Sales | C94: =C74+C75 -> 0
B95: Total Cash and Sales Thru Gadgets | C95: =C71+C72 -> 12217960
B96: Cash Overage/Shortfall | C96: =C76+C77 -> 12217960
B97: Net Balances after Payments
B98: a. Net Cash in- Hand | C98: ='Expenses Report'!E24 -> 580000
B99: b. Net Company Bank Balances | C99: ='Expenses Report'!G24 -> 1168374.5
B100: c. Net Company Wallet Balances | C100: ='Expenses Report'!I24 -> 975000
B101: d. Net Company Contributions | C101: ='Suppliers Report'!K29 -> 0
B102: Total Balances Carried Forward | C102: =SUM(C98:C101) -> 2723374.5

Sheet Suppliers Report
A1: GOODS SUPPLIED REPORT
C4: Amount Due to Suppliers | E4: Payments by Cash-in-Hand | G4: Payments by Bank Transfer | I4: Payments by Wallet | K4: Payments by Capital Injection
B5: Supplier Name | C5: Debt Amount | D5: Outstanding Amount | E5: Amount Paid | F5: Outstanding Amount | G5: Amount Paid | H5: Outstanding Amount | I5: Amount Paid | J5: Outstanding Amount | K5: Amount Paid | L5: Outstanding Amount
B6: Universal Industries | C6: =IF('Consolidated Sales'!$C$2=1,'Sales Input'!C69,IF('Consolidated Sales'!$C$2=2,'Sales Input'!D69,IF('Consolidated Sales'!$C$2=3,'Sales Input'!E69,IF('Consolidated Sales'!$C$2=4,'Sales Input'!F69,IF('Consolidated Sales'!$C$2=5,'Sales Input'!G69,IF('Consolidated Sales'!$C$2=6,'Sales Input'!H69,IF('Consolidated Sales'!$C$2=7,'Sales Input'!I69,IF('Consolidated Sales'!$C$2=8,'Sales Input'!J69,IF('Consolidated Sales'!$C$2=9,'Sales Input'!K69,IF('Consolidated Sales'!$C$2=10,'Sales Input'!L69,IF('Consolidated Sales'!$C$2=11,'Sales Input'!M69,IF('Consolidated Sales'!$C$2=12,'Sales Input'!N69,IF('Consolidated Sales'!$C$2=13,'Sales Input'!O69,0))))))))))))) -> 323500.02 | D6: =SUM(C6-E6-G6-I6-K6) -> 0 | E6: =IF('Consolidated Sales'!$C$2=1,'Sales Input'!C103,IF('Consolidated Sales'!$C$2=2,'Sales Input'!D103,IF('Consolidated Sales'!$C$2=3,'Sales Input'!E103,IF('Consolidated Sales'!$C$2=4,'Sales Input'!F103,IF('Consolidated Sales'!$C$2=5,'Sales Input'!G103,IF('Consolidated Sales'!$C$2=6,'Sales Input'!H103,IF('Consolidated Sales'!$C$2=7,'Sales Input'!I103,IF('Consolidated Sales'!$C$2=8,'Sales Input'!J103,IF('Consolidated Sales'!$C$2=9,'Sales Input'!K103,IF('Consolidated Sales'!$C$2=10,'Sales Input'!L103,IF('Consolidated Sales'!$C$2=11,'Sales Input'!M103,IF('Consolidated Sales'!$C$2=12,'Sales Input'!N103,IF('Consolidated Sales'!$C$2=13,'Sales Input'!O103,0))))))))))))) -> 0 | F6: =SUM(C6-E6-G6-I6-K6) -> 0 | G6: =IF('Consolidated Sales'!$C$2=1,'Sales Input'!C125,IF('Consolidated Sales'!$C$2=2,'Sales Input'!D125,IF('Consolidated Sales'!$C$2=3,'Sales Input'!E125,IF('Consolidated Sales'!$C$2=4,'Sales Input'!F125,IF('Consolidated Sales'!$C$2=5,'Sales Input'!G125,IF('Consolidated Sales'!$C$2=6,'Sales Input'!H125,IF('Consolidated Sales'!$C$2=7,'Sales Input'!I125,IF('Consolidated Sales'!$C$2=8,'Sales Input'!J125,IF('Consolidated Sales'!$C$2=9,'Sales Input'!K125,IF('Consolidated Sales'!$C$2=10,'Sales Input'!L125,IF('Consolidated Sales'!$C$2=11,'Sales Input'!M125,IF('Consolidated Sales'!$C$2=12,'Sales Input'!N125,IF('Consolidated Sales'!$C$2=13,'Sales Input'!O125,0))))))))))))) -> 323500.02 | H6: =C6-E6-G6-I6-K6 -> 0 | I6: =IF('Consolidated Sales'!$C$2=1,'Sales Input'!C147,IF('Consolidated Sales'!$C$2=2,'Sales Input'!D147,IF('Consolidated Sales'!$C$2=3,'Sales Input'!E147,IF('Consolidated Sales'!$C$2=4,'Sales Input'!F147,IF('Consolidated Sales'!$C$2=5,'Sales Input'!G147,IF('Consolidated Sales'!$C$2=6,'Sales Input'!H147,IF('Consolidated Sales'!$C$2=7,'Sales Input'!I147,IF('Consolidated Sales'!$C$2=8,'Sales Input'!J147,IF('Consolidated Sales'!$C$2=9,'Sales Input'!K147,IF('Consolidated Sales'!$C$2=10,'Sales Input'!L147,IF('Consolidated Sales'!$C$2=11,'Sales Input'!M147,IF('Consolidated Sales'!$C$2=12,'Sales Input'!N147,IF('Consolidated Sales'!$C$2=13,'Sales Input'!O147,0))))))))))))) -> 0 | J6: =C6-E6-G6-I6-K6 -> 0 | K6: =IF('Consolidated Sales'!$C$2=1,'Sales Input'!C169,IF('Consolidated Sales'!$C$2=2,'Sales Input'!D169,IF('Consolidated Sales'!$C$2=3,'Sales Input'!E169,IF('Consolidated Sales'!$C$2=4,'Sales Input'!F169,IF('Consolidated Sales'!$C$2=5,'Sales Input'!G169,IF('Consolidated Sales'!$C$2=6,'Sales Input'!H169,IF('Consolidated Sales'!$C$2=7,'Sales Input'!I169,IF('Consolidated Sales'!$C$2=8,'Sales Input'!J169,IF('Consolidated Sales'!$C$2=9,'Sales Input'!K169,IF('Consolidated Sales'!$C$2=10,'Sales Input'!L169,IF('Consolidated Sales'!$C$2=11,'Sales Input'!M169,IF('Consolidated Sales'!$C$2=12,'Sales Input'!N169,IF('Consolidated Sales'!$C$2=13,'Sales Input'!O169,0))))))))))))) -> 0 | L6: =C6-E6-G6-I6-K6 -> 0
B7: Bottled Water | C7: =IF('Consolidated Sales'!$C$2=1,'Sales Input'!C70,IF('Consolidated Sales'!$C$2=2,'Sales Input'!D70,IF('Consolidated Sales'!$C$2=3,'Sales Input'!E70,IF('Consolidated Sales'!$C$2=4,'Sales Input'!F70,IF('Consolidated Sales'!$C$2=5,'Sales Input'!G70,IF('Consolidated Sales'!$C$2=6,'Sales Input'!H70,IF('Consolidated Sales'!$C$2=7,'Sales Input'!I70,IF('Consolidated Sales'!$C$2=8,'Sales Input'!J70,IF('Consolidated Sales'!$C$2=9,'Sales Input'!K70,IF('Consolidated Sales'!$C$2=10,'Sales Input'!L70,IF('Consolidated Sales'!$C$2=11,'Sales Input'!M70,IF('Consolidated Sales'!$C$2=12,'Sales Input'!N70,IF('Consolidated Sales'!$C$2=13,'Sales Input'!O70,0))))))))))))) -> 0 | D7: =SUM(C7-E7-G7-I7-K7) -> 0 | E7: =IF('Consolidated Sales'!$C$2=1,'Sales Input'!C104,IF('Consolidated Sales'!$C$2=2,'Sales Input'!D104,IF('Consolidated Sales'!$C$2=3,'Sales Input'!E104,IF('Consolidated Sales'!$C$2=4,'Sales Input'!F104,IF('Consolidated Sales'!$C$2=5,'Sales Input'!G104,IF('Consolidated Sales'!$C$2=6,'Sales Input'!H104,IF('Consolidated Sales'!$C$2=7,'Sales Input'!I104,IF('Consolidated Sales'!$C$2=8,'Sales Input'!J104,IF('Consolidated Sales'!$C$2=9,'Sales Input'!K104,IF('Consolidated Sales'!$C$2=10,'Sales Input'!L104,IF('Consolidated Sales'!$C$2=11,'Sales Input'!M104,IF('Consolidated Sales'!$C$2=12,'Sales Input'!N104,IF('Consolidated Sales'!$C$2=13,'Sales Input'!O104,0))))))))))))) -> 0 | F7: =SUM(C7-E7-G7-I7-K7) -> 0 | G7: =IF('Consolidated Sales'!$C$2=1,'Sales Input'!C126,IF('Consolidated Sales'!$C$2=2,'Sales Input'!D126,IF('Consolidated Sales'!$C$2=3,'Sales Input'!E126,IF('Consolidated Sales'!$C$2=4,'Sales Input'!F126,IF('Consolidated Sales'!$C$2=5,'Sales Input'!G126,IF('Consolidated Sales'!$C$2=6,'Sales Input'!H126,IF('Consolidated Sales'!$C$2=7,'Sales Input'!I126,IF('Consolidated Sales'!$C$2=8,'Sales Input'!J126,IF('Consolidated Sales'!$C$2=9,'Sales Input'!K126,IF('Consolidated Sales'!$C$2=10,'Sales Input'!L126,IF('Consolidated Sales'!$C$2=11,'Sales Input'!M126,IF('Consolidated Sales'!$C$2=12,'Sales Input'!N126,IF('Consolidated Sales'!$C$2=13,'Sales Input'!O126,0))))))))))))) -> 0 | H7: =C7-E7-G7-I7-K7 -> 0 | I7: =IF('Consolidated Sales'!$C$2=1,'Sales Input'!C148,IF('Consolidated Sales'!$C$2=2,'Sales Input'!D148,IF('Consolidated Sales'!$C$2=3,'Sales Input'!E148,IF('Consolidated Sales'!$C$2=4,'Sales Input'!F148,IF('Consolidated Sales'!$C$2=5,'Sales Input'!G148,IF('Consolidated Sales'!$C$2=6,'Sales Input'!H148,IF('Consolidated Sales'!$C$2=7,'Sales Input'!I148,IF('Consolidated Sales'!$C$2=8,'Sales Input'!J148,IF('Consolidated Sales'!$C$2=9,'Sales Input'!K148,IF('Consolidated Sales'!$C$2=10,'Sales Input'!L148,IF('Consolidated Sales'!$C$2=11,'Sales Input'!M148,IF('Consolidated Sales'!$C$2=12,'Sales Input'!N148,IF('Consolidated Sales'!$C$2=13,'Sales Input'!O148,0))))))))))))) -> 0 | J7: =C7-E7-G7-I7-K7 -> 0 | K7: =IF('Consolidated Sales'!$C$2=1,'Sales Input'!C170,IF('Consolidated Sales'!$C$2=2,'Sales Input'!D170,IF('Consolidated Sales'!$C$2=3,'Sales Input'!E170,IF('Consolidated Sales'!$C$2=4,'Sales Input'!F170,IF('Consolidated Sales'!$C$2=5,'Sales Input'!G170,IF('Consolidated Sales'!$C$2=6,'Sales Input'!H170,IF('Consolidated Sales'!$C$2=7,'Sales Input'!I170,IF('Consolidated Sales'!$C$2=8,'Sales Input'!J170,IF('Consolidated Sales'!$C$2=9,'Sales Input'!K170,IF('Consolidated Sales'!$C$2=10,'Sales Input'!L170,IF('Consolidated Sales'!$C$2=11,'Sales Input'!M170,IF('Consolidated Sales'!$C$2=12,'Sales Input'!N170,IF('Consolidated Sales'!$C$2=13,'Sales Input'!O170,0))))))))))))) -> 0 | L7: =C7-E7-G7-I7-K7 -> 0
B8: Bakeries | C8: =IF('Consolidated Sales'!$C$2=1,'Sales Input'!C77,IF('Consolidated Sales'!$C$2=2,'Sales Input'!D77,IF('Consolidated Sales'!$C$2=3,'Sales Input'!E77,IF('Consolidated Sales'!$C$2=4,'Sales Input'!F77,IF('Consolidated Sales'!$C$2=5,'Sales Input'!G77,IF('Consolidated Sales'!$C$2=6,'Sales Input'!H77,IF('Consolidated Sales'!$C$2=7,'Sales Input'!I77,IF('Consolidated Sales'!$C$2=8,'Sales Input'!J77,IF('Consolidated Sales'!$C$2=9,'Sales Input'!K77,IF('Consolidated Sales'!$C$2=10,'Sales Input'!L77,IF('Consolidated Sales'!$C$2=11,'Sales Input'!M77,IF('Consolidated Sales'!$C$2=12,'Sales Input'!N77,IF('Consolidated Sales'!$C$2=13,'Sales Input'!O77,0))))))))))))) -> 104700 | D8: =SUM(C8-E8-G8-I8-K8) -> 0 | E8: =IF('Consolidated Sales'!$C$2=1,'Sales Input'!C105,IF('Consolidated Sales'!$C$2=2,'Sales Input'!D105,IF('Consolidated Sales'!$C$2=3,'Sales Input'!E105,IF('Consolidated Sales'!$C$2=4,'Sales Input'!F105,IF('Consolidated Sales'!$C$2=5,'Sales Input'!G105,IF('Consolidated Sales'!$C$2=6,'Sales Input'!H105,IF('Consolidated Sales'!$C$2=7,'Sales Input'!I105,IF('Consolidated Sales'!$C$2=8,'Sales Input'!J105,IF('Consolidated Sales'!$C$2=9,'Sales Input'!K105,IF('Consolidated Sales'!$C$2=10,'Sales Input'!L105,IF('Consolidated Sales'!$C$2=11,'Sales Input'!M105,IF('Consolidated Sales'!$C$2=12,'Sales Input'!N105,IF('Consolidated Sales'!$C$2=13,'Sales Input'!O105,0))))))))))))) -> 0 | F8: =SUM(C8-E8-G8-I8-K8) -> 0 | G8: =IF('Consolidated Sales'!$C$2=1,'Sales Input'!C127,IF('Consolidated Sales'!$C$2=2,'Sales Input'!D127,IF('Consolidated Sales'!$C$2=3,'Sales Input'!E127,IF('Consolidated Sales'!$C$2=4,'Sales Input'!F127,IF('Consolidated Sales'!$C$2=5,'Sales Input'!G127,IF('Consolidated Sales'!$C$2=6,'Sales Input'!H127,IF('Consolidated Sales'!$C$2=7,'Sales Input'!I127,IF('Consolidated Sales'!$C$2=8,'Sales Input'!J127,IF('Consolidated Sales'!$C$2=9,'Sales Input'!K127,IF('Consolidated Sales'!$C$2=10,'Sales Input'!L127,IF('Consolidated Sales'!$C$2=11,'Sales Input'!M127,IF('Consolidated Sales'!$C$2=12,'Sales Input'!N127,IF('Consolidated Sales'!$C$2=13,'Sales Input'!O127,0))))))))))))) -> 0 | H8: =C8-E8-G8-I8-K8 -> 0 | I8: =IF('Consolidated Sales'!$C$2=1,'Sales Input'!C149,IF('Consolidated Sales'!$C$2=2,'Sales Input'!D149,IF('Consolidated Sales'!$C$2=3,'Sales Input'!E149,IF('Consolidated Sales'!$C$2=4,'Sales Input'!F149,IF('Consolidated Sales'!$C$2=5,'Sales Input'!G149,IF('Consolidated Sales'!$C$2=6,'Sales Input'!H149,IF('Consolidated Sales'!$C$2=7,'Sales Input'!I149,IF('Consolidated Sales'!$C$2=8,'Sales Input'!J149,IF('Consolidated Sales'!$C$2=9,'Sales Input'!K149,IF('Consolidated Sales'!$C$2=10,'Sales Input'!L149,IF('Consolidated Sales'!$C$2=11,'Sales Input'!M149,IF('Consolidated Sales'!$C$2=12,'Sales Input'!N149,IF('Consolidated Sales'!$C$2=13,'Sales Input'!O149,0))))))))))))) -> 104700 | J8: =C8-E8-G8-I8-K8 -> 0 | K8: =IF('Consolidated Sales'!$C$2=1,'Sales Input'!C171,IF('Consolidated Sales'!$C$2=2,'Sales Input'!D171,IF('Consolidated Sales'!$C$2=3,'Sales Input'!E171,IF('Consolidated Sales'!$C$2=4,'Sales Input'!F171,IF('Consolidated Sales'!$C$2=5,'Sales Input'!G171,IF('Consolidated Sales'!$C$2=6,'Sales Input'!H171,IF('Consolidated Sales'!$C$2=7,'Sales Input'!I171,IF('Consolidated Sales'!$C$2=8,'Sales Input'!J171,IF('Consolidated Sales'!$C$2=9,'Sales Input'!K171,IF('Consolidated Sales'!$C$2=10,'Sales Input'!L171,IF('Consolidated Sales'!$C$2=11,'Sales Input'!M171,IF('Consolidated Sales'!$C$2=12,'Sales Input'!N171,IF('Consolidated Sales'!$C$2=13,'Sales Input'!O171,0))))))))))))) -> 0 | L8: =C8-E8-G8-I8-K8 -> 0
B9: Suncrest Ltd | C9: =IF('Consolidated Sales'!$C$2=1,'Sales Input'!C78,IF('Consolidated Sales'!$C$2=2,'Sales Input'!D78,IF('Consolidated Sales'!$C$2=3,'Sales Input'!E78,IF('Consolidated Sales'!$C$2=4,'Sales Input'!F78,IF('Consolidated Sales'!$C$2=5,'Sales Input'!G78,IF('Consolidated Sales'!$C$2=6,'Sales Input'!H78,IF('Consolidated Sales'!$C$2=7,'Sales Input'!I78,IF('Consolidated Sales'!$C$2=8,'Sales Input'!J78,IF('Consolidated Sales'!$C$2=9,'Sales Input'!K78,IF('Consolidated Sales'!$C$2=10,'Sales Input'!L78,IF('Consolidated Sales'!$C$2=11,'Sales Input'!M78,IF('Consolidated Sales'!$C$2=12,'Sales Input'!N78,IF('Consolidated Sales'!$C$2=13,'Sales Input'!O78,0))))))))))))) -> 0 | D9: =SUM(C9-E9-G9-I9-K9) -> 0 | E9: =IF('Consolidated Sales'!$C$2=1,'Sales Input'!C106,IF('Consolidated Sales'!$C$2=2,'Sales Input'!D106,IF('Consolidated Sales'!$C$2=3,'Sales Input'!E106,IF('Consolidated Sales'!$C$2=4,'Sales Input'!F106,IF('Consolidated Sales'!$C$2=5,'Sales Input'!G106,IF('Consolidated Sales'!$C$2=6,'Sales Input'!H106,IF('Consolidated Sales'!$C$2=7,'Sales Input'!I106,IF('Consolidated Sales'!$C$2=8,'Sales Input'!J106,IF('Consolidated Sales'!$C$2=9,'Sales Input'!K106,IF('Consolidated Sales'!$C$2=10,'Sales Input'!L106,IF('Consolidated Sales'!$C$2=11,'Sales Input'!M106,IF('Consolidated Sales'!$C$2=12,'Sales Input'!N106,IF('Consolidated Sales'!$C$2=13,'Sales Input'!O106,0))))))))))))) -> 0 | F9: =SUM(C9-E9-G9-I9-K9) -> 0 | G9: =IF('Consolidated Sales'!$C$2=1,'Sales Input'!C128,IF('Consolidated Sales'!$C$2=2,'Sales Input'!D128,IF('Consolidated Sales'!$C$2=3,'Sales Input'!E128,IF('Consolidated Sales'!$C$2=4,'Sales Input'!F128,IF('Consolidated Sales'!$C$2=5,'Sales Input'!G128,IF('Consolidated Sales'!$C$2=6,'Sales Input'!H128,IF('Consolidated Sales'!$C$2=7,'Sales Input'!I128,IF('Consolidated Sales'!$C$2=8,'Sales Input'!J128,IF('Consolidated Sales'!$C$2=9,'Sales Input'!K128,IF('Consolidated Sales'!$C$2=10,'Sales Input'!L128,IF('Consolidated Sales'!$C$2=11,'Sales Input'!M128,IF('Consolidated Sales'!$C$2=12,'Sales Input'!N128,IF('Consolidated Sales'!$C$2=13,'Sales Input'!O128,0))))))))))))) -> 0 | H9: =C9-E9-G9-I9-K9 -> 0 | I9: =IF('Consolidated Sales'!$C$2=1,'Sales Input'!C150,IF('Consolidated Sales'!$C$2=2,'Sales Input'!D150,IF('Consolidated Sales'!$C$2=3,'Sales Input'!E150,IF('Consolidated Sales'!$C$2=4,'Sales Input'!F150,IF('Consolidated Sales'!$C$2=5,'Sales Input'!G150,IF('Consolidated Sales'!$C$2=6,'Sales Input'!H150,IF('Consolidated Sales'!$C$2=7,'Sales Input'!I150,IF('Consolidated Sales'!$C$2=8,'Sales Input'!J150,IF('Consolidated Sales'!$C$2=9,'Sales Input'!K150,IF('Consolidated Sales'!$C$2=10,'Sales Input'!L150,IF('Consolidated Sales'!$C$2=11,'Sales Input'!M150,IF('Consolidated Sales'!$C$2=12,'Sales Input'!N150,IF('Consolidated Sales'!$C$2=13,'Sales Input'!O150,0))))))))))))) -> 0 | J9: =C9-E9-G9-I9-K9 -> 0 | K9: =IF('Consolidated Sales'!$C$2=1,'Sales Input'!C172,IF('Consolidated Sales'!$C$2=2,'Sales Input'!D172,IF('Consolidated Sales'!$C$2=3,'Sales Input'!E172,IF('Consolidated Sales'!$C$2=4,'Sales Input'!F172,IF('Consolidated Sales'!$C$2=5,'Sales Input'!G172,IF('Consolidated Sales'!$C$2=6,'Sales Input'!H172,IF('Consolidated Sales'!$C$2=7,'Sales Input'!I172,IF('Consolidated Sales'!$C$2=8,'Sales Input'!J172,IF('Consolidated Sales'!$C$2=9,'Sales Input'!K172,IF('Consolidated Sales'!$C$2=10,'Sales Input'!L172,IF('Consolidated Sales'!$C$2=11,'Sales Input'!M172,IF('Consolidated Sales'!$C$2=12,'Sales Input'!N172,IF('Consolidated Sales'!$C$2=13,'Sales Input'!O172,0))))))))))))) -> 0 | L9: =C9-E9-G9-I9-K9 -> 0
B10: Cold Chain | C10: =IF('Consolidated Sales'!$C$2=1,'Sales Input'!C79,IF('Consolidated Sales'!$C$2=2,'Sales Input'!D79,IF('Consolidated Sales'!$C$2=3,'Sales Input'!E79,IF('Consolidated Sales'!$C$2=4,'Sales Input'!F79,IF('Consolidated Sales'!$C$2=5,'Sales Input'!G79,IF('Consolidated Sales'!$C$2=6,'Sales Input'!H79,IF('Consolidated Sales'!$C$2=7,'Sales Input'!I79,IF('Consolidated Sales'!$C$2=8,'Sales Input'!J79,IF('Consolidated Sales'!$C$2=9,'Sales Input'!K79,IF('Consolidated Sales'!$C$2=10,'Sales Input'!L79,IF('Consolidated Sales'!$C$2=11,'Sales Input'!M79,IF('Consolidated Sales'!$C$2=12,'Sales Input'!N79,IF('Consolidated Sales'!$C$2=13,'Sales Input'!O79,0))))))))))))) -> 0 | D10: =SUM(C10-E10-G10-I10-K10) -> 0 | E10: =IF('Consolidated Sales'!$C$2=1,'Sales Input'!C107,IF('Consolidated Sales'!$C$2=2,'Sales Input'!D107,IF('Consolidated Sales'!$C$2=3,'Sales Input'!E107,IF('Consolidated Sales'!$C$2=4,'Sales Input'!F107,IF('Consolidated Sales'!$C$2=5,'Sales Input'!G107,IF('Consolidated Sales'!$C$2=6,'Sales Input'!H107,IF('Consolidated Sales'!$C$2=7,'Sales Input'!I107,IF('Consolidated Sales'!$C$2=8,'Sales Input'!J107,IF('Consolidated Sales'!$C$2=9,'Sales Input'!K107,IF('Consolidated Sales'!$C$2=10,'Sales Input'!L107,IF('Consolidated Sales'!$C$2=11,'Sales Input'!M107,IF('Consolidated Sales'!$C$2=12,'Sales Input'!N107,IF('Consolidated Sales'!$C$2=13,'Sales Input'!O107,0))))))))))))) -> 0 | F10: =SUM(C10-E10-G10-I10-K10) -> 0 | G10: =IF('Consolidated Sales'!$C$2=1,'Sales Input'!C129,IF('Consolidated Sales'!$C$2=2,'Sales Input'!D129,IF('Consolidated Sales'!$C$2=3,'Sales Input'!E129,IF('Consolidated Sales'!$C$2=4,'Sales Input'!F129,IF('Consolidated Sales'!$C$2=5,'Sales Input'!G129,IF('Consolidated Sales'!$C$2=6,'Sales Input'!H129,IF('Consolidated Sales'!$C$2=7,'Sales Input'!I129,IF('Consolidated Sales'!$C$2=8,'Sales Input'!J129,IF('Consolidated Sales'!$C$2=9,'Sales Input'!K129,IF('Consolidated Sales'!$C$2=10,'Sales Input'!L129,IF('Consolidated Sales'!$C$2=11,'Sales Input'!M129,IF('Consolidated Sales'!$C$2=12,'Sales Input'!N129,IF('Consolidated Sales'!$C$2=13,'Sales Input'!O129,0))))))))))))) -> 0 | H10: =C10-E10-G10-I10-K10 -> 0 | I10: =IF('Consolidated Sales'!$C$2=1,'Sales Input'!C151,IF('Consolidated Sales'!$C$2=2,'Sales Input'!D151,IF('Consolidated Sales'!$C$2=3,'Sales Input'!E151,IF('Consolidated Sales'!$C$2=4,'Sales Input'!F151,IF('Consolidated Sales'!$C$2=5,'Sales Input'!G151,IF('Consolidated Sales'!$C$2=6,'Sales Input'!H151,IF('Consolidated Sales'!$C$2=7,'Sales Input'!I151,IF('Consolidated Sales'!$C$2=8,'Sales Input'!J151,IF('Consolidated Sales'!$C$2=9,'Sales Input'!K151,IF('Consolidated Sales'!$C$2=10,'Sales Input'!L151,IF('Consolidated Sales'!$C$2=11,'Sales Input'!M151,IF('Consolidated Sales'!$C$2=12,'Sales Input'!N151,IF('Consolidated Sales'!$C$2=13,'Sales Input'!O151,0))))))))))))) -> 0 | J10: =C10-E10-G10-I10-K10 -> 0 | K10: =IF('Consolidated Sales'!$C$2=1,'Sales Input'!C173,IF('Consolidated Sales'!$C$2=2,'Sales Input'!D173,IF('Consolidated Sales'!$C$2=3,'Sales Input'!E173,IF('Consolidated Sales'!$C$2=4,'Sales Input'!F173,IF('Consolidated Sales'!$C$2=5,'Sales Input'!G173,IF('Consolidated Sales'!$C$2=6,'Sales Input'!H173,IF('Consolidated Sales'!$C$2=7,'Sales Input'!I173,IF('Consolidated Sales'!$C$2=8,'Sales Input'!J173,IF('Consolidated Sales'!$C$2=9,'Sales Input'!K173,IF('Consolidated Sales'!$C$2=10,'Sales Input'!L173,IF('Consolidated Sales'!$C$2=11,'Sales Input'!M173,IF('Consolidated Sales'!$C$2=12,'Sales Input'!N173,IF('Consolidated Sales'!$C$2=13,'Sales Input'!O173,0))))))))))))) -> 0 | L10: =C10-E10-G10-I10-K10 -> 0
B11: Unilever | C11: =IF('Consolidated Sales'!$C$2=1,'Sales Input'!C80,IF('Consolidated Sales'!$C$2=2,'Sales Input'!D80,IF('Consolidated Sales'!$C$2=3,'Sales Input'!E80,IF('Consolidated Sales'!$C$2=4,'Sales Input'!F80,IF('Consolidated Sales'!$C$2=5,'Sales Input'!G80,IF('Consolidated Sales'!$C$2=6,'Sales Input'!H80,IF('Consolidated Sales'!$C$2=7,'Sales Input'!I80,IF('Consolidated Sales'!$C$2=8,'Sales Input'!J80,IF('Consolidated Sales'!$C$2=9,'Sales Input'!K80,IF('Consolidated Sales'!$C$2=10,'Sales Input'!L80,IF('Consolidated Sales'!$C$2=11,'Sales Input'!M80,IF('Consolidated Sales'!$C$2=12,'Sales Input'!N80,IF('Consolidated Sales'!$C$2=13,'Sales Input'!O80,0))))))))))))) -> 0 | D11: =SUM(C11-E11-G11-I11-K11) -> 0 | E11: =IF('Consolidated Sales'!$C$2=1,'Sales Input'!C108,IF('Consolidated Sales'!$C$2=2,'Sales Input'!D108,IF('Consolidated Sales'!$C$2=3,'Sales Input'!E108,IF('Consolidated Sales'!$C$2=4,'Sales Input'!F108,IF('Consolidated Sales'!$C$2=5,'Sales Input'!G108,IF('Consolidated Sales'!$C$2=6,'Sales Input'!H108,IF('Consolidated Sales'!$C$2=7,'Sales Input'!I108,IF('Consolidated Sales'!$C$2=8,'Sales Input'!J108,IF('Consolidated Sales'!$C$2=9,'Sales Input'!K108,IF('Consolidated Sales'!$C$2=10,'Sales Input'!L108,IF('Consolidated Sales'!$C$2=11,'Sales Input'!M108,IF('Consolidated Sales'!$C$2=12,'Sales Input'!N108,IF('Consolidated Sales'!$C$2=13,'Sales Input'!O108,0))))))))))))) -> 0 | F11: =SUM(C11-E11-G11-I11-K11) -> 0 | G11: =IF('Consolidated Sales'!$C$2=1,'Sales Input'!C130,IF('Consolidated Sales'!$C$2=2,'Sales Input'!D130,IF('Consolidated Sales'!$C$2=3,'Sales Input'!E130,IF('Consolidated Sales'!$C$2=4,'Sales Input'!F130,IF('Consolidated Sales'!$C$2=5,'Sales Input'!G130,IF('Consolidated Sales'!$C$2=6,'Sales Input'!H130,IF('Consolidated Sales'!$C$2=7,'Sales Input'!I130,IF('Consolidated Sales'!$C$2=8,'Sales Input'!J130,IF('Consolidated Sales'!$C$2=9,'Sales Input'!K130,IF('Consolidated Sales'!$C$2=10,'Sales Input'!L130,IF('Consolidated Sales'!$C$2=11,'Sales Input'!M130,IF('Consolidated Sales'!$C$2=12,'Sales Input'!N130,IF('Consolidated Sales'!$C$2=13,'Sales Input'!O130,0))))))))))))) -> 0 | H11: =C11-E11-G11-I11-K11 -> 0 | I11: =IF('Consolidated Sales'!$C$2=1,'Sales Input'!C152,IF('Consolidated Sales'!$C$2=2,'Sales Input'!D152,IF('Consolidated Sales'!$C$2=3,'Sales Input'!E152,IF('Consolidated Sales'!$C$2=4,'Sales Input'!F152,IF('Consolidated Sales'!$C$2=5,'Sales Input'!G152,IF('Consolidated Sales'!$C$2=6,'Sales Input'!H152,IF('Consolidated Sales'!$C$2=7,'Sales Input'!I152,IF('Consolidated Sales'!$C$2=8,'Sales Input'!J152,IF('Consolidated Sales'!$C$2=9,'Sales Input'!K152,IF('Consolidated Sales'!$C$2=10,'Sales Input'!L152,IF('Consolidated Sales'!$C$2=11,'Sales Input'!M152,IF('Consolidated Sales'!$C$2=12,'Sales Input'!N152,IF('Consolidated Sales'!$C$2=13,'Sales Input'!O152,0))))))))))))) -> 0 | J11: =C11-E11-G11-I11-K11 -> 0 | K11: =IF('Consolidated Sales'!$C$2=1,'Sales Input'!C174,IF('Consolidated Sales'!$C$2=2,'Sales Input'!D174,IF('Consolidated Sales'!$C$2=3,'Sales Input'!E174,IF('Consolidated Sales'!$C$2=4,'Sales Input'!F174,IF('Consolidated Sales'!$C$2=5,'Sales Input'!G174,IF('Consolidated Sales'!$C$2=6,'Sales Input'!H174,IF('Consolidated Sales'!$C$2=7,'Sales Input'!I174,IF('Consolidated Sales'!$C$2=8,'Sales Input'!J174,IF('Consolidated Sales'!$C$2=9,'Sales Input'!K174,IF('Consolidated Sales'!$C$2=10,'Sales Input'!L174,IF('Consolidated Sales'!$C$2=11,'Sales Input'!M174,IF('Consolidated Sales'!$C$2=12,'Sales Input'!N174,IF('Consolidated Sales'!$C$2=13,'Sales Input'!O174,0))))))))))))) -> 0 | L11: =C11-E11-G11-I11-K11 -> 0
B12: Rab Processors | C12: =IF('Consolidated Sales'!$C$2=1,'Sales Input'!C81,IF('Consolidated Sales'!$C$2=2,'Sales Input'!D81,IF('Consolidated Sales'!$C$2=3,'Sales Input'!E81,IF('Consolidated Sales'!$C$2=4,'Sales Input'!F81,IF('Consolidated Sales'!$C$2=5,'Sales Input'!G81,IF('Consolidated Sales'!$C$2=6,'Sales Input'!H81,IF('Consolidated Sales'!$C$2=7,'Sales Input'!I81,IF('Consolidated Sales'!$C$2=8,'Sales Input'!J81,IF('Consolidated Sales'!$C$2=9,'Sales Input'!K81,IF('Consolidated Sales'!$C$2=10,'Sales Input'!L81,IF('Consolidated Sales'!$C$2=11,'Sales Input'!M81,IF('Consolidated Sales'!$C$2=12,'Sales Input'!N81,IF('Consolidated Sales'!$C$2=13,'Sales Input'!O81,0))))))))))))) -> 0 | D12: =SUM(C12-E12-G12-I12-K12) -> 0 | E12: =IF('Consolidated Sales'!$C$2=1,'Sales Input'!C109,IF('Consolidated Sales'!$C$2=2,'Sales Input'!D109,IF('Consolidated Sales'!$C$2=3,'Sales Input'!E109,IF('Consolidated Sales'!$C$2=4,'Sales Input'!F109,IF('Consolidated Sales'!$C$2=5,'Sales Input'!G109,IF('Consolidated Sales'!$C$2=6,'Sales Input'!H109,IF('Consolidated Sales'!$C$2=7,'Sales Input'!I109,IF('Consolidated Sales'!$C$2=8,'Sales Input'!J109,IF('Consolidated Sales'!$C$2=9,'Sales Input'!K109,IF('Consolidated Sales'!$C$2=10,'Sales Input'!L109,IF('Consolidated Sales'!$C$2=11,'Sales Input'!M109,IF('Consolidated Sales'!$C$2=12,'Sales Input'!N109,IF('Consolidated Sales'!$C$2=13,'Sales Input'!O109,0))))))))))))) -> 0 | F12: =SUM(C12-E12-G12-I12-K12) -> 0 | G12: =IF('Consolidated Sales'!$C$2=1,'Sales Input'!C131,IF('Consolidated Sales'!$C$2=2,'Sales Input'!D131,IF('Consolidated Sales'!$C$2=3,'Sales Input'!E131,IF('Consolidated Sales'!$C$2=4,'Sales Input'!F131,IF('Consolidated Sales'!$C$2=5,'Sales Input'!G131,IF('Consolidated Sales'!$C$2=6,'Sales Input'!H131,IF('Consolidated Sales'!$C$2=7,'Sales Input'!I131,IF('Consolidated Sales'!$C$2=8,'Sales Input'!J131,IF('Consolidated Sales'!$C$2=9,'Sales Input'!K131,IF('Consolidated Sales'!$C$2=10,'Sales Input'!L131,IF('Consolidated Sales'!$C$2=11,'Sales Input'!M131,IF('Consolidated Sales'!$C$2=12,'Sales Input'!N131,IF('Consolidated Sales'!$C$2=13,'Sales Input'!O131,0))))))))))))) -> 0 | H12: =C12-E12-G12-I12-K12 -> 0 | I12: =IF('Consolidated Sales'!$C$2=1,'Sales Input'!C153,IF('Consolidated Sales'!$C$2=2,'Sales Input'!D153,IF('Consolidated Sales'!$C$2=3,'Sales Input'!E153,IF('Consolidated Sales'!$C$2=4,'Sales Input'!F153,IF('Consolidated Sales'!$C$2=5,'Sales Input'!G153,IF('Consolidated Sales'!$C$2=6,'Sales Input'!H153,IF('Consolidated Sales'!$C$2=7,'Sales Input'!I153,IF('Consolidated Sales'!$C$2=8,'Sales Input'!J153,IF('Consolidated Sales'!$C$2=9,'Sales Input'!K153,IF('Consolidated Sales'!$C$2=10,'Sales Input'!L153,IF('Consolidated Sales'!$C$2=11,'Sales Input'!M153,IF('Consolidated Sales'!$C$2=12,'Sales Input'!N153,IF('Consolidated Sales'!$C$2=13,'Sales Input'!O153,0))))))))))))) -> 0 | J12: =C12-E12-G12-I12-K12 -> 0 | K12: =IF('Consolidated Sales'!$C$2=1,'Sales Input'!C175,IF('Consolidated Sales'!$C$2=2,'Sales Input'!D175,IF('Consolidated Sales'!$C$2=3,'Sales Input'!E175,IF('Consolidated Sales'!$C$2=4,'Sales Input'!F175,IF('Consolidated Sales'!$C$2=5,'Sales Input'!G175,IF('Consolidated Sales'!$C$2=6,'Sales Input'!H175,IF('Consolidated Sales'!$C$2=7,'Sales Input'!I175,IF('Consolidated Sales'!$C$2=8,'Sales Input'!J175,IF('Consolidated Sales'!$C$2=9,'Sales Input'!K175,IF('Consolidated Sales'!$C$2=10,'Sales Input'!L175,IF('Consolidated Sales'!$C$2=11,'Sales Input'!M175,IF('Consolidated Sales'!$C$2=12,'Sales Input'!N175,IF('Consolidated Sales'!$C$2=13,'Sales Input'!O175,0))))))))))))) -> 0 | L12: =C12-E12-G12-I12-K12 -> 0
B13: Kwacha Fund | C13: =IF('Consolidated Sales'!$C$2=1,'Sales Input'!C82,IF('Consolidated Sales'!$C$2=2,'Sales Input'!D82,IF('Consolidated Sales'!$C$2=3,'Sales Input'!E82,IF('Consolidated Sales'!$C$2=4,'Sales Input'!F82,IF('Consolidated Sales'!$C$2=5,'Sales Input'!G82,IF('Consolidated Sales'!$C$2=6,'Sales Input'!H82,IF('Consolidated Sales'!$C$2=7,'Sales Input'!I82,IF('Consolidated Sales'!$C$2=8,'Sales Input'!J82,IF('Consolidated Sales'!$C$2=9,'Sales Input'!K82,IF('Consolidated Sales'!$C$2=10,'Sales Input'!L82,IF('Consolidated Sales'!$C$2=11,'Sales Input'!M82,IF('Consolidated Sales'!$C$2=12,'Sales Input'!N82,IF('Consolidated Sales'!$C$2=13,'Sales Input'!O82,0))))))))))))) -> 3323620.5 | D13: =SUM(C13-E13-G13-I13-K13) -> 0 | E13: =IF('Consolidated Sales'!$C$2=1,'Sales Input'!C110,IF('Consolidated Sales'!$C$2=2,'Sales Input'!D110,IF('Consolidated Sales'!$C$2=3,'Sales Input'!E110,IF('Consolidated Sales'!$C$2=4,'Sales Input'!F110,IF('Consolidated Sales'!$C$2=5,'Sales Input'!G110,IF('Consolidated Sales'!$C$2=6,'Sales Input'!H110,IF('Consolidated Sales'!$C$2=7,'Sales Input'!I110,IF('Consolidated Sales'!$C$2=8,'Sales Input'!J110,IF('Consolidated Sales'!$C$2=9,'Sales Input'!K110,IF('Consolidated Sales'!$C$2=10,'Sales Input'!L110,IF('Consolidated Sales'!$C$2=11,'Sales Input'!M110,IF('Consolidated Sales'!$C$2=12,'Sales Input'!N110,IF('Consolidated Sales'!$C$2=13,'Sales Input'!O110,0))))))))))))) -> 0 | F13: =SUM(C13-E13-G13-I13-K13) -> 0 | G13: =IF('Consolidated Sales'!$C$2=1,'Sales Input'!C132,IF('Consolidated Sales'!$C$2=2,'Sales Input'!D132,IF('Consolidated Sales'!$C$2=3,'Sales Input'!E132,IF('Consolidated Sales'!$C$2=4,'Sales Input'!F132,IF('Consolidated Sales'!$C$2=5,'Sales Input'!G132,IF('Consolidated Sales'!$C$2=6,'Sales Input'!H132,IF('Consolidated Sales'!$C$2=7,'Sales Input'!I132,IF('Consolidated Sales'!$C$2=8,'Sales Input'!J132,IF('Consolidated Sales'!$C$2=9,'Sales Input'!K132,IF('Consolidated Sales'!$C$2=10,'Sales Input'!L132,IF('Consolidated Sales'!$C$2=11,'Sales Input'!M132,IF('Consolidated Sales'!$C$2=12,'Sales Input'!N132,IF('Consolidated Sales'!$C$2=13,'Sales Input'!O132,0))))))))))))) -> 3323620.5 | H13: =C13-E13-G13-I13-K13 -> 0 | I13: =IF('Consolidated Sales'!$C$2=1,'Sales Input'!C154,IF('Consolidated Sales'!$C$2=2,'Sales Input'!D154,IF('Consolidated Sales'!$C$2=3,'Sales Input'!E154,IF('Consolidated Sales'!$C$2=4,'Sales Input'!F154,IF('Consolidated Sales'!$C$2=5,'Sales Input'!G154,IF('Consolidated Sales'!$C$2=6,'Sales Input'!H154,IF('Consolidated Sales'!$C$2=7,'Sales Input'!I154,IF('Consolidated Sales'!$C$2=8,'Sales Input'!J154,IF('Consolidated Sales'!$C$2=9,'Sales Input'!K154,IF('Consolidated Sales'!$C$2=10,'Sales Input'!L154,IF('Consolidated Sales'!$C$2=11,'Sales Input'!M154,IF('Consolidated Sales'!$C$2=12,'Sales Input'!N154,IF('Consolidated Sales'!$C$2=13,'Sales Input'!O154,0))))))))))))) -> 0 | J13: =C13-E13-G13-I13-K13 -> 0 | K13: =IF('Consolidated Sales'!$C$2=1,'Sales Input'!C176,IF('Consolidated Sales'!$C$2=2,'Sales Input'!D176,IF('Consolidated Sales'!$C$2=3,'Sales Input'!E176,IF('Consolidated Sales'!$C$2=4,'Sales Input'!F176,IF('Consolidated Sales'!$C$2=5,'Sales Input'!G176,IF('Consolidated Sales'!$C$2=6,'Sales Input'!H176,IF('Consolidated Sales'!$C$2=7,'Sales Input'!I176,IF('Consolidated Sales'!$C$2=8,'Sales Input'!J176,IF('Consolidated Sales'!$C$2=9,'Sales Input'!K176,IF('Consolidated Sales'!$C$2=10,'Sales Input'!L176,IF('Consolidated Sales'!$C$2=11,'Sales Input'!M176,IF('Consolidated Sales'!$C$2=12,'Sales Input'!N176,IF('Consolidated Sales'!$C$2=13,'Sales Input'!O176,0))))))))))))) -> 0 | L13: =C13-E13-G13-I13-K13 -> 0
B14: Ekhaya Farms | C14: =IF('Consolidated Sales'!$C$2=1,'Sales Input'!C83,IF('Consolidated Sales'!$C$2=2,'Sales Input'!D83,IF('Consolidated Sales'!$C$2=3,'Sales Input'!E83,IF('Consolidated Sales'!$C$2=4,'Sales Input'!F83,IF('Consolidated Sales'!$C$2=5,'Sales Input'!G83,IF('Consolidated Sales'!$C$2=6,'Sales Input'!H83,IF('Consolidated Sales'!$C$2=7,'Sales Input'!I83,IF('Consolidated Sales'!$C$2=8,'Sales Input'!J83,IF('Consolidated Sales'!$C$2=9,'Sales Input'!K83,IF('Consolidated Sales'!$C$2=10,'Sales Input'!L83,IF('Consolidated Sales'!$C$2=11,'Sales Input'!M83,IF('Consolidated Sales'!$C$2=12,'Sales Input'!N83,IF('Consolidated Sales'!$C$2=13,'Sales Input'!O83,0))))))))))))) -> 0 | D14: =SUM(C14-E14-G14-I14-K14) -> 0 | E14: =IF('Consolidated Sales'!$C$2=1,'Sales Input'!C111,IF('Consolidated Sales'!$C$2=2,'Sales Input'!D111,IF('Consolidated Sales'!$C$2=3,'Sales Input'!E111,IF('Consolidated Sales'!$C$2=4,'Sales Input'!F111,IF('Consolidated Sales'!$C$2=5,'Sales Input'!G111,IF('Consolidated Sales'!$C$2=6,'Sales Input'!H111,IF('Consolidated Sales'!$C$2=7,'Sales Input'!I111,IF('Consolidated Sales'!$C$2=8,'Sales Input'!J111,IF('Consolidated Sales'!$C$2=9,'Sales Input'!K111,IF('Consolidated Sales'!$C$2=10,'Sales Input'!L111,IF('Consolidated Sales'!$C$2=11,'Sales Input'!M111,IF('Consolidated Sales'!$C$2=12,'Sales Input'!N111,IF('Consolidated Sales'!$C$2=13,'Sales Input'!O111,0))))))))))))) -> 0 | F14: =SUM(C14-E14-G14-I14-K14) -> 0 | G14: =IF('Consolidated Sales'!$C$2=1,'Sales Input'!C133,IF('Consolidated Sales'!$C$2=2,'Sales Input'!D133,IF('Consolidated Sales'!$C$2=3,'Sales Input'!E133,IF('Consolidated Sales'!$C$2=4,'Sales Input'!F133,IF('Consolidated Sales'!$C$2=5,'Sales Input'!G133,IF('Consolidated Sales'!$C$2=6,'Sales Input'!H133,IF('Consolidated Sales'!$C$2=7,'Sales Input'!I133,IF('Consolidated Sales'!$C$2=8,'Sales Input'!J133,IF('Consolidated Sales'!$C$2=9,'Sales Input'!K133,IF('Consolidated Sales'!$C$2=10,'Sales Input'!L133,IF('Consolidated Sales'!$C$2=11,'Sales Input'!M133,IF('Consolidated Sales'!$C$2=12,'Sales Input'!N133,IF('Consolidated Sales'!$C$2=13,'Sales Input'!O133,0))))))))))))) -> 0 | H14: =C14-E14-G14-I14-K14 -> 0 | I14: =IF('Consolidated Sales'!$C$2=1,'Sales Input'!C155,IF('Consolidated Sales'!$C$2=2,'Sales Input'!D155,IF('Consolidated Sales'!$C$2=3,'Sales Input'!E155,IF('Consolidated Sales'!$C$2=4,'Sales Input'!F155,IF('Consolidated Sales'!$C$2=5,'Sales Input'!G155,IF('Consolidated Sales'!$C$2=6,'Sales Input'!H155,IF('Consolidated Sales'!$C$2=7,'Sales Input'!I155,IF('Consolidated Sales'!$C$2=8,'Sales Input'!J155,IF('Consolidated Sales'!$C$2=9,'Sales Input'!K155,IF('Consolidated Sales'!$C$2=10,'Sales Input'!L155,IF('Consolidated Sales'!$C$2=11,'Sales Input'!M155,IF('Consolidated Sales'!$C$2=12,'Sales Input'!N155,IF('Consolidated Sales'!$C$2=13,'Sales Input'!O155,0))))))))))))) -> 0 | J14: =C14-E14-G14-I14-K14 -> 0 | K14: =IF('Consolidated Sales'!$C$2=1,'Sales Input'!C177,IF('Consolidated Sales'!$C$2=2,'Sales Input'!D177,IF('Consolidated Sales'!$C$2=3,'Sales Input'!E177,IF('Consolidated Sales'!$C$2=4,'Sales Input'!F177,IF('Consolidated Sales'!$C$2=5,'Sales Input'!G177,IF('Consolidated Sales'!$C$2=6,'Sales Input'!H177,IF('Consolidated Sales'!$C$2=7,'Sales Input'!I177,IF('Consolidated Sales'!$C$2=8,'Sales Input'!J177,IF('Consolidated Sales'!$C$2=9,'Sales Input'!K177,IF('Consolidated Sales'!$C$2=10,'Sales Input'!L177,IF('Consolidated Sales'!$C$2=11,'Sales Input'!M177,IF('Consolidated Sales'!$C$2=12,'Sales Input'!N177,IF('Consolidated Sales'!$C$2=13,'Sales Input'!O177,0))))))))))))) -> 0 | L14: =C14-E14-G14-I14-K14 -> 0
B15: Central Poultry | C15: =IF('Consolidated Sales'!$C$2=1,'Sales Input'!C84,IF('Consolidated Sales'!$C$2=2,'Sales Input'!D84,IF('Consolidated Sales'!$C$2=3,'Sales Input'!E84,IF('Consolidated Sales'!$C$2=4,'Sales Input'!F84,IF('Consolidated Sales'!$C$2=5,'Sales Input'!G84,IF('Consolidated Sales'!$C$2=6,'Sales Input'!H84,IF('Consolidated Sales'!$C$2=7,'Sales Input'!I84,IF('Consolidated Sales'!$C$2=8,'Sales Input'!J84,IF('Consolidated Sales'!$C$2=9,'Sales Input'!K84,IF('Consolidated Sales'!$C$2=10,'Sales Input'!L84,IF('Consolidated Sales'!$C$2=11,'Sales Input'!M84,IF('Consolidated Sales'!$C$2=12,'Sales Input'!N84,IF('Consolidated Sales'!$C$2=13,'Sales Input'!O84,0))))))))))))) -> 0 | D15: =SUM(C15-E15-G15-I15-K15) -> 0 | E15: =IF('Consolidated Sales'!$C$2=1,'Sales Input'!C112,IF('Consolidated Sales'!$C$2=2,'Sales Input'!D112,IF('Consolidated Sales'!$C$2=3,'Sales Input'!E112,IF('Consolidated Sales'!$C$2=4,'Sales Input'!F112,IF('Consolidated Sales'!$C$2=5,'Sales Input'!G112,IF('Consolidated Sales'!$C$2=6,'Sales Input'!H112,IF('Consolidated Sales'!$C$2=7,'Sales Input'!I112,IF('Consolidated Sales'!$C$2=8,'Sales Input'!J112,IF('Consolidated Sales'!$C$2=9,'Sales Input'!K112,IF('Consolidated Sales'!$C$2=10,'Sales Input'!L112,IF('Consolidated Sales'!$C$2=11,'Sales Input'!M112,IF('Consolidated Sales'!$C$2=12,'Sales Input'!N112,IF('Consolidated Sales'!$C$2=13,'Sales Input'!O112,0))))))))))))) -> 0 | F15: =SUM(C15-E15-G15-I15-K15) -> 0 | G15: =IF('Consolidated Sales'!$C$2=1,'Sales Input'!C134,IF('Consolidated Sales'!$C$2=2,'Sales Input'!D134,IF('Consolidated Sales'!$C$2=3,'Sales Input'!E134,IF('Consolidated Sales'!$C$2=4,'Sales Input'!F134,IF('Consolidated Sales'!$C$2=5,'Sales Input'!G134,IF('Consolidated Sales'!$C$2=6,'Sales Input'!H134,IF('Consolidated Sales'!$C$2=7,'Sales Input'!I134,IF('Consolidated Sales'!$C$2=8,'Sales Input'!J134,IF('Consolidated Sales'!$C$2=9,'Sales Input'!K134,IF('Consolidated Sales'!$C$2=10,'Sales Input'!L134,IF('Consolidated Sales'!$C$2=11,'Sales Input'!M134,IF('Consolidated Sales'!$C$2=12,'Sales Input'!N134,IF('Consolidated Sales'!$C$2=13,'Sales Input'!O134,0))))))))))))) -> 0 | H15: =C15-E15-G15-I15-K15 -> 0 | I15: =IF('Consolidated Sales'!$C$2=1,'Sales Input'!C156,IF('Consolidated Sales'!$C$2=2,'Sales Input'!D156,IF('Consolidated Sales'!$C$2=3,'Sales Input'!E156,IF('Consolidated Sales'!$C$2=4,'Sales Input'!F156,IF('Consolidated Sales'!$C$2=5,'Sales Input'!G156,IF('Consolidated Sales'!$C$2=6,'Sales Input'!H156,IF('Consolidated Sales'!$C$2=7,'Sales Input'!I156,IF('Consolidated Sales'!$C$2=8,'Sales Input'!J156,IF('Consolidated Sales'!$C$2=9,'Sales Input'!K156,IF('Consolidated Sales'!$C$2=10,'Sales Input'!L156,IF('Consolidated Sales'!$C$2=11,'Sales Input'!M156,IF('Consolidated Sales'!$C$2=12,'Sales Input'!N156,IF('Consolidated Sales'!$C$2=13,'Sales Input'!O156,0))))))))))))) -> 0 | J15: =C15-E15-G15-I15-K15 -> 0 | K15: =IF('Consolidated Sales'!$C$2=1,'Sales Input'!C178,IF('Consolidated Sales'!$C$2=2,'Sales Input'!D178,IF('Consolidated Sales'!$C$2=3,'Sales Input'!E178,IF('Consolidated Sales'!$C$2=4,'Sales Input'!F178,IF('Consolidated Sales'!$C$2=5,'Sales Input'!G178,IF('Consolidated Sales'!$C$2=6,'Sales Input'!H178,IF('Consolidated Sales'!$C$2=7,'Sales Input'!I178,IF('Consolidated Sales'!$C$2=8,'Sales Input'!J178,IF('Consolidated Sales'!$C$2=9,'Sales Input'!K178,IF('Consolidated Sales'!$C$2=10,'Sales Input'!L178,IF('Consolidated Sales'!$C$2=11,'Sales Input'!M178,IF('Consolidated Sales'!$C$2=12,'Sales Input'!N178,IF('Consolidated Sales'!$C$2=13,'Sales Input'!O178,0))))))))))))) -> 0 | L15: =C15-E15-G15-I15-K15 -> 0
B16: Licorice Investment (Burundi Shop) | C16: =IF('Consolidated Sales'!$C$2=1,'Sales Input'!C85,IF('Consolidated Sales'!$C$2=2,'Sales Input'!D85,IF('Consolidated Sales'!$C$2=3,'Sales Input'!E85,IF('Consolidated Sales'!$C$2=4,'Sales Input'!F85,IF('Consolidated Sales'!$C$2=5,'Sales Input'!G85,IF('Consolidated Sales'!$C$2=6,'Sales Input'!H85,IF('Consolidated Sales'!$C$2=7,'Sales Input'!I85,IF('Consolidated Sales'!$C$2=8,'Sales Input'!J85,IF('Consolidated Sales'!$C$2=9,'Sales Input'!K85,IF('Consolidated Sales'!$C$2=10,'Sales Input'!L85,IF('Consolidated Sales'!$C$2=11,'Sales Input'!M85,IF('Consolidated Sales'!$C$2=12,'Sales Input'!N85,IF('Consolidated Sales'!$C$2=13,'Sales Input'!O85,0))))))))))))) -> 0 | D16: =SUM(C16-E16-G16-I16-K16) -> 0 | E16: =IF('Consolidated Sales'!$C$2=1,'Sales Input'!C113,IF('Consolidated Sales'!$C$2=2,'Sales Input'!D113,IF('Consolidated Sales'!$C$2=3,'Sales Input'!E113,IF('Consolidated Sales'!$C$2=4,'Sales Input'!F113,IF('Consolidated Sales'!$C$2=5,'Sales Input'!G113,IF('Consolidated Sales'!$C$2=6,'Sales Input'!H113,IF('Consolidated Sales'!$C$2=7,'Sales Input'!I113,IF('Consolidated Sales'!$C$2=8,'Sales Input'!J113,IF('Consolidated Sales'!$C$2=9,'Sales Input'!K113,IF('Consolidated Sales'!$C$2=10,'Sales Input'!L113,IF('Consolidated Sales'!$C$2=11,'Sales Input'!M113,IF('Consolidated Sales'!$C$2=12,'Sales Input'!N113,IF('Consolidated Sales'!$C$2=13,'Sales Input'!O113,0))))))))))))) -> 0 | F16: =SUM(C16-E16-G16-I16-K16) -> 0 | G16: =IF('Consolidated Sales'!$C$2=1,'Sales Input'!C135,IF('Consolidated Sales'!$C$2=2,'Sales Input'!D135,IF('Consolidated Sales'!$C$2=3,'Sales Input'!E135,IF('Consolidated Sales'!$C$2=4,'Sales Input'!F135,IF('Consolidated Sales'!$C$2=5,'Sales Input'!G135,IF('Consolidated Sales'!$C$2=6,'Sales Input'!H135,IF('Consolidated Sales'!$C$2=7,'Sales Input'!I135,IF('Consolidated Sales'!$C$2=8,'Sales Input'!J135,IF('Consolidated Sales'!$C$2=9,'Sales Input'!K135,IF('Consolidated Sales'!$C$2=10,'Sales Input'!L135,IF('Consolidated Sales'!$C$2=11,'Sales Input'!M135,IF('Consolidated Sales'!$C$2=12,'Sales Input'!N135,IF('Consolidated Sales'!$C$2=13,'Sales Input'!O135,0))))))))))))) -> 0 | H16: =C16-E16-G16-I16-K16 -> 0 | I16: =IF('Consolidated Sales'!$C$2=1,'Sales Input'!C157,IF('Consolidated Sales'!$C$2=2,'Sales Input'!D157,IF('Consolidated Sales'!$C$2=3,'Sales Input'!E157,IF('Consolidated Sales'!$C$2=4,'Sales Input'!F157,IF('Consolidated Sales'!$C$2=5,'Sales Input'!G157,IF('Consolidated Sales'!$C$2=6,'Sales Input'!H157,IF('Consolidated Sales'!$C$2=7,'Sales Input'!I157,IF('Consolidated Sales'!$C$2=8,'Sales Input'!J157,IF('Consolidated Sales'!$C$2=9,'Sales Input'!K157,IF('Consolidated Sales'!$C$2=10,'Sales Input'!L157,IF('Consolidated Sales'!$C$2=11,'Sales Input'!M157,IF('Consolidated Sales'!$C$2=12,'Sales Input'!N157,IF('Consolidated Sales'!$C$2=13,'Sales Input'!O157,0))))))))))))) -> 0 | J16: =C16-E16-G16-I16-K16 -> 0 | K16: =IF('Consolidated Sales'!$C$2=1,'Sales Input'!C179,IF('Consolidated Sales'!$C$2=2,'Sales Input'!D179,IF('Consolidated Sales'!$C$2=3,'Sales Input'!E179,IF('Consolidated Sales'!$C$2=4,'Sales Input'!F179,IF('Consolidated Sales'!$C$2=5,'Sales Input'!G179,IF('Consolidated Sales'!$C$2=6,'Sales Input'!H179,IF('Consolidated Sales'!$C$2=7,'Sales Input'!I179,IF('Consolidated Sales'!$C$2=8,'Sales Input'!J179,IF('Consolidated Sales'!$C$2=9,'Sales Input'!K179,IF('Consolidated Sales'!$C$2=10,'Sales Input'!L179,IF('Consolidated Sales'!$C$2=11,'Sales Input'!M179,IF('Consolidated Sales'!$C$2=12,'Sales Input'!N179,IF('Consolidated Sales'!$C$2=13,'Sales Input'!O179,0))))))))))))) -> 0 | L16: =C16-E16-G16-I16-K16 -> 0
B17: Insco Trading | C17: =IF('Consolidated Sales'!$C$2=1,'Sales Input'!C86,IF('Consolidated Sales'!$C$2=2,'Sales Input'!D86,IF('Consolidated Sales'!$C$2=3,'Sales Input'!E86,IF('Consolidated Sales'!$C$2=4,'Sales Input'!F86,IF('Consolidated Sales'!$C$2=5,'Sales Input'!G86,IF('Consolidated Sales'!$C$2=6,'Sales Input'!H86,IF('Consolidated Sales'!$C$2=7,'Sales Input'!I86,IF('Consolidated Sales'!$C$2=8,'Sales Input'!J86,IF('Consolidated Sales'!$C$2=9,'Sales Input'!K86,IF('Consolidated Sales'!$C$2=10,'Sales Input'!L86,IF('Consolidated Sales'!$C$2=11,'Sales Input'!M86,IF('Consolidated Sales'!$C$2=12,'Sales Input'!N86,IF('Consolidated Sales'!$C$2=13,'Sales Input'!O86,0))))))))))))) -> 647850 | D17: =SUM(C17-E17-G17-I17-K17) -> 0 | E17: =IF('Consolidated Sales'!$C$2=1,'Sales Input'!C114,IF('Consolidated Sales'!$C$2=2,'Sales Input'!D114,IF('Consolidated Sales'!$C$2=3,'Sales Input'!E114,IF('Consolidated Sales'!$C$2=4,'Sales Input'!F114,IF('Consolidated Sales'!$C$2=5,'Sales Input'!G114,IF('Consolidated Sales'!$C$2=6,'Sales Input'!H114,IF('Consolidated Sales'!$C$2=7,'Sales Input'!I114,IF('Consolidated Sales'!$C$2=8,'Sales Input'!J114,IF('Consolidated Sales'!$C$2=9,'Sales Input'!K114,IF('Consolidated Sales'!$C$2=10,'Sales Input'!L114,IF('Consolidated Sales'!$C$2=11,'Sales Input'!M114,IF('Consolidated Sales'!$C$2=12,'Sales Input'!N114,IF('Consolidated Sales'!$C$2=13,'Sales Input'!O114,0))))))))))))) -> 0 | F17: =SUM(C17-E17-G17-I17-K17) -> 0 | G17: =IF('Consolidated Sales'!$C$2=1,'Sales Input'!C136,IF('Consolidated Sales'!$C$2=2,'Sales Input'!D136,IF('Consolidated Sales'!$C$2=3,'Sales Input'!E136,IF('Consolidated Sales'!$C$2=4,'Sales Input'!F136,IF('Consolidated Sales'!$C$2=5,'Sales Input'!G136,IF('Consolidated Sales'!$C$2=6,'Sales Input'!H136,IF('Consolidated Sales'!$C$2=7,'Sales Input'!I136,IF('Consolidated Sales'!$C$2=8,'Sales Input'!J136,IF('Consolidated Sales'!$C$2=9,'Sales Input'!K136,IF('Consolidated Sales'!$C$2=10,'Sales Input'!L136,IF('Consolidated Sales'!$C$2=11,'Sales Input'!M136,IF('Consolidated Sales'!$C$2=12,'Sales Input'!N136,IF('Consolidated Sales'!$C$2=13,'Sales Input'!O136,0))))))))))))) -> 647850 | H17: =C17-E17-G17-I17-K17 -> 0 | I17: =IF('Consolidated Sales'!$C$2=1,'Sales Input'!C158,IF('Consolidated Sales'!$C$2=2,'Sales Input'!D158,IF('Consolidated Sales'!$C$2=3,'Sales Input'!E158,IF('Consolidated Sales'!$C$2=4,'Sales Input'!F158,IF('Consolidated Sales'!$C$2=5,'Sales Input'!G158,IF('Consolidated Sales'!$C$2=6,'Sales Input'!H158,IF('Consolidated Sales'!$C$2=7,'Sales Input'!I158,IF('Consolidated Sales'!$C$2=8,'Sales Input'!J158,IF('Consolidated Sales'!$C$2=9,'Sales Input'!K158,IF('Consolidated Sales'!$C$2=10,'Sales Input'!L158,IF('Consolidated Sales'!$C$2=11,'Sales Input'!M158,IF('Consolidated Sales'!$C$2=12,'Sales Input'!N158,IF('Consolidated Sales'!$C$2=13,'Sales Input'!O158,0))))))))))))) -> 0 | J17: =C17-E17-G17-I17-K17 -> 0 | K17: =IF('Consolidated Sales'!$C$2=1,'Sales Input'!C180,IF('Consolidated Sales'!$C$2=2,'Sales Input'!D180,IF('Consolidated Sales'!$C$2=3,'Sales Input'!E180,IF('Consolidated Sales'!$C$2=4,'Sales Input'!F180,IF('Consolidated Sales'!$C$2=5,'Sales Input'!G180,IF('Consolidated Sales'!$C$2=6,'Sales Input'!H180,IF('Consolidated Sales'!$C$2=7,'Sales Input'!I180,IF('Consolidated Sales'!$C$2=8,'Sales Input'!J180,IF('Consolidated Sales'!$C$2=9,'Sales Input'!K180,IF('Consolidated Sales'!$C$2=10,'Sales Input'!L180,IF('Consolidated Sales'!$C$2=11,'Sales Input'!M180,IF('Consolidated Sales'!$C$2=12,'Sales Input'!N180,IF('Consolidated Sales'!$C$2=13,'Sales Input'!O180,0))))))))))))) -> 0 | L17: =C17-E17-G17-I17-K17 -> 0
B18: Chimwemwe Mafeni Trading | C18: =IF('Consolidated Sales'!$C$2=1,'Sales Input'!C87,IF('Consolidated Sales'!$C$2=2,'Sales Input'!D87,IF('Consolidated Sales'!$C$2=3,'Sales Input'!E87,IF('Consolidated Sales'!$C$2=4,'Sales Input'!F87,IF('Consolidated Sales'!$C$2=5,'Sales Input'!G87,IF('Consolidated Sales'!$C$2=6,'Sales Input'!H87,IF('Consolidated Sales'!$C$2=7,'Sales Input'!I87,IF('Consolidated Sales'!$C$2=8,'Sales Input'!J87,IF('Consolidated Sales'!$C$2=9,'Sales Input'!K87,IF('Consolidated Sales'!$C$2=10,'Sales Input'!L87,IF('Consolidated Sales'!$C$2=11,'Sales Input'!M87,IF('Consolidated Sales'!$C$2=12,'Sales Input'!N87,IF('Consolidated Sales'!$C$2=13,'Sales Input'!O87,0))))))))))))) -> 736199.99 | D18: =SUM(C18-E18-G18-I18-K18) -> 0 | E18: =IF('Consolidated Sales'!$C$2=1,'Sales Input'!C115,IF('Consolidated Sales'!$C$2=2,'Sales Input'!D115,IF('Consolidated Sales'!$C$2=3,'Sales Input'!E115,IF('Consolidated Sales'!$C$2=4,'Sales Input'!F115,IF('Consolidated Sales'!$C$2=5,'Sales Input'!G115,IF('Consolidated Sales'!$C$2=6,'Sales Input'!H115,IF('Consolidated Sales'!$C$2=7,'Sales Input'!I115,IF('Consolidated Sales'!$C$2=8,'Sales Input'!J115,IF('Consolidated Sales'!$C$2=9,'Sales Input'!K115,IF('Consolidated Sales'!$C$2=10,'Sales Input'!L115,IF('Consolidated Sales'!$C$2=11,'Sales Input'!M115,IF('Consolidated Sales'!$C$2=12,'Sales Input'!N115,IF('Consolidated Sales'!$C$2=13,'Sales Input'!O115,0))))))))))))) -> 0 | F18: =SUM(C18-E18-G18-I18-K18) -> 0 | G18: =IF('Consolidated Sales'!$C$2=1,'Sales Input'!C137,IF('Consolidated Sales'!$C$2=2,'Sales Input'!D137,IF('Consolidated Sales'!$C$2=3,'Sales Input'!E137,IF('Consolidated Sales'!$C$2=4,'Sales Input'!F137,IF('Consolidated Sales'!$C$2=5,'Sales Input'!G137,IF('Consolidated Sales'!$C$2=6,'Sales Input'!H137,IF('Consolidated Sales'!$C$2=7,'Sales Input'!I137,IF('Consolidated Sales'!$C$2=8,'Sales Input'!J137,IF('Consolidated Sales'!$C$2=9,'Sales Input'!K137,IF('Consolidated Sales'!$C$2=10,'Sales Input'!L137,IF('Consolidated Sales'!$C$2=11,'Sales Input'!M137,IF('Consolidated Sales'!$C$2=12,'Sales Input'!N137,IF('Consolidated Sales'!$C$2=13,'Sales Input'!O137,0))))))))))))) -> 736199.99 | H18: =C18-E18-G18-I18-K18 -> 0 | I18: =IF('Consolidated Sales'!$C$2=1,'Sales Input'!C159,IF('Consolidated Sales'!$C$2=2,'Sales Input'!D159,IF('Consolidated Sales'!$C$2=3,'Sales Input'!E159,IF('Consolidated Sales'!$C$2=4,'Sales Input'!F159,IF('Consolidated Sales'!$C$2=5,'Sales Input'!G159,IF('Consolidated Sales'!$C$2=6,'Sales Input'!H159,IF('Consolidated Sales'!$C$2=7,'Sales Input'!I159,IF('Consolidated Sales'!$C$2=8,'Sales Input'!J159,IF('Consolidated Sales'!$C$2=9,'Sales Input'!K159,IF('Consolidated Sales'!$C$2=10,'Sales Input'!L159,IF('Consolidated Sales'!$C$2=11,'Sales Input'!M159,IF('Consolidated Sales'!$C$2=12,'Sales Input'!N159,IF('Consolidated Sales'!$C$2=13,'Sales Input'!O159,0))))))))))))) -> 0 | J18: =C18-E18-G18-I18-K18 -> 0 | K18: =IF('Consolidated Sales'!$C$2=1,'Sales Input'!C181,IF('Consolidated Sales'!$C$2=2,'Sales Input'!D181,IF('Consolidated Sales'!$C$2=3,'Sales Input'!E181,IF('Consolidated Sales'!$C$2=4,'Sales Input'!F181,IF('Consolidated Sales'!$C$2=5,'Sales Input'!G181,IF('Consolidated Sales'!$C$2=6,'Sales Input'!H181,IF('Consolidated Sales'!$C$2=7,'Sales Input'!I181,IF('Consolidated Sales'!$C$2=8,'Sales Input'!J181,IF('Consolidated Sales'!$C$2=9,'Sales Input'!K181,IF('Consolidated Sales'!$C$2=10,'Sales Input'!L181,IF('Consolidated Sales'!$C$2=11,'Sales Input'!M181,IF('Consolidated Sales'!$C$2=12,'Sales Input'!N181,IF('Consolidated Sales'!$C$2=13,'Sales Input'!O181,0))))))))))))) -> 0 | L18: =C18-E18-G18-I18-K18 -> 0
B19: Lilongwe Dairy | C19: =IF('Consolidated Sales'!$C$2=1,'Sales Input'!C88,IF('Consolidated Sales'!$C$2=2,'Sales Input'!D88,IF('Consolidated Sales'!$C$2=3,'Sales Input'!E88,IF('Consolidated Sales'!$C$2=4,'Sales Input'!F88,IF('Consolidated Sales'!$C$2=5,'Sales Input'!G88,IF('Consolidated Sales'!$C$2=6,'Sales Input'!H88,IF('Consolidated Sales'!$C$2=7,'Sales Input'!I88,IF('Consolidated Sales'!$C$2=8,'Sales Input'!J88,IF('Consolidated Sales'!$C$2=9,'Sales Input'!K88,IF('Consolidated Sales'!$C$2=10,'Sales Input'!L88,IF('Consolidated Sales'!$C$2=11,'Sales Input'!M88,IF('Consolidated Sales'!$C$2=12,'Sales Input'!N88,IF('Consolidated Sales'!$C$2=13,'Sales Input'!O88,0))))))))))))) -> 0 | D19: =SUM(C19-E19-G19-I19-K19) -> 0 | E19: =IF('Consolidated Sales'!$C$2=1,'Sales Input'!C116,IF('Consolidated Sales'!$C$2=2,'Sales Input'!D116,IF('Consolidated Sales'!$C$2=3,'Sales Input'!E116,IF('Consolidated Sales'!$C$2=4,'Sales Input'!F116,IF('Consolidated Sales'!$C$2=5,'Sales Input'!G116,IF('Consolidated Sales'!$C$2=6,'Sales Input'!H116,IF('Consolidated Sales'!$C$2=7,'Sales Input'!I116,IF('Consolidated Sales'!$C$2=8,'Sales Input'!J116,IF('Consolidated Sales'!$C$2=9,'Sales Input'!K116,IF('Consolidated Sales'!$C$2=10,'Sales Input'!L116,IF('Consolidated Sales'!$C$2=11,'Sales Input'!M116,IF('Consolidated Sales'!$C$2=12,'Sales Input'!N116,IF('Consolidated Sales'!$C$2=13,'Sales Input'!O116,0))))))))))))) -> 0 | F19: =SUM(C19-E19-G19-I19-K19) -> 0 | G19: =IF('Consolidated Sales'!$C$2=1,'Sales Input'!C138,IF('Consolidated Sales'!$C$2=2,'Sales Input'!D138,IF('Consolidated Sales'!$C$2=3,'Sales Input'!E138,IF('Consolidated Sales'!$C$2=4,'Sales Input'!F138,IF('Consolidated Sales'!$C$2=5,'Sales Input'!G138,IF('Consolidated Sales'!$C$2=6,'Sales Input'!H138,IF('Consolidated Sales'!$C$2=7,'Sales Input'!I138,IF('Consolidated Sales'!$C$2=8,'Sales Input'!J138,IF('Consolidated Sales'!$C$2=9,'Sales Input'!K138,IF('Consolidated Sales'!$C$2=10,'Sales Input'!L138,IF('Consolidated Sales'!$C$2=11,'Sales Input'!M138,IF('Consolidated Sales'!$C$2=12,'Sales Input'!N138,IF('Consolidated Sales'!$C$2=13,'Sales Input'!O138,0))))))))))))) -> 0 | H19: =C19-E19-G19-I19-K19 -> 0 | I19: =IF('Consolidated Sales'!$C$2=1,'Sales Input'!C160,IF('Consolidated Sales'!$C$2=2,'Sales Input'!D160,IF('Consolidated Sales'!$C$2=3,'Sales Input'!E160,IF('Consolidated Sales'!$C$2=4,'Sales Input'!F160,IF('Consolidated Sales'!$C$2=5,'Sales Input'!G160,IF('Consolidated Sales'!$C$2=6,'Sales Input'!H160,IF('Consolidated Sales'!$C$2=7,'Sales Input'!I160,IF('Consolidated Sales'!$C$2=8,'Sales Input'!J160,IF('Consolidated Sales'!$C$2=9,'Sales Input'!K160,IF('Consolidated Sales'!$C$2=10,'Sales Input'!L160,IF('Consolidated Sales'!$C$2=11,'Sales Input'!M160,IF('Consolidated Sales'!$C$2=12,'Sales Input'!N160,IF('Consolidated Sales'!$C$2=13,'Sales Input'!O160,0))))))))))))) -> 0 | J19: =C19-E19-G19-I19-K19 -> 0 | K19: =IF('Consolidated Sales'!$C$2=1,'Sales Input'!C182,IF('Consolidated Sales'!$C$2=2,'Sales Input'!D182,IF('Consolidated Sales'!$C$2=3,'Sales Input'!E182,IF('Consolidated Sales'!$C$2=4,'Sales Input'!F182,IF('Consolidated Sales'!$C$2=5,'Sales Input'!G182,IF('Consolidated Sales'!$C$2=6,'Sales Input'!H182,IF('Consolidated Sales'!$C$2=7,'Sales Input'!I182,IF('Consolidated Sales'!$C$2=8,'Sales Input'!J182,IF('Consolidated Sales'!$C$2=9,'Sales Input'!K182,IF('Consolidated Sales'!$C$2=10,'Sales Input'!L182,IF('Consolidated Sales'!$C$2=11,'Sales Input'!M182,IF('Consolidated Sales'!$C$2=12,'Sales Input'!N182,IF('Consolidated Sales'!$C$2=13,'Sales Input'!O182,0))))))))))))) -> 0 | L19: =C19-E19-G19-I19-K19 -> 0
... B25: Other Products | C25: =IF('Consolidated Sales'!$C$2=1,'Sales Input'!C94,IF('Consolidated Sales'!$C$2=2,'Sales Input'!D94,IF('Consolidated Sales'!$C$2=3,'Sales Input'!E94,IF('Consolidated Sales'!$C$2=4,'Sales Input'!F94,IF('Consolidated Sales'!$C$2=5,'Sales Input'!G94,IF('Consolidated Sales'!$C$2=6,'Sales Input'!H94,IF('Consolidated Sales'!$C$2=7,'Sales Input'!I94,IF('Consolidated Sales'!$C$2=8,'Sales Input'!J94,IF('Consolidated Sales'!$C$2=9,'Sales Input'!K94,IF('Consolidated Sales'!$C$2=10,'Sales Input'!L94,IF('Consolidated Sales'!$C$2=11,'Sales Input'!M94,IF('Consolidated Sales'!$C$2=12,'Sales Input'!N94,IF('Consolidated Sales'!$C$2=13,'Sales Input'!O94,0))))))))))))) -> 64000 | D25: =SUM(C25-E25-G25-I25-K25) -> 0 | E25: =IF('Consolidated Sales'!$C$2=1,'Sales Input'!C122,IF('Consolidated Sales'!$C$2=2,'Sales Input'!D122,IF('Consolidated Sales'!$C$2=3,'Sales Input'!E122,IF('Consolidated Sales'!$C$2=4,'Sales Input'!F122,IF('Consolidated Sales'!$C$2=5,'Sales Input'!G122,IF('Consolidated Sales'!$C$2=6,'Sales Input'!H122,IF('Consolidated Sales'!$C$2=7,'Sales Input'!I122,IF('Consolidated Sales'!$C$2=8,'Sales Input'!J122,IF('Consolidated Sales'!$C$2=9,'Sales Input'!K122,IF('Consolidated Sales'!$C$2=10,'Sales Input'!L122,IF('Consolidated Sales'!$C$2=11,'Sales Input'!M122,IF('Consolidated Sales'!$C$2=12,'Sales Input'!N122,IF('Consolidated Sales'!$C$2=13,'Sales Input'!O122,0))))))))))))) -> 0 | F25: =SUM(C25-E25-G25-I25-K25) -> 0 | G25: =IF('Consolidated Sales'!$C$2=1,'Sales Input'!C144,IF('Consolidated Sales'!$C$2=2,'Sales Input'!D144,IF('Consolidated Sales'!$C$2=3,'Sales Input'!E144,IF('Consolidated Sales'!$C$2=4,'Sales Input'!F144,IF('Consolidated Sales'!$C$2=5,'Sales Input'!G144,IF('Consolidated Sales'!$C$2=6,'Sales Input'!H144,IF('Consolidated Sales'!$C$2=7,'Sales Input'!I144,IF('Consolidated Sales'!$C$2=8,'Sales Input'!J144,IF('Consolidated Sales'!$C$2=9,'Sales Input'!K144,IF('Consolidated Sales'!$C$2=10,'Sales Input'!L144,IF('Consolidated Sales'!$C$2=11,'Sales Input'!M144,IF('Consolidated Sales'!$C$2=12,'Sales Input'!N144,IF('Consolidated Sales'!$C$2=13,'Sales Input'!O144,0))))))))))))) -> 64000 | H25: =C25-E25-G25-I25-K25 -> 0 | I25: =IF('Consolidated Sales'!$C$2=1,'Sales Input'!C166,IF('Consolidated Sales'!$C$2=2,'Sales Input'!D166,IF('Consolidated Sales'!$C$2=3,'Sales Input'!E166,IF('Consolidated Sales'!$C$2=4,'Sales Input'!F166,IF('Consolidated Sales'!$C$2=5,'Sales Input'!G166,IF('Consolidated Sales'!$C$2=6,'Sales Input'!H166,IF('Consolidated Sales'!$C$2=7,'Sales Input'!I166,IF('Consolidated Sales'!$C$2=8,'Sales Input'!J166,IF('Consolidated Sales'!$C$2=9,'Sales Input'!K166,IF('Consolidated Sales'!$C$2=10,'Sales Input'!L166,IF('Consolidated Sales'!$C$2=11,'Sales Input'!M166,IF('Consolidated Sales'!$C$2=12,'Sales Input'!N166,IF('Consolidated Sales'!$C$2=13,'Sales Input'!O166,0))))))))))))) -> 0 | J25: =C25-E25-G25-I25-K25 -> 0 | K25: =IF('Consolidated Sales'!$C$2=1,'Sales Input'!C188,IF('Consolidated Sales'!$C$2=2,'Sales Input'!D188,IF('Consolidated Sales'!$C$2=3,'Sales Input'!E188,IF('Consolidated Sales'!$C$2=4,'Sales Input'!F188,IF('Consolidated Sales'!$C$2=5,'Sales Input'!G188,IF('Consolidated Sales'!$C$2=6,'Sales Input'!H188,IF('Consolidated Sales'!$C$2=7,'Sales Input'!I188,IF('Consolidated Sales'!$C$2=8,'Sales Input'!J188,IF('Consolidated Sales'!$C$2=9,'Sales Input'!K188,IF('Consolidated Sales'!$C$2=10,'Sales Input'!L188,IF('Consolidated Sales'!$C$2=11,'Sales Input'!M188,IF('Consolidated Sales'!$C$2=12,'Sales Input'!N188,IF('Consolidated Sales'!$C$2=13,'Sales Input'!O188,0))))))))))))) -> 0 | L25: =C25-E25-G25-I25-K25 -> 0
B27: Totals Due | C27: =SUM(C6:C25) -> 7905085.5 | D27: =SUM(D6:D25) -> 0 | E27: =SUM(E6:E25) -> 0 | F27: =SUM(F6:F25) -> 0 | G27: =SUM(G6:G25) -> 7800385.5 | H27: =SUM(H6:H25) -> 0 | I27: =SUM(I6:I25) -> 104700 | J27: =SUM(J6:J25) -> 0 | K27: =SUM(K7:K25) -> 0 | L27: =SUM(L7:L25) -> 0
B29: Net Balances | E29: ='Consolidated Sales'!C87-E27 -> 580000 | G29: =SUM('Consolidated Sales'!C81+'Consolidated Sales'!C82-G27) -> 1227874.5 | I29: =SUM('Consolidated Sales'!C83+'Consolidated Sales'!C84-I27) -> 2505000 | K29: =SUM('Consolidated Sales'!C85-K27) -> 0

Sheet Expenses Report
B1: EXPENSES REPORT
C6: Total Expenses | E6: Payments by Cash-in-Hand | G6: Payments by Bank Transfer | I6: Payments by Wallet
B7: Expense Distribution | C7: Debt Amount | D7: Outstanding Amount | E7: Amount Paid | F7: Outstanding Amount | G7: Amount Paid | H7: Outstanding Amount | I7: Amount Paid | J7: Outstanding Amount
B8: Wages for the Month | C8: =IF('Consolidated Sales'!$C$2=1,'Sales Input'!C194,IF('Consolidated Sales'!$C$2=2,'Sales Input'!D194,IF('Consolidated Sales'!$C$2=3,'Sales Input'!E194,IF('Consolidated Sales'!$C$2=4,'Sales Input'!F194,IF('Consolidated Sales'!$C$2=5,'Sales Input'!G194,IF('Consolidated Sales'!$C$2=6,'Sales Input'!H194,IF('Consolidated Sales'!$C$2=7,'Sales Input'!I194,IF('Consolidated Sales'!$C$2=8,'Sales Input'!J194,IF('Consolidated Sales'!$C$2=9,'Sales Input'!K194,IF('Consolidated Sales'!$C$2=10,'Sales Input'!L194,IF('Consolidated Sales'!$C$2=11,'Sales Input'!M194,IF('Consolidated Sales'!$C$2=12,'Sales Input'!N194,IF('Consolidated Sales'!$C$2=13,'Sales Input'!O194,0))))))))))))) -> 1260000 | D8: =SUM(C8-E8-G8-I8) -> 0 | E8: =IF('Consolidated Sales'!$C$2=1,'Sales Input'!C208,IF('Consolidated Sales'!$C$2=2,'Sales Input'!D208,IF('Consolidated Sales'!$C$2=3,'Sales Input'!E208,IF('Consolidated Sales'!$C$2=4,'Sales Input'!F208,IF('Consolidated Sales'!$C$2=5,'Sales Input'!G208,IF('Consolidated Sales'!$C$2=6,'Sales Input'!H208,IF('Consolidated Sales'!$C$2=7,'Sales Input'!I208,IF('Consolidated Sales'!$C$2=8,'Sales Input'!J208,IF('Consolidated Sales'!$C$2=9,'Sales Input'!K208,IF('Consolidated Sales'!$C$2=10,'Sales Input'!L208,IF('Consolidated Sales'!$C$2=11,'Sales Input'!M208,IF('Consolidated Sales'!$C$2=12,'Sales Input'!N208,IF('Consolidated Sales'!$C$2=13,'Sales Input'!O208,0))))))))))))) -> 0 | F8: =SUM(C8-G8-I8) -> 0 | G8: =IF('Consolidated Sales'!$C$2=1,'Sales Input'!C222,IF('Consolidated Sales'!$C$2=2,'Sales Input'!D222,IF('Consolidated Sales'!$C$2=3,'Sales Input'!E222,IF('Consolidated Sales'!$C$2=4,'Sales Input'!F222,IF('Consolidated Sales'!$C$2=5,'Sales Input'!G222,IF('Consolidated Sales'!$C$2=6,'Sales Input'!H222,IF('Consolidated Sales'!$C$2=7,'Sales Input'!I222,IF('Consolidated Sales'!$C$2=8,'Sales Input'!J222,IF('Consolidated Sales'!$C$2=9,'Sales Input'!K222,IF('Consolidated Sales'!$C$2=10,'Sales Input'!L222,IF('Consolidated Sales'!$C$2=11,'Sales Input'!M222,IF('Consolidated Sales'!$C$2=12,'Sales Input'!N222,IF('Consolidated Sales'!$C$2=13,'Sales Input'!O222,0))))))))))))) -> 0 | H8: =SUM(C8-E8-G8-I8) -> 0 | I8: =IF('Consolidated Sales'!$C$2=1,'Sales Input'!C236,IF('Consolidated Sales'!$C$2=2,'Sales Input'!D236,IF('Consolidated Sales'!$C$2=3,'Sales Input'!E236,IF('Consolidated Sales'!$C$2=4,'Sales Input'!F236,IF('Consolidated Sales'!$C$2=5,'Sales Input'!G236,IF('Consolidated Sales'!$C$2=6,'Sales Input'!H236,IF('Consolidated Sales'!$C$2=7,'Sales Input'!I236,IF('Consolidated Sales'!$C$2=8,'Sales Input'!J236,IF('Consolidated Sales'!$C$2=9,'Sales Input'!K236,IF('Consolidated Sales'!$C$2=10,'Sales Input'!L236,IF('Consolidated Sales'!$C$2=11,'Sales Input'!M236,IF('Consolidated Sales'!$C$2=12,'Sales Input'!N236,IF('Consolidated Sales'!$C$2=13,'Sales Input'!O236,0))))))))))))) -> 1260000 | J8: =SUM(C8-E8-G8-I8) -> 0
B9: Utility Expenses | C9: =SUM(C10:C12) -> 329500 | D9: =SUM(C9-E9-G9-I9) -> 0 | E9: =SUM(E10:E12) -> 0 | F9: =SUM(C9-G9-I9) -> 0 | G9: =SUM(G10:G12) -> 59500 | H9: =SUM(C9-E9-G9-I9) -> 0 | I9: =SUM(I10:I12) -> 270000 | J9: =SUM(C9-E9-G9-I9) -> 0
B10: 1. Water | C10: =IF('Consolidated Sales'!$C$2=1,'Sales Input'!C195,IF('Consolidated Sales'!$C$2=2,'Sales Input'!D195,IF('Consolidated Sales'!$C$2=3,'Sales Input'!E195,IF('Consolidated Sales'!$C$2=4,'Sales Input'!F195,IF('Consolidated Sales'!$C$2=5,'Sales Input'!G195,IF('Consolidated Sales'!$C$2=6,'Sales Input'!H195,IF('Consolidated Sales'!$C$2=7,'Sales Input'!I195,IF('Consolidated Sales'!$C$2=8,'Sales Input'!J195,IF('Consolidated Sales'!$C$2=9,'Sales Input'!K195,IF('Consolidated Sales'!$C$2=10,'Sales Input'!L195,IF('Consolidated Sales'!$C$2=11,'Sales Input'!M195,IF('Consolidated Sales'!$C$2=12,'Sales Input'!N195,IF('Consolidated Sales'!$C$2=13,'Sales Input'!O195,0))))))))))))) -> 70000 | D10: =SUM(C10-E10-G10-I10) -> 0 | E10: =IF('Consolidated Sales'!$C$2=1,'Sales Input'!C209,IF('Consolidated Sales'!$C$2=2,'Sales Input'!D209,IF('Consolidated Sales'!$C$2=3,'Sales Input'!E209,IF('Consolidated Sales'!$C$2=4,'Sales Input'!F209,IF('Consolidated Sales'!$C$2=5,'Sales Input'!G209,IF('Consolidated Sales'!$C$2=6,'Sales Input'!H209,IF('Consolidated Sales'!$C$2=7,'Sales Input'!I209,IF('Consolidated Sales'!$C$2=8,'Sales Input'!J209,IF('Consolidated Sales'!$C$2=9,'Sales Input'!K209,IF('Consolidated Sales'!$C$2=10,'Sales Input'!L209,IF('Consolidated Sales'!$C$2=11,'Sales Input'!M209,IF('Consolidated Sales'!$C$2=12,'Sales Input'!N209,IF('Consolidated Sales'!$C$2=13,'Sales Input'!O209,0))))))))))))) -> 0 | F10: =SUM(C10-G10-I10) -> 0 | G10: =IF('Consolidated Sales'!$C$2=1,'Sales Input'!C223,IF('Consolidated Sales'!$C$2=2,'Sales Input'!D223,IF('Consolidated Sales'!$C$2=3,'Sales Input'!E223,IF('Consolidated Sales'!$C$2=4,'Sales Input'!F223,IF('Consolidated Sales'!$C$2=5,'Sales Input'!G223,IF('Consolidated Sales'!$C$2=6,'Sales Input'!H223,IF('Consolidated Sales'!$C$2=7,'Sales Input'!I223,IF('Consolidated Sales'!$C$2=8,'Sales Input'!J223,IF('Consolidated Sales'!$C$2=9,'Sales Input'!K223,IF('Consolidated Sales'!$C$2=10,'Sales Input'!L223,IF('Consolidated Sales'!$C$2=11,'Sales Input'!M223,IF('Consolidated Sales'!$C$2=12,'Sales Input'!N223,IF('Consolidated Sales'!$C$2=13,'Sales Input'!O223,0))))))))))))) -> 0 | H10: =SUM(C10-E10-G10-I10) -> 0 | I10: =IF('Consolidated Sales'!$C$2=1,'Sales Input'!C237,IF('Consolidated Sales'!$C$2=2,'Sales Input'!D237,IF('Consolidated Sales'!$C$2=3,'Sales Input'!E237,IF('Consolidated Sales'!$C$2=4,'Sales Input'!F237,IF('Consolidated Sales'!$C$2=5,'Sales Input'!G237,IF('Consolidated Sales'!$C$2=6,'Sales Input'!H237,IF('Consolidated Sales'!$C$2=7,'Sales Input'!I237,IF('Consolidated Sales'!$C$2=8,'Sales Input'!J237,IF('Consolidated Sales'!$C$2=9,'Sales Input'!K237,IF('Consolidated Sales'!$C$2=10,'Sales Input'!L237,IF('Consolidated Sales'!$C$2=11,'Sales Input'!M237,IF('Consolidated Sales'!$C$2=12,'Sales Input'!N237,IF('Consolidated Sales'!$C$2=13,'Sales Input'!O237,0))))))))))))) -> 70000 | J10: =SUM(C10-E10-G10-I10) -> 0
B11: 2. Electricity | C11: =IF('Consolidated Sales'!$C$2=1,'Sales Input'!C196,IF('Consolidated Sales'!$C$2=2,'Sales Input'!D196,IF('Consolidated Sales'!$C$2=3,'Sales Input'!E196,IF('Consolidated Sales'!$C$2=4,'Sales Input'!F196,IF('Consolidated Sales'!$C$2=5,'Sales Input'!G196,IF('Consolidated Sales'!$C$2=6,'Sales Input'!H196,IF('Consolidated Sales'!$C$2=7,'Sales Input'!I196,IF('Consolidated Sales'!$C$2=8,'Sales Input'!J196,IF('Consolidated Sales'!$C$2=9,'Sales Input'!K196,IF('Consolidated Sales'!$C$2=10,'Sales Input'!L196,IF('Consolidated Sales'!$C$2=11,'Sales Input'!M196,IF('Consolidated Sales'!$C$2=12,'Sales Input'!N196,IF('Consolidated Sales'!$C$2=13,'Sales Input'!O196,0))))))))))))) -> 200000 | D11: =SUM(C11-E11-G11-I11) -> 0 | E11: =IF('Consolidated Sales'!$C$2=1,'Sales Input'!C210,IF('Consolidated Sales'!$C$2=2,'Sales Input'!D210,IF('Consolidated Sales'!$C$2=3,'Sales Input'!E210,IF('Consolidated Sales'!$C$2=4,'Sales Input'!F210,IF('Consolidated Sales'!$C$2=5,'Sales Input'!G210,IF('Consolidated Sales'!$C$2=6,'Sales Input'!H210,IF('Consolidated Sales'!$C$2=7,'Sales Input'!I210,IF('Consolidated Sales'!$C$2=8,'Sales Input'!J210,IF('Consolidated Sales'!$C$2=9,'Sales Input'!K210,IF('Consolidated Sales'!$C$2=10,'Sales Input'!L210,IF('Consolidated Sales'!$C$2=11,'Sales Input'!M210,IF('Consolidated Sales'!$C$2=12,'Sales Input'!N210,IF('Consolidated Sales'!$C$2=13,'Sales Input'!O210,0))))))))))))) -> 0 | F11: =SUM(C11-G11-I11) -> 0 | G11: =IF('Consolidated Sales'!$C$2=1,'Sales Input'!C224,IF('Consolidated Sales'!$C$2=2,'Sales Input'!D224,IF('Consolidated Sales'!$C$2=3,'Sales Input'!E224,IF('Consolidated Sales'!$C$2=4,'Sales Input'!F224,IF('Consolidated Sales'!$C$2=5,'Sales Input'!G224,IF('Consolidated Sales'!$C$2=6,'Sales Input'!H224,IF('Consolidated Sales'!$C$2=7,'Sales Input'!I224,IF('Consolidated Sales'!$C$2=8,'Sales Input'!J224,IF('Consolidated Sales'!$C$2=9,'Sales Input'!K224,IF('Consolidated Sales'!$C$2=10,'Sales Input'!L224,IF('Consolidated Sales'!$C$2=11,'Sales Input'!M224,IF('Consolidated Sales'!$C$2=12,'Sales Input'!N224,IF('Consolidated Sales'!$C$2=13,'Sales Input'!O224,0))))))))))))) -> 0 | H11: =SUM(C11-E11-G11-I11) -> 0 | I11: =IF('Consolidated Sales'!$C$2=1,'Sales Input'!C238,IF('Consolidated Sales'!$C$2=2,'Sales Input'!D238,IF('Consolidated Sales'!$C$2=3,'Sales Input'!E238,IF('Consolidated Sales'!$C$2=4,'Sales Input'!F238,IF('Consolidated Sales'!$C$2=5,'Sales Input'!G238,IF('Consolidated Sales'!$C$2=6,'Sales Input'!H238,IF('Consolidated Sales'!$C$2=7,'Sales Input'!I238,IF('Consolidated Sales'!$C$2=8,'Sales Input'!J238,IF('Consolidated Sales'!$C$2=9,'Sales Input'!K238,IF('Consolidated Sales'!$C$2=10,'Sales Input'!L238,IF('Consolidated Sales'!$C$2=11,'Sales Input'!M238,IF('Consolidated Sales'!$C$2=12,'Sales Input'!N238,IF('Consolidated Sales'!$C$2=13,'Sales Input'!O238,0))))))))))))) -> 200000 | J11: =SUM(C11-E11-G11-I11) -> 0
B12: 3. DSTV Subscription | C12: =IF('Consolidated Sales'!$C$2=1,'Sales Input'!C197,IF('Consolidated Sales'!$C$2=2,'Sales Input'!D197,IF('Consolidated Sales'!$C$2=3,'Sales Input'!E197,IF('Consolidated Sales'!$C$2=4,'Sales Input'!F197,IF('Consolidated Sales'!$C$2=5,'Sales Input'!G197,IF('Consolidated Sales'!$C$2=6,'Sales Input'!H197,IF('Consolidated Sales'!$C$2=7,'Sales Input'!I197,IF('Consolidated Sales'!$C$2=8,'Sales Input'!J197,IF('Consolidated Sales'!$C$2=9,'Sales Input'!K197,IF('Consolidated Sales'!$C$2=10,'Sales Input'!L197,IF('Consolidated Sales'!$C$2=11,'Sales Input'!M197,IF('Consolidated Sales'!$C$2=12,'Sales Input'!N197,IF('Consolidated Sales'!$C$2=13,'Sales Input'!O197,0))))))))))))) -> 59500 | D12: =SUM(C12-E12-G12-I12) -> 0 | E12: =IF('Consolidated Sales'!$C$2=1,'Sales Input'!C211,IF('Consolidated Sales'!$C$2=2,'Sales Input'!D211,IF('Consolidated Sales'!$C$2=3,'Sales Input'!E211,IF('Consolidated Sales'!$C$2=4,'Sales Input'!F211,IF('Consolidated Sales'!$C$2=5,'Sales Input'!G211,IF('Consolidated Sales'!$C$2=6,'Sales Input'!H211,IF('Consolidated Sales'!$C$2=7,'Sales Input'!I211,IF('Consolidated Sales'!$C$2=8,'Sales Input'!J211,IF('Consolidated Sales'!$C$2=9,'Sales Input'!K211,IF('Consolidated Sales'!$C$2=10,'Sales Input'!L211,IF('Consolidated Sales'!$C$2=11,'Sales Input'!M211,IF('Consolidated Sales'!$C$2=12,'Sales Input'!N211,IF('Consolidated Sales'!$C$2=13,'Sales Input'!O211,0))))))))))))) -> 0 | F12: =SUM(C12-G12-I12) -> 0 | G12: =IF('Consolidated Sales'!$C$2=1,'Sales Input'!C225,IF('Consolidated Sales'!$C$2=2,'Sales Input'!D225,IF('Consolidated Sales'!$C$2=3,'Sales Input'!E225,IF('Consolidated Sales'!$C$2=4,'Sales Input'!F225,IF('Consolidated Sales'!$C$2=5,'Sales Input'!G225,IF('Consolidated Sales'!$C$2=6,'Sales Input'!H225,IF('Consolidated Sales'!$C$2=7,'Sales Input'!I225,IF('Consolidated Sales'!$C$2=8,'Sales Input'!J225,IF('Consolidated Sales'!$C$2=9,'Sales Input'!K225,IF('Consolidated Sales'!$C$2=10,'Sales Input'!L225,IF('Consolidated Sales'!$C$2=11,'Sales Input'!M225,IF('Consolidated Sales'!$C$2=12,'Sales Input'!N225,IF('Consolidated Sales'!$C$2=13,'Sales Input'!O225,0))))))))))))) -> 59500 | H12: =SUM(C12-E12-G12-I12) -> 0 | I12: =IF('Consolidated Sales'!$C$2=1,'Sales Input'!C239,IF('Consolidated Sales'!$C$2=2,'Sales Input'!D239,IF('Consolidated Sales'!$C$2=3,'Sales Input'!E239,IF('Consolidated Sales'!$C$2=4,'Sales Input'!F239,IF('Consolidated Sales'!$C$2=5,'Sales Input'!G239,IF('Consolidated Sales'!$C$2=6,'Sales Input'!H239,IF('Consolidated Sales'!$C$2=7,'Sales Input'!I239,IF('Consolidated Sales'!$C$2=8,'Sales Input'!J239,IF('Consolidated Sales'!$C$2=9,'Sales Input'!K239,IF('Consolidated Sales'!$C$2=10,'Sales Input'!L239,IF('Consolidated Sales'!$C$2=11,'Sales Input'!M239,IF('Consolidated Sales'!$C$2=12,'Sales Input'!N239,IF('Consolidated Sales'!$C$2=13,'Sales Input'!O239,0))))))))))))) -> 0 | J12: =SUM(C12-E12-G12-I12) -> 0
B13: Expired and Damage Products | C13: =IF('Consolidated Sales'!$C$2=1,'Sales Input'!C198,IF('Consolidated Sales'!$C$2=2,'Sales Input'!D198,IF('Consolidated Sales'!$C$2=3,'Sales Input'!E198,IF('Consolidated Sales'!$C$2=4,'Sales Input'!F198,IF('Consolidated Sales'!$C$2=5,'Sales Input'!G198,IF('Consolidated Sales'!$C$2=6,'Sales Input'!H198,IF('Consolidated Sales'!$C$2=7,'Sales Input'!I198,IF('Consolidated Sales'!$C$2=8,'Sales Input'!J198,IF('Consolidated Sales'!$C$2=9,'Sales Input'!K198,IF('Consolidated Sales'!$C$2=10,'Sales Input'!L198,IF('Consolidated Sales'!$C$2=11,'Sales Input'!M198,IF('Consolidated Sales'!$C$2=12,'Sales Input'!N198,IF('Consolidated Sales'!$C$2=13,'Sales Input'!O198,0))))))))))))) -> 0 | D13: =SUM(C13-E13-G13-I13) -> 0 | E13: =IF('Consolidated Sales'!$C$2=1,'Sales Input'!C212,IF('Consolidated Sales'!$C$2=2,'Sales Input'!D212,IF('Consolidated Sales'!$C$2=3,'Sales Input'!E212,IF('Consolidated Sales'!$C$2=4,'Sales Input'!F212,IF('Consolidated Sales'!$C$2=5,'Sales Input'!G212,IF('Consolidated Sales'!$C$2=6,'Sales Input'!H212,IF('Consolidated Sales'!$C$2=7,'Sales Input'!I212,IF('Consolidated Sales'!$C$2=8,'Sales Input'!J212,IF('Consolidated Sales'!$C$2=9,'Sales Input'!K212,IF('Consolidated Sales'!$C$2=10,'Sales Input'!L212,IF('Consolidated Sales'!$C$2=11,'Sales Input'!M212,IF('Consolidated Sales'!$C$2=12,'Sales Input'!N212,IF('Consolidated Sales'!$C$2=13,'Sales Input'!O212,0))))))))))))) -> 0 | F13: =SUM(C13-G13-I13) -> 0 | G13: =IF('Consolidated Sales'!$C$2=1,'Sales Input'!C226,IF('Consolidated Sales'!$C$2=2,'Sales Input'!D226,IF('Consolidated Sales'!$C$2=3,'Sales Input'!E226,IF('Consolidated Sales'!$C$2=4,'Sales Input'!F226,IF('Consolidated Sales'!$C$2=5,'Sales Input'!G226,IF('Consolidated Sales'!$C$2=6,'Sales Input'!H226,IF('Consolidated Sales'!$C$2=7,'Sales Input'!I226,IF('Consolidated Sales'!$C$2=8,'Sales Input'!J226,IF('Consolidated Sales'!$C$2=9,'Sales Input'!K226,IF('Consolidated Sales'!$C$2=10,'Sales Input'!L226,IF('Consolidated Sales'!$C$2=11,'Sales Input'!M226,IF('Consolidated Sales'!$C$2=12,'Sales Input'!N226,IF('Consolidated Sales'!$C$2=13,'Sales Input'!O226,0))))))))))))) -> 0 | H13: =SUM(C13-E13-G13-I13) -> 0 | I13: =IF('Consolidated Sales'!$C$2=1,'Sales Input'!C240,IF('Consolidated Sales'!$C$2=2,'Sales Input'!D240,IF('Consolidated Sales'!$C$2=3,'Sales Input'!E240,IF('Consolidated Sales'!$C$2=4,'Sales Input'!F240,IF('Consolidated Sales'!$C$2=5,'Sales Input'!G240,IF('Consolidated Sales'!$C$2=6,'Sales Input'!H240,IF('Consolidated Sales'!$C$2=7,'Sales Input'!I240,IF('Consolidated Sales'!$C$2=8,'Sales Input'!J240,IF('Consolidated Sales'!$C$2=9,'Sales Input'!K240,IF('Consolidated Sales'!$C$2=10,'Sales Input'!L240,IF('Consolidated Sales'!$C$2=11,'Sales Input'!M240,IF('Consolidated Sales'!$C$2=12,'Sales Input'!N240,IF('Consolidated Sales'!$C$2=13,'Sales Input'!O240,0))))))))))))) -> 0 | J13: =SUM(C13-E13-G13-I13) -> 0
B14: MBS Penalties | C14: =IF('Consolidated Sales'!$C$2=1,'Sales Input'!C199,IF('Consolidated Sales'!$C$2=2,'Sales Input'!D199,IF('Consolidated Sales'!$C$2=3,'Sales Input'!E199,IF('Consolidated Sales'!$C$2=4,'Sales Input'!F199,IF('Consolidated Sales'!$C$2=5,'Sales Input'!G199,IF('Consolidated Sales'!$C$2=6,'Sales Input'!H199,IF('Consolidated Sales'!$C$2=7,'Sales Input'!I199,IF('Consolidated Sales'!$C$2=8,'Sales Input'!J199,IF('Consolidated Sales'!$C$2=9,'Sales Input'!K199,IF('Consolidated Sales'!$C$2=10,'Sales Input'!L199,IF('Consolidated Sales'!$C$2=11,'Sales Input'!M199,IF('Consolidated Sales'!$C$2=12,'Sales Input'!N199,IF('Consolidated Sales'!$C$2=13,'Sales Input'!O199,0))))))))))))) -> 0 | D14: =SUM(C14-E14-G14-I14) -> 0 | E14: =IF('Consolidated Sales'!$C$2=1,'Sales Input'!C213,IF('Consolidated Sales'!$C$2=2,'Sales Input'!D213,IF('Consolidated Sales'!$C$2=3,'Sales Input'!E213,IF('Consolidated Sales'!$C$2=4,'Sales Input'!F213,IF('Consolidated Sales'!$C$2=5,'Sales Input'!G213,IF('Consolidated Sales'!$C$2=6,'Sales Input'!H213,IF('Consolidated Sales'!$C$2=7,'Sales Input'!I213,IF('Consolidated Sales'!$C$2=8,'Sales Input'!J213,IF('Consolidated Sales'!$C$2=9,'Sales Input'!K213,IF('Consolidated Sales'!$C$2=10,'Sales Input'!L213,IF('Consolidated Sales'!$C$2=11,'Sales Input'!M213,IF('Consolidated Sales'!$C$2=12,'Sales Input'!N213,IF('Consolidated Sales'!$C$2=13,'Sales Input'!O213,0))))))))))))) -> 0 | F14: =SUM(C14-G14-I14) -> 0 | G14: =IF('Consolidated Sales'!$C$2=1,'Sales Input'!C227,IF('Consolidated Sales'!$C$2=2,'Sales Input'!D227,IF('Consolidated Sales'!$C$2=3,'Sales Input'!E227,IF('Consolidated Sales'!$C$2=4,'Sales Input'!F227,IF('Consolidated Sales'!$C$2=5,'Sales Input'!G227,IF('Consolidated Sales'!$C$2=6,'Sales Input'!H227,IF('Consolidated Sales'!$C$2=7,'Sales Input'!I227,IF('Consolidated Sales'!$C$2=8,'Sales Input'!J227,IF('Consolidated Sales'!$C$2=9,'Sales Input'!K227,IF('Consolidated Sales'!$C$2=10,'Sales Input'!L227,IF('Consolidated Sales'!$C$2=11,'Sales Input'!M227,IF('Consolidated Sales'!$C$2=12,'Sales Input'!N227,IF('Consolidated Sales'!$C$2=13,'Sales Input'!O227,0))))))))))))) -> 0 | H14: =SUM(C14-E14-G14-I14) -> 0 | I14: =IF('Consolidated Sales'!$C$2=1,'Sales Input'!C241,IF('Consolidated Sales'!$C$2=2,'Sales Input'!D241,IF('Consolidated Sales'!$C$2=3,'Sales Input'!E241,IF('Consolidated Sales'!$C$2=4,'Sales Input'!F241,IF('Consolidated Sales'!$C$2=5,'Sales Input'!G241,IF('Consolidated Sales'!$C$2=6,'Sales Input'!H241,IF('Consolidated Sales'!$C$2=7,'Sales Input'!I241,IF('Consolidated Sales'!$C$2=8,'Sales Input'!J241,IF('Consolidated Sales'!$C$2=9,'Sales Input'!K241,IF('Consolidated Sales'!$C$2=10,'Sales Input'!L241,IF('Consolidated Sales'!$C$2=11,'Sales Input'!M241,IF('Consolidated Sales'!$C$2=12,'Sales Input'!N241,IF('Consolidated Sales'!$C$2=13,'Sales Input'!O241,0))))))))))))) -> 0 | J14: =SUM(C14-E14-G14-I14) -> 0
B15: POS Licence and Attendant Costs | C15: =IF('Consolidated Sales'!$C$2=1,'Sales Input'!C200,IF('Consolidated Sales'!$C$2=2,'Sales Input'!D200,IF('Consolidated Sales'!$C$2=3,'Sales Input'!E200,IF('Consolidated Sales'!$C$2=4,'Sales Input'!F200,IF('Consolidated Sales'!$C$2=5,'Sales Input'!G200,IF('Consolidated Sales'!$C$2=6,'Sales Input'!H200,IF('Consolidated Sales'!$C$2=7,'Sales Input'!I200,IF('Consolidated Sales'!$C$2=8,'Sales Input'!J200,IF('Consolidated Sales'!$C$2=9,'Sales Input'!K200,IF('Consolidated Sales'!$C$2=10,'Sales Input'!L200,IF('Consolidated Sales'!$C$2=11,'Sales Input'!M200,IF('Consolidated Sales'!$C$2=12,'Sales Input'!N200,IF('Consolidated Sales'!$C$2=13,'Sales Input'!O200,0))))))))))))) -> 0 | D15: =SUM(C15-E15-G15-I15) -> 0 | E15: =IF('Consolidated Sales'!$C$2=1,'Sales Input'!C214,IF('Consolidated Sales'!$C$2=2,'Sales Input'!D214,IF('Consolidated Sales'!$C$2=3,'Sales Input'!E214,IF('Consolidated Sales'!$C$2=4,'Sales Input'!F214,IF('Consolidated Sales'!$C$2=5,'Sales Input'!G214,IF('Consolidated Sales'!$C$2=6,'Sales Input'!H214,IF('Consolidated Sales'!$C$2=7,'Sales Input'!I214,IF('Consolidated Sales'!$C$2=8,'Sales Input'!J214,IF('Consolidated Sales'!$C$2=9,'Sales Input'!K214,IF('Consolidated Sales'!$C$2=10,'Sales Input'!L214,IF('Consolidated Sales'!$C$2=11,'Sales Input'!M214,IF('Consolidated Sales'!$C$2=12,'Sales Input'!N214,IF('Consolidated Sales'!$C$2=13,'Sales Input'!O214,0))))))))))))) -> 0 | F15: =SUM(C15-G15-I15) -> 0 | G15: =IF('Consolidated Sales'!$C$2=1,'Sales Input'!C228,IF('Consolidated Sales'!$C$2=2,'Sales Input'!D228,IF('Consolidated Sales'!$C$2=3,'Sales Input'!E228,IF('Consolidated Sales'!$C$2=4,'Sales Input'!F228,IF('Consolidated Sales'!$C$2=5,'Sales Input'!G228,IF('Consolidated Sales'!$C$2=6,'Sales Input'!H228,IF('Consolidated Sales'!$C$2=7,'Sales Input'!I228,IF('Consolidated Sales'!$C$2=8,'Sales Input'!J228,IF('Consolidated Sales'!$C$2=9,'Sales Input'!K228,IF('Consolidated Sales'!$C$2=10,'Sales Input'!L228,IF('Consolidated Sales'!$C$2=11,'Sales Input'!M228,IF('Consolidated Sales'!$C$2=12,'Sales Input'!N228,IF('Consolidated Sales'!$C$2=13,'Sales Input'!O228,0))))))))))))) -> 0 | H15: =SUM(C15-E15-G15-I15) -> 0 | I15: =IF('Consolidated Sales'!$C$2=1,'Sales Input'!C242,IF('Consolidated Sales'!$C$2=2,'Sales Input'!D242,IF('Consolidated Sales'!$C$2=3,'Sales Input'!E242,IF('Consolidated Sales'!$C$2=4,'Sales Input'!F242,IF('Consolidated Sales'!$C$2=5,'Sales Input'!G242,IF('Consolidated Sales'!$C$2=6,'Sales Input'!H242,IF('Consolidated Sales'!$C$2=7,'Sales Input'!I242,IF('Consolidated Sales'!$C$2=8,'Sales Input'!J242,IF('Consolidated Sales'!$C$2=9,'Sales Input'!K242,IF('Consolidated Sales'!$C$2=10,'Sales Input'!L242,IF('Consolidated Sales'!$C$2=11,'Sales Input'!M242,IF('Consolidated Sales'!$C$2=12,'Sales Input'!N242,IF('Consolidated Sales'!$C$2=13,'Sales Input'!O242,0))))))))))))) -> 0 | J15: =SUM(C15-E15-G15-I15) -> 0
B16: Maintenance Works | C16: =IF('Consolidated Sales'!$C$2=1,'Sales Input'!C201,IF('Consolidated Sales'!$C$2=2,'Sales Input'!D201,IF('Consolidated Sales'!$C$2=3,'Sales Input'!E201,IF('Consolidated Sales'!$C$2=4,'Sales Input'!F201,IF('Consolidated Sales'!$C$2=5,'Sales Input'!G201,IF('Consolidated Sales'!$C$2=6,'Sales Input'!H201,IF('Consolidated Sales'!$C$2=7,'Sales Input'!I201,IF('Consolidated Sales'!$C$2=8,'Sales Input'!J201,IF('Consolidated Sales'!$C$2=9,'Sales Input'!K201,IF('Consolidated Sales'!$C$2=10,'Sales Input'!L201,IF('Consolidated Sales'!$C$2=11,'Sales Input'!M201,IF('Consolidated Sales'!$C$2=12,'Sales Input'!N201,IF('Consolidated Sales'!$C$2=13,'Sales Input'!O201,0))))))))))))) -> 0 | D16: =SUM(C16-E16-G16-I16) -> 0 | E16: =IF('Consolidated Sales'!$C$2=1,'Sales Input'!C215,IF('Consolidated Sales'!$C$2=2,'Sales Input'!D215,IF('Consolidated Sales'!$C$2=3,'Sales Input'!E215,IF('Consolidated Sales'!$C$2=4,'Sales Input'!F215,IF('Consolidated Sales'!$C$2=5,'Sales Input'!G215,IF('Consolidated Sales'!$C$2=6,'Sales Input'!H215,IF('Consolidated Sales'!$C$2=7,'Sales Input'!I215,IF('Consolidated Sales'!$C$2=8,'Sales Input'!J215,IF('Consolidated Sales'!$C$2=9,'Sales Input'!K215,IF('Consolidated Sales'!$C$2=10,'Sales Input'!L215,IF('Consolidated Sales'!$C$2=11,'Sales Input'!M215,IF('Consolidated Sales'!$C$2=12,'Sales Input'!N215,IF('Consolidated Sales'!$C$2=13,'Sales Input'!O215,0))))))))))))) -> 0 | F16: =SUM(C16-G16-I16) -> 0 | G16: =IF('Consolidated Sales'!$C$2=1,'Sales Input'!C229,IF('Consolidated Sales'!$C$2=2,'Sales Input'!D229,IF('Consolidated Sales'!$C$2=3,'Sales Input'!E229,IF('Consolidated Sales'!$C$2=4,'Sales Input'!F229,IF('Consolidated Sales'!$C$2=5,'Sales Input'!G229,IF('Consolidated Sales'!$C$2=6,'Sales Input'!H229,IF('Consolidated Sales'!$C$2=7,'Sales Input'!I229,IF('Consolidated Sales'!$C$2=8,'Sales Input'!J229,IF('Consolidated Sales'!$C$2=9,'Sales Input'!K229,IF('Consolidated Sales'!$C$2=10,'Sales Input'!L229,IF('Consolidated Sales'!$C$2=11,'Sales Input'!M229,IF('Consolidated Sales'!$C$2=12,'Sales Input'!N229,IF('Consolidated Sales'!$C$2=13,'Sales Input'!O229,0))))))))))))) -> 0 | H16: =SUM(C16-E16-G16-I16) -> 0 | I16: =IF('Consolidated Sales'!$C$2=1,'Sales Input'!C243,IF('Consolidated Sales'!$C$2=2,'Sales Input'!D243,IF('Consolidated Sales'!$C$2=3,'Sales Input'!E243,IF('Consolidated Sales'!$C$2=4,'Sales Input'!F243,IF('Consolidated Sales'!$C$2=5,'Sales Input'!G243,IF('Consolidated Sales'!$C$2=6,'Sales Input'!H243,IF('Consolidated Sales'!$C$2=7,'Sales Input'!I243,IF('Consolidated Sales'!$C$2=8,'Sales Input'!J243,IF('Consolidated Sales'!$C$2=9,'Sales Input'!K243,IF('Consolidated Sales'!$C$2=10,'Sales Input'!L243,IF('Consolidated Sales'!$C$2=11,'Sales Input'!M243,IF('Consolidated Sales'!$C$2=12,'Sales Input'!N243,IF('Consolidated Sales'!$C$2=13,'Sales Input'!O243,0))))))))))))) -> 0 | J16: =SUM(C16-E16-G16-I16) -> 0
B17: Shop Cleaning Materials | C17: =IF('Consolidated Sales'!$C$2=1,'Sales Input'!C202,IF('Consolidated Sales'!$C$2=2,'Sales Input'!D202,IF('Consolidated Sales'!$C$2=3,'Sales Input'!E202,IF('Consolidated Sales'!$C$2=4,'Sales Input'!F202,IF('Consolidated Sales'!$C$2=5,'Sales Input'!G202,IF('Consolidated Sales'!$C$2=6,'Sales Input'!H202,IF('Consolidated Sales'!$C$2=7,'Sales Input'!I202,IF('Consolidated Sales'!$C$2=8,'Sales Input'!J202,IF('Consolidated Sales'!$C$2=9,'Sales Input'!K202,IF('Consolidated Sales'!$C$2=10,'Sales Input'!L202,IF('Consolidated Sales'!$C$2=11,'Sales Input'!M202,IF('Consolidated Sales'!$C$2=12,'Sales Input'!N202,IF('Consolidated Sales'!$C$2=13,'Sales Input'!O202,0))))))))))))) -> 0 | D17: =SUM(C17-E17-G17-I17) -> 0 | E17: =IF('Consolidated Sales'!$C$2=1,'Sales Input'!C216,IF('Consolidated Sales'!$C$2=2,'Sales Input'!D216,IF('Consolidated Sales'!$C$2=3,'Sales Input'!E216,IF('Consolidated Sales'!$C$2=4,'Sales Input'!F216,IF('Consolidated Sales'!$C$2=5,'Sales Input'!G216,IF('Consolidated Sales'!$C$2=6,'Sales Input'!H216,IF('Consolidated Sales'!$C$2=7,'Sales Input'!I216,IF('Consolidated Sales'!$C$2=8,'Sales Input'!J216,IF('Consolidated Sales'!$C$2=9,'Sales Input'!K216,IF('Consolidated Sales'!$C$2=10,'Sales Input'!L216,IF('Consolidated Sales'!$C$2=11,'Sales Input'!M216,IF('Consolidated Sales'!$C$2=12,'Sales Input'!N216,IF('Consolidated Sales'!$C$2=13,'Sales Input'!O216,0))))))))))))) -> 0 | F17: =SUM(C17-G17-I17) -> 0 | G17: =IF('Consolidated Sales'!$C$2=1,'Sales Input'!C230,IF('Consolidated Sales'!$C$2=2,'Sales Input'!D230,IF('Consolidated Sales'!$C$2=3,'Sales Input'!E230,IF('Consolidated Sales'!$C$2=4,'Sales Input'!F230,IF('Consolidated Sales'!$C$2=5,'Sales Input'!G230,IF('Consolidated Sales'!$C$2=6,'Sales Input'!H230,IF('Consolidated Sales'!$C$2=7,'Sales Input'!I230,IF('Consolidated Sales'!$C$2=8,'Sales Input'!J230,IF('Consolidated Sales'!$C$2=9,'Sales Input'!K230,IF('Consolidated Sales'!$C$2=10,'Sales Input'!L230,IF('Consolidated Sales'!$C$2=11,'Sales Input'!M230,IF('Consolidated Sales'!$C$2=12,'Sales Input'!N230,IF('Consolidated Sales'!$C$2=13,'Sales Input'!O230,0))))))))))))) -> 0 | H17: =SUM(C17-E17-G17-I17) -> 0 | I17: =IF('Consolidated Sales'!$C$2=1,'Sales Input'!C244,IF('Consolidated Sales'!$C$2=2,'Sales Input'!D244,IF('Consolidated Sales'!$C$2=3,'Sales Input'!E244,IF('Consolidated Sales'!$C$2=4,'Sales Input'!F244,IF('Consolidated Sales'!$C$2=5,'Sales Input'!G244,IF('Consolidated Sales'!$C$2=6,'Sales Input'!H244,IF('Consolidated Sales'!$C$2=7,'Sales Input'!I244,IF('Consolidated Sales'!$C$2=8,'Sales Input'!J244,IF('Consolidated Sales'!$C$2=9,'Sales Input'!K244,IF('Consolidated Sales'!$C$2=10,'Sales Input'!L244,IF('Consolidated Sales'!$C$2=11,'Sales Input'!M244,IF('Consolidated Sales'!$C$2=12,'Sales Input'!N244,IF('Consolidated Sales'!$C$2=13,'Sales Input'!O244,0))))))))))))) -> 0 | J17: =SUM(C17-E17-G17-I17) -> 0
B18: Casual Labourers | C18: =IF('Consolidated Sales'!$C$2=1,'Sales Input'!C203,IF('Consolidated Sales'!$C$2=2,'Sales Input'!D203,IF('Consolidated Sales'!$C$2=3,'Sales Input'!E203,IF('Consolidated Sales'!$C$2=4,'Sales Input'!F203,IF('Consolidated Sales'!$C$2=5,'Sales Input'!G203,IF('Consolidated Sales'!$C$2=6,'Sales Input'!H203,IF('Consolidated Sales'!$C$2=7,'Sales Input'!I203,IF('Consolidated Sales'!$C$2=8,'Sales Input'!J203,IF('Consolidated Sales'!$C$2=9,'Sales Input'!K203,IF('Consolidated Sales'!$C$2=10,'Sales Input'!L203,IF('Consolidated Sales'!$C$2=11,'Sales Input'!M203,IF('Consolidated Sales'!$C$2=12,'Sales Input'!N203,IF('Consolidated Sales'!$C$2=13,'Sales Input'!O203,0))))))))))))) -> 0 | D18: =SUM(C18-E18-G18-I18) -> 0 | E18: =IF('Consolidated Sales'!$C$2=1,'Sales Input'!C217,IF('Consolidated Sales'!$C$2=2,'Sales Input'!D217,IF('Consolidated Sales'!$C$2=3,'Sales Input'!E217,IF('Consolidated Sales'!$C$2=4,'Sales Input'!F217,IF('Consolidated Sales'!$C$2=5,'Sales Input'!G217,IF('Consolidated Sales'!$C$2=6,'Sales Input'!H217,IF('Consolidated Sales'!$C$2=7,'Sales Input'!I217,IF('Consolidated Sales'!$C$2=8,'Sales Input'!J217,IF('Consolidated Sales'!$C$2=9,'Sales Input'!K217,IF('Consolidated Sales'!$C$2=10,'Sales Input'!L217,IF('Consolidated Sales'!$C$2=11,'Sales Input'!M217,IF('Consolidated Sales'!$C$2=12,'Sales Input'!N217,IF('Consolidated Sales'!$C$2=13,'Sales Input'!O217,0))))))))))))) -> 0 | F18: =SUM(C18-G18-I18) -> 0 | G18: =IF('Consolidated Sales'!$C$2=1,'Sales Input'!C231,IF('Consolidated Sales'!$C$2=2,'Sales Input'!D231,IF('Consolidated Sales'!$C$2=3,'Sales Input'!E231,IF('Consolidated Sales'!$C$2=4,'Sales Input'!F231,IF('Consolidated Sales'!$C$2=5,'Sales Input'!G231,IF('Consolidated Sales'!$C$2=6,'Sales Input'!H231,IF('Consolidated Sales'!$C$2=7,'Sales Input'!I231,IF('Consolidated Sales'!$C$2=8,'Sales Input'!J231,IF('Consolidated Sales'!$C$2=9,'Sales Input'!K231,IF('Consolidated Sales'!$C$2=10,'Sales Input'!L231,IF('Consolidated Sales'!$C$2=11,'Sales Input'!M231,IF('Consolidated Sales'!$C$2=12,'Sales Input'!N231,IF('Consolidated Sales'!$C$2=13,'Sales Input'!O231,0))))))))))))) -> 0 | H18: =SUM(C18-E18-G18-I18) -> 0 | I18: =IF('Consolidated Sales'!$C$2=1,'Sales Input'!C245,IF('Consolidated Sales'!$C$2=2,'Sales Input'!D245,IF('Consolidated Sales'!$C$2=3,'Sales Input'!E245,IF('Consolidated Sales'!$C$2=4,'Sales Input'!F245,IF('Consolidated Sales'!$C$2=5,'Sales Input'!G245,IF('Consolidated Sales'!$C$2=6,'Sales Input'!H245,IF('Consolidated Sales'!$C$2=7,'Sales Input'!I245,IF('Consolidated Sales'!$C$2=8,'Sales Input'!J245,IF('Consolidated Sales'!$C$2=9,'Sales Input'!K245,IF('Consolidated Sales'!$C$2=10,'Sales Input'!L245,IF('Consolidated Sales'!$C$2=11,'Sales Input'!M245,IF('Consolidated Sales'!$C$2=12,'Sales Input'!N245,IF('Consolidated Sales'!$C$2=13,'Sales Input'!O245,0))))))))))))) -> 0 | J18: =SUM(C18-E18-G18-I18) -> 0
B19: Braai Condiments | C19: =IF('Consolidated Sales'!$C$2=1,'Sales Input'!C204,IF('Consolidated Sales'!$C$2=2,'Sales Input'!D204,IF('Consolidated Sales'!$C$2=3,'Sales Input'!E204,IF('Consolidated Sales'!$C$2=4,'Sales Input'!F204,IF('Consolidated Sales'!$C$2=5,'Sales Input'!G204,IF('Consolidated Sales'!$C$2=6,'Sales Input'!H204,IF('Consolidated Sales'!$C$2=7,'Sales Input'!I204,IF('Consolidated Sales'!$C$2=8,'Sales Input'!J204,IF('Consolidated Sales'!$C$2=9,'Sales Input'!K204,IF('Consolidated Sales'!$C$2=10,'Sales Input'!L204,IF('Consolidated Sales'!$C$2=11,'Sales Input'!M204,IF('Consolidated Sales'!$C$2=12,'Sales Input'!N204,IF('Consolidated Sales'!$C$2=13,'Sales Input'!O204,0))))))))))))) -> 0 | D19: =SUM(C19-E19-G19-I19) -> 0 | E19: =IF('Consolidated Sales'!$C$2=1,'Sales Input'!C218,IF('Consolidated Sales'!$C$2=2,'Sales Input'!D218,IF('Consolidated Sales'!$C$2=3,'Sales Input'!E218,IF('Consolidated Sales'!$C$2=4,'Sales Input'!F218,IF('Consolidated Sales'!$C$2=5,'Sales Input'!G218,IF('Consolidated Sales'!$C$2=6,'Sales Input'!H218,IF('Consolidated Sales'!$C$2=7,'Sales Input'!I218,IF('Consolidated Sales'!$C$2=8,'Sales Input'!J218,IF('Consolidated Sales'!$C$2=9,'Sales Input'!K218,IF('Consolidated Sales'!$C$2=10,'Sales Input'!L218,IF('Consolidated Sales'!$C$2=11,'Sales Input'!M218,IF('Consolidated Sales'!$C$2=12,'Sales Input'!N218,IF('Consolidated Sales'!$C$2=13,'Sales Input'!O218,0))))))))))))) -> 0 | F19: =SUM(C19-G19-I19) -> 0 | G19: =IF('Consolidated Sales'!$C$2=1,'Sales Input'!C232,IF('Consolidated Sales'!$C$2=2,'Sales Input'!D232,IF('Consolidated Sales'!$C$2=3,'Sales Input'!E232,IF('Consolidated Sales'!$C$2=4,'Sales Input'!F232,IF('Consolidated Sales'!$C$2=5,'Sales Input'!G232,IF('Consolidated Sales'!$C$2=6,'Sales Input'!H232,IF('Consolidated Sales'!$C$2=7,'Sales Input'!I232,IF('Consolidated Sales'!$C$2=8,'Sales Input'!J232,IF('Consolidated Sales'!$C$2=9,'Sales Input'!K232,IF('Consolidated Sales'!$C$2=10,'Sales Input'!L232,IF('Consolidated Sales'!$C$2=11,'Sales Input'!M232,IF('Consolidated Sales'!$C$2=12,'Sales Input'!N232,IF('Consolidated Sales'!$C$2=13,'Sales Input'!O232,0))))))))))))) -> 0 | H19: =SUM(C19-E19-G19-I19) -> 0 | I19: =IF('Consolidated Sales'!$C$2=1,'Sales Input'!C246,IF('Consolidated Sales'!$C$2=2,'Sales Input'!D246,IF('Consolidated Sales'!$C$2=3,'Sales Input'!E246,IF('Consolidated Sales'!$C$2=4,'Sales Input'!F246,IF('Consolidated Sales'!$C$2=5,'Sales Input'!G246,IF('Consolidated Sales'!$C$2=6,'Sales Input'!H246,IF('Consolidated Sales'!$C$2=7,'Sales Input'!I246,IF('Consolidated Sales'!$C$2=8,'Sales Input'!J246,IF('Consolidated Sales'!$C$2=9,'Sales Input'!K246,IF('Consolidated Sales'!$C$2=10,'Sales Input'!L246,IF('Consolidated Sales'!$C$2=11,'Sales Input'!M246,IF('Consolidated Sales'!$C$2=12,'Sales Input'!N246,IF('Consolidated Sales'!$C$2=13,'Sales Input'!O246,0))))))))))))) -> 0 | J19: =SUM(C19-E19-G19-I19) -> 0
B20: Other Expenses | C20: =IF('Consolidated Sales'!$C$2=1,'Sales Input'!C205,IF('Consolidated Sales'!$C$2=2,'Sales Input'!D205,IF('Consolidated Sales'!$C$2=3,'Sales Input'!E205,IF('Consolidated Sales'!$C$2=4,'Sales Input'!F205,IF('Consolidated Sales'!$C$2=5,'Sales Input'!G205,IF('Consolidated Sales'!$C$2=6,'Sales Input'!H205,IF('Consolidated Sales'!$C$2=7,'Sales Input'!I205,IF('Consolidated Sales'!$C$2=8,'Sales Input'!J205,IF('Consolidated Sales'!$C$2=9,'Sales Input'!K205,IF('Consolidated Sales'!$C$2=10,'Sales Input'!L205,IF('Consolidated Sales'!$C$2=11,'Sales Input'!M205,IF('Consolidated Sales'!$C$2=12,'Sales Input'!N205,IF('Consolidated Sales'!$C$2=13,'Sales Input'!O205,0))))))))))))) -> 0 | D20: =SUM(C20-E20-G20-I20) -> 0 | E20: =IF('Consolidated Sales'!$C$2=1,'Sales Input'!C219,IF('Consolidated Sales'!$C$2=2,'Sales Input'!D219,IF('Consolidated Sales'!$C$2=3,'Sales Input'!E219,IF('Consolidated Sales'!$C$2=4,'Sales Input'!F219,IF('Consolidated Sales'!$C$2=5,'Sales Input'!G219,IF('Consolidated Sales'!$C$2=6,'Sales Input'!H219,IF('Consolidated Sales'!$C$2=7,'Sales Input'!I219,IF('Consolidated Sales'!$C$2=8,'Sales Input'!J219,IF('Consolidated Sales'!$C$2=9,'Sales Input'!K219,IF('Consolidated Sales'!$C$2=10,'Sales Input'!L219,IF('Consolidated Sales'!$C$2=11,'Sales Input'!M219,IF('Consolidated Sales'!$C$2=12,'Sales Input'!N219,IF('Consolidated Sales'!$C$2=13,'Sales Input'!O219,0))))))))))))) -> 0 | F20: =SUM(C20-G20-I20) -> 0 | G20: =IF('Consolidated Sales'!$C$2=1,'Sales Input'!C233,IF('Consolidated Sales'!$C$2=2,'Sales Input'!D233,IF('Consolidated Sales'!$C$2=3,'Sales Input'!E233,IF('Consolidated Sales'!$C$2=4,'Sales Input'!F233,IF('Consolidated Sales'!$C$2=5,'Sales Input'!G233,IF('Consolidated Sales'!$C$2=6,'Sales Input'!H233,IF('Consolidated Sales'!$C$2=7,'Sales Input'!I233,IF('Consolidated Sales'!$C$2=8,'Sales Input'!J233,IF('Consolidated Sales'!$C$2=9,'Sales Input'!K233,IF('Consolidated Sales'!$C$2=10,'Sales Input'!L233,IF('Consolidated Sales'!$C$2=11,'Sales Input'!M233,IF('Consolidated Sales'!$C$2=12,'Sales Input'!N233,IF('Consolidated Sales'!$C$2=13,'Sales Input'!O233,0))))))))))))) -> 0 | H20: =SUM(C20-E20-G20-I20) -> 0 | I20: =IF('Consolidated Sales'!$C$2=1,'Sales Input'!C247,IF('Consolidated Sales'!$C$2=2,'Sales Input'!D247,IF('Consolidated Sales'!$C$2=3,'Sales Input'!E247,IF('Consolidated Sales'!$C$2=4,'Sales Input'!F247,IF('Consolidated Sales'!$C$2=5,'Sales Input'!G247,IF('Consolidated Sales'!$C$2=6,'Sales Input'!H247,IF('Consolidated Sales'!$C$2=7,'Sales Input'!I247,IF('Consolidated Sales'!$C$2=8,'Sales Input'!J247,IF('Consolidated Sales'!$C$2=9,'Sales Input'!K247,IF('Consolidated Sales'!$C$2=10,'Sales Input'!L247,IF('Consolidated Sales'!$C$2=11,'Sales Input'!M247,IF('Consolidated Sales'!$C$2=12,'Sales Input'!N247,IF('Consolidated Sales'!$C$2=13,'Sales Input'!O247,0))))))))))))) -> 0 | J20: =SUM(C20-E20-G20-I20) -> 0
A22: 1 | B22: Total Expenses Incurred | C22: =SUM(C13:C20)+C9+C8 -> 1589500 | D22: =SUM(D8+D9+D15+D17+D18+D19+D20) -> 0 | E22: =E8+E9+SUM(E13:E20) -> 0 | F22: =SUM(F8+F9+F15+F17+F18+F20+D37) -> 0 | G22: =G8+G9+SUM(G13:G20) -> 59500 | H22: =SUM(H8+H9+H15+H17+H18+H20+D56) -> 0 | I22: =SUM(I8+I9+I13+I14+I15+I16+I17+I18+I19+I20) -> 1530000 | J22: =SUM(J8+J9+J13+J14+J15+J16+J17+J18+J19) -> 0
B24: Net Balances | E24: ='Suppliers Report'!E29-E22 -> 580000 | G24: =+'Suppliers Report'!G29-G22 -> 1168374.5 | I24: =+'Suppliers Report'!I29-I22 -> 975000

Sheet Summary
A1: =+'Consolidated Sales'!A1 -> Sales Report for Supermarket, Stop-Over and Restaurant
A3: Enter Month to Report on Here -----------> | C3: 8
A5: =+'Consolidated Sales'!B4 -> Sales as at | C5: =+'Consolidated Sales'!C4 -> August 2025
A7: Summary of Sales and Expenses
B8: =+'Consolidated Sales'!B94 -> Total POS Sales | H8: =+H37 -> 0
B9: =+'Consolidated Sales'!B95 -> Total Cash and Sales Thru Gadgets | H9: =+H35 -> 12217960
B10: =+'Consolidated Sales'!B96 -> Cash Overage/Shortfall | H10: =+H39 -> 12217960
B11: =+'Suppliers Report'!B27 -> Totals Due | H11: =+'Suppliers Report'!C27 -> 7905085.5
B12: Total Amount Paid to Suppliers | H12: =SUM('Suppliers Report'!E27+'Suppliers Report'!G27+'Suppliers Report'!I27) -> 7905085.5
B13: Total Amount Outstanding to Suppliers | H13: =+H11-H12 -> 0
B14: =+'Expenses Report'!B22 -> Total Expenses Incurred | H14: =+'Expenses Report'!C22 -> 1589500
B15: Total Expenses Paid | H15: =+'Expenses Report'!E22+'Expenses Report'!G22+'Expenses Report'!I22 -> 1589500
B16: Total Outstaning Expenses to be Paid | H16: =+H14-H15 -> 0
B17: =+'Consolidated Sales'!B97 -> Net Balances after Payments
B18: =+'Consolidated Sales'!B98 -> a. Net Cash in- Hand | H18: =+'Consolidated Sales'!C98 -> 580000
B19: =+'Consolidated Sales'!B99 -> b. Net Company Bank Balances | H19: =+'Consolidated Sales'!C99 -> 1168374.5
B20: =+'Consolidated Sales'!B100 -> c. Net Company Wallet Balances | H20: =+'Consolidated Sales'!C100 -> 975000
B21: =+'Consolidated Sales'!B101 -> d. Net Company Contributions | H21: =+'Consolidated Sales'!C101 -> 0
B22: e. Status of Company Contribution | D22: Amount repaid | E22: ='Consolidated Sales'!C90 -> 0 | F22: Amount Outstanding | G22: ='Consolidated Sales'!D90 -> 0
B23: =+'Consolidated Sales'!B102 -> Total Balances Carried Forward | H23: =+'Consolidated Sales'!C102 -> 2723374.5
A26: Department | C26: Cash sales | D26: FDH | E26: MO626 | F26: Airtel Money | G26: Mpamba | H26: Totals
A27: 1 | B27: =+'Consolidated Sales'!B9 -> Domasi Supermarket | C27: =+'Consolidated Sales'!C9 -> 4715460 | D27: =+'Consolidated Sales'!C24 -> 0 | E27: =+'Consolidated Sales'!C22 -> 205650 | F27: =+'Consolidated Sales'!C21 -> 784650 | G27: =+'Consolidated Sales'!C23 -> 74900 | H27: =SUM(C27:G27) -> 5780660
A28: =+A27+1 -> 2 | B28: =+'Consolidated Sales'!B11 -> Stop Over | C28: =+'Consolidated Sales'!C11 -> 3303950 | D28: =+'Consolidated Sales'!C36 -> 0 | E28: =+'Consolidated Sales'!C34 -> 566700 | F28: =+'Consolidated Sales'!C33 -> 1526450 | G28: =+'Consolidated Sales'!C35 -> 223700 | H28: =SUM(C28:G28) -> 5620800
A29: =+A28+1 -> 3 | B29: =+'Consolidated Sales'!B12 -> Nati-Foods | C29: =+'Consolidated Sales'!C12 -> 0 | D29: =+'Consolidated Sales'!C42 -> 0 | E29: =+'Consolidated Sales'!C40 -> 0 | F29: =+'Consolidated Sales'!C39 -> 0 | G29: =+'Consolidated Sales'!C41 -> 0 | H29: =SUM(C29:G29) -> 0
A30: =+A29+1 -> 4 | B30: =+'Consolidated Sales'!B13 -> Braai | C30: =+'Consolidated Sales'!C13 -> 120000 | D30: =+'Consolidated Sales'!C48 -> 0 | E30: =+'Consolidated Sales'!C46 -> 0 | F30: =+'Consolidated Sales'!C45 -> 0 | G30: ='Consolidated Sales'!C47 -> 0 | H30: =SUM(C30:G30) -> 120000
A31: =+A30+1 -> 5 | B31: =+'Consolidated Sales'!B14 -> Pool Table | C31: =+'Consolidated Sales'!C14 -> 236500 | D31: =+'Consolidated Sales'!C54 -> 0 | E31: =+'Consolidated Sales'!C52 -> 0 | F31: =+'Consolidated Sales'!C51 -> 0 | G31: =+'Consolidated Sales'!C53 -> 0 | H31: =SUM(C31:G31) -> 236500
A32: =+A31+1 -> 6 | B32: =+'Consolidated Sales'!B15 -> AirTime | C32: =+'Consolidated Sales'!C15 -> 0 | D32: =+'Consolidated Sales'!C60 -> 0 | E32: =+'Consolidated Sales'!C58 -> 0 | F32: =+'Consolidated Sales'!C57 -> 0 | G32: =+'Consolidated Sales'!C59 -> 0 | H32: =SUM(C32:G32) -> 0
A33: =+A32+1 -> 7 | B33: =+'Consolidated Sales'!B16 -> Student Accommodation | C33: =+'Consolidated Sales'!C16 -> 460000 | D33: =+'Consolidated Sales'!C66 -> 0 | E33: =+'Consolidated Sales'!C64 -> 0 | F33: =+'Consolidated Sales'!C63 -> 0 | G33: =+'Consolidated Sales'!C65 -> 0 | H33: =SUM(C33:G33) -> 460000
B35: Totals | C35: =SUM(C27:C33) -> 8835910 | D35: =SUM(D27:D33) -> 0 | E35: =SUM(E27:E33) -> 772350 | F35: =SUM(F27:F33) -> 2311100 | G35: =SUM(G27:G33) -> 298600 | H35: =SUM(H27:H33) -> 12217960
B37: =+'Consolidated Sales'!B74 -> Total Domasi POS Sales | H37: =+'Consolidated Sales'!C74 -> 0
B39: =+'Consolidated Sales'!B76 -> Domasi Overage/Shortfall | H39: =+H35-H37 -> 12217960
C41: Staus of Debts to Suppliers
A42: Name of Supplier | C42: Amount Due | D42: Cash Payment | E42: Bank Transfer | F42: Wallet Transfer | G42: Total Paid | H42: Total Outstanding
A43: 1 | B43: ='Suppliers Report'!B6 -> Universal Industries | C43: =+'Suppliers Report'!C6 -> 323500.02 | D43: =+'Suppliers Report'!E6 -> 0 | E43: =+'Suppliers Report'!G6 -> 323500.02 | F43: =+'Suppliers Report'!I6 -> 0 | G43: =SUM(D43:F43) -> 323500.02 | H43: =+C43-G43 -> 0
A44: =+A43+1 -> 2 | B44: ='Suppliers Report'!B7 -> Bottled Water | C44: =+'Suppliers Report'!C7 -> 0 | D44: =+'Suppliers Report'!E7 -> 0 | E44: =+'Suppliers Report'!G7 -> 0 | F44: =+'Suppliers Report'!I7 -> 0 | G44: =SUM(D44:F44) -> 0 | H44: =+C44-G44 -> 0
A45: =+A44+1 -> 3 | B45: ='Suppliers Report'!B8 -> Bakeries | C45: =+'Suppliers Report'!C8 -> 104700 | D45: =+'Suppliers Report'!E8 -> 0 | E45: =+'Suppliers Report'!G8 -> 0 | F45: =+'Suppliers Report'!I8 -> 104700 | G45: =SUM(D45:F45) -> 104700 | H45: =+C45-G45 -> 0
A46: =+A45+1 -> 4 | B46: ='Suppliers Report'!B9 -> Suncrest Ltd | C46: =+'Suppliers Report'!C9 -> 0 | D46: =+'Suppliers Report'!E9 -> 0 | E46: =+'Suppliers Report'!G9 -> 0 | F46: =+'Suppliers Report'!I9 -> 0 | G46: =SUM(D46:F46) -> 0 | H46: =+C46-G46 -> 0
A47: =+A46+1 -> 5 | B47: ='Suppliers Report'!B10 -> Cold Chain | C47: =+'Suppliers Report'!C10 -> 0 | D47: =+'Suppliers Report'!E10 -> 0 | E47: =+'Suppliers Report'!G10 -> 0 | F47: =+'Suppliers Report'!I10 -> 0 | G47: =SUM(D47:F47) -> 0 | H47: =+C47-G47 -> 0
A48: =+A47+1 -> 6 | B48: ='Suppliers Report'!B11 -> Unilever | C48: =+'Suppliers Report'!C11 -> 0 | D48: =+'Suppliers Report'!E11 -> 0 | E48: =+'Suppliers Report'!G11 -> 0 | F48: =+'Suppliers Report'!I11 -> 0 | G48: =SUM(D48:F48) -> 0 | H48: =+C48-G48 -> 0
A49: =+A48+1 -> 7 | B49: ='Suppliers Report'!B12 -> Rab Processors | C49: =+'Suppliers Report'!C12 -> 0 | D49: =+'Suppliers Report'!E12 -> 0 | E49: =+'Suppliers Report'!G12 -> 0 | F49: =+'Suppliers Report'!I12 -> 0 | G49: =SUM(D49:F49) -> 0 | H49: =+C49-G49 -> 0
A50: =+A49+1 -> 8 | B50: ='Suppliers Report'!B13 -> Kwacha Fund | C50: =+'Suppliers Report'!C13 -> 3323620.5 | D50: =+'Suppliers Report'!E13 -> 0 | E50: =+'Suppliers Report'!G13 -> 3323620.5 | F50: =+'Suppliers Report'!I13 -> 0 | G50: =SUM(D50:F50) -> 3323620.5 | H50: =+C50-G50 -> 0
A51: =+A50+1 -> 9 | B51: ='Suppliers Report'!B14 -> Ekhaya Farms | C51: =+'Suppliers Report'!C14 -> 0 | D51: =+'Suppliers Report'!E14 -> 0 | E51: =+'Suppliers Report'!G14 -> 0 | F51: =+'Suppliers Report'!I14 -> 0 | G51: =SUM(D51:F51) -> 0 | H51: =+C51-G51 -> 0
A52: =+A51+1 -> 10 | B52: ='Suppliers Report'!B15 -> Central Poultry | C52: =+'Suppliers Report'!C15 -> 0 | D52: =+'Suppliers Report'!E15 -> 0 | E52: =+'Suppliers Report'!G15 -> 0 | F52: =+'Suppliers Report'!I15 -> 0 | G52: =SUM(D52:F52) -> 0 | H52: =+C52-G52 -> 0
A53: =+A52+1 -> 11 | B53: ='Suppliers Report'!B16 -> Licorice Investment (Burundi Shop) | C53: =+'Suppliers Report'!C16 -> 0 | D53: =+'Suppliers Report'!E16 -> 0 | E53: =+'Suppliers Report'!G16 -> 0 | F53: =+'Suppliers Report'!I16 -> 0 | G53: =SUM(D53:F53) -> 0 | H53: =+C53-G53 -> 0
A54: =+A53+1 -> 12 | B54: ='Suppliers Report'!B17 -> Insco Trading | C54: =+'Suppliers Report'!C17 -> 647850 | D54: =+'Suppliers Report'!E17 -> 0 | E54: =+'Suppliers Report'!G17 -> 647850 | F54: =+'Suppliers Report'!I17 -> 0 | G54: =SUM(D54:F54) -> 647850 | H54: =+C54-G54 -> 0
A55: =+A54+1 -> 13 | B55: ='Suppliers Report'!B18 -> Chimwemwe Mafeni Trading | C55: =+'Suppliers Report'!C18 -> 736199.99 | D55: =+'Suppliers Report'!E18 -> 0 | E55: =+'Suppliers Report'!G18 -> 736199.99 | F55: =+'Suppliers Report'!I18 -> 0 | G55: =SUM(D55:F55) -> 736199.99 | H55: =+C55-G55 -> 0
... A61: =+A60+1 -> 19 | B61: ='Suppliers Report'!B24 -> Siera Shop (Burundi Shop) | C61: =+'Suppliers Report'!C24 -> 0 | D61: =+'Suppliers Report'!E24 -> 0 | E61: =+'Suppliers Report'!G24 -> 0 | F61: =+'Suppliers Report'!I24 -> 0 | G61: =SUM(D61:F61) -> 0 | H61: =+C61-G61 -> 0
A62: =+A61+1 -> 20 | B62: =+'Suppliers Report'!B25 -> Other Products | C62: =+'Suppliers Report'!C25 -> 64000 | D62: =+'Suppliers Report'!E25 -> 0 | E62: =+'Suppliers Report'!G25 -> 64000 | F62: =+'Suppliers Report'!I25 -> 0 | G62: =SUM(D62:F62) -> 64000 | H62: =+C62-G62 -> 0
B63: Totals | C63: =SUM(C43:C62) -> 7905085.5 | D63: =SUM(D43:D62) -> 0 | E63: =SUM(E43:E62) -> 7800385.5 | F63: =SUM(F43:F62) -> 104700 | G63: =SUM(G43:G62) -> 7905085.5 | H63: =+SUM(C63-G63) -> 0
A65: Description of Expense | C65: Staus of Debts to Suppliers
C66: Amount Due | D66: Cash Payment | E66: Bank Transfer | F66: Wallet Transfer | G66: Total Paid | H66: Total Outstanding
A67: 1 | B67: =+'Expenses Report'!B8 -> Wages for the Month | C67: =+'Expenses Report'!C8 -> 1260000 | D67: =+'Expenses Report'!E8 -> 0 | E67: =+'Expenses Report'!G8 -> 0 | F67: =+'Expenses Report'!I8 -> 1260000 | G67: =SUM(D67:F67) -> 1260000 | H67: =+C67-G67 -> 0
A68: =+A67+1 -> 2 | B68: =+'Expenses Report'!B9 -> Utility Expenses | C68: =+'Expenses Report'!C9 -> 329500 | D68: =+'Expenses Report'!E9 -> 0 | E68: =+'Expenses Report'!G9 -> 59500 | F68: =+'Expenses Report'!I9 -> 270000 | G68: =SUM(D68:F68) -> 329500 | H68: =+C68-G68 -> 0
A69: =+A68+1 -> 3 | B69: =+'Expenses Report'!B13 -> Expired and Damage Products | C69: =+'Expenses Report'!C13 -> 0 | D69: =+'Expenses Report'!E13 -> 0 | E69: =+'Expenses Report'!G13 -> 0 | F69: =+'Expenses Report'!I13 -> 0 | G69: =SUM(D69:F69) -> 0 | H69: =+C69-G69 -> 0
A70: =+A69+1 -> 4 | B70: =+'Expenses Report'!B14 -> MBS Penalties | C70: =+'Expenses Report'!C14 -> 0 | D70: =+'Expenses Report'!E14 -> 0 | E70: =+'Expenses Report'!G14 -> 0 | F70: =+'Expenses Report'!I14 -> 0 | G70: =SUM(D70:F70) -> 0 | H70: =+C70-G70 -> 0
A71: =+A70+1 -> 5 | B71: =+'Expenses Report'!B15 -> POS Licence and Attendant Costs | C71: =+'Expenses Report'!C15 -> 0 | D71: =+'Expenses Report'!E15 -> 0 | E71: =+'Expenses Report'!G15 -> 0 | F71: =+'Expenses Report'!I15 -> 0 | G71: =SUM(D71:F71) -> 0 | H71: =+C71-G71 -> 0
A72: =+A71+1 -> 6 | B72: =+'Expenses Report'!B16 -> Maintenance Works | C72: =+'Expenses Report'!C16 -> 0 | D72: =+'Expenses Report'!E16 -> 0 | E72: =+'Expenses Report'!G16 -> 0 | F72: =+'Expenses Report'!I16 -> 0 | G72: =SUM(D72:F72) -> 0 | H72: =+C72-G72 -> 0
A73: =+A72+1 -> 7 | B73: =+'Expenses Report'!B17 -> Shop Cleaning Materials | C73: =+'Expenses Report'!C17 -> 0 | D73: =+'Expenses Report'!E17 -> 0 | E73: =+'Expenses Report'!G17 -> 0 | F73: =+'Expenses Report'!I17 -> 0 | G73: =SUM(D73:F73) -> 0 | H73: =+C73-G73 -> 0
A74: =+A73+1 -> 8 | B74: =+'Expenses Report'!B18 -> Casual Labourers | C74: =+'Expenses Report'!C18 -> 0 | D74: =+'Expenses Report'!E18 -> 0 | E74: =+'Expenses Report'!G18 -> 0 | F74: =+'Expenses Report'!I18 -> 0 | G74: =SUM(D74:F74) -> 0 | H74: =+C74-G74 -> 0
A75: =+A74+1 -> 9 | B75: =+'Expenses Report'!B19 -> Braai Condiments | C75: =+'Expenses Report'!C19 -> 0 | D75: =+'Expenses Report'!E19 -> 0 | E75: =+'Expenses Report'!G19 -> 0 | F75: =+'Expenses Report'!I19 -> 0 | G75: =SUM(D75:F75) -> 0 | H75: =+C75-G75 -> 0
A76: =+A75+1 -> 10 | B76: =+'Expenses Report'!B20 -> Other Expenses | C76: =+'Expenses Report'!C20 -> 0 | D76: =+'Expenses Report'!E20 -> 0 | E76: =+'Expenses Report'!G20 -> 0 | F76: =+'Expenses Report'!I20 -> 0 | G76: =SUM(D76:F76) -> 0 | H76: =+C76-G76 -> 0
B77: Totals | C77: =SUM(C67:C76) -> 1589500 | D77: =SUM(D67:D76) -> 0 | E77: =SUM(E67:E76) -> 59500 | F77: =SUM(F67:F76) -> 1530000 | G77: =SUM(G67:G76) -> 1589500 | H77: =+SUM(C77-G77) -> 0
